Workbook

Sheet Read Me
B7: RIDGELINE CONSTRUCTION — Project Template
B9: TABS
B10: Settings · Specifications (descriptions) · Estimate (pricing) · Schedule.
B16: PRICING (cost ▸ markup ▸ ext ▸ tax ▸ total)
B17: Enter My Cost & Markup % in the yellow INTERNAL columns (right). Ext Cost = cost + markup = the
B18: customer's pre-tax price. Those internal columns are outside the print area — never printed.
B20: DESCRIPTIONS & PRINTING
B21: Click a blue cost code to jump to its description on Specifications. Run PrintPacket (Alt+F8) for the
B22: clean packet: Specifications ▸ Estimate ▸ (optional) Schedule.
B24: MACROS (import Ridgeline_Macros.bas: Alt+F11 ▸ File ▸ Import)
B25: AddCostLine · DeleteCostLine · AdoptSuggested · BuildScheduleFromToggles · PrintPacket · ExportScheduleICS · PublishProject.
B27: Prefer no macros? Ask me to publish or export a calendar and I'll do it here.
... B38: Import = the .bas (buttons). Paste into the Schedule sheet = the .txt (auto status behavior).

Sheet Settings
C2: RIDGELINE CONSTRUCTION
C3: Estimate + Schedule - master project template
B7: Project Information
B8: Project / Client | C8: Truesdell SFD
B9: Project Address
B10: Estimate # | C10: EST-1001
B12: Takeoff Quantities (drive the Suggested $ column)
B13: Living space SF | C13: 1800 | D13: Heated area; drives $/sf, flooring, framing, etc.
B14: Garage SF | C14: 400
B15: Covered porch SF | C15: 120
B16: Deck SF | C16: 0
B17: Covered deck SF | C17: 0
B18: Exterior concrete SF | C18: 600
B19: Driveway length (lf) | C19: 40
B20: Foundation wall (lin ft) | C20: 190
B21: Avg foundation wall ht (ft) | C21: 4
B22: Avg ceiling ht (ft) | C22: 9
B23: Exterior wall SF | C23: =C20*C22 -> 1710 | D23: foundation lf x avg ceiling ht
B24: Tile area SF | C24: 400
B25: Remaining floor SF | C25: =MAX(C13-C24,0) -> 1400 | D25: living minus tile (to LVT/laminate)
B26: Kitchen run (lin ft) | C26: 20 | D26: Counter + upper & lower cab length
B27: Windows (qty) | C27: 18
B28: Exterior doors (qty) | C28: 3
B29: Sliding glass doors (qty) | C29: 1
B30: Garage doors (qty) | C30: 1
B31: Total under roof | C31: =C13+C14+C15 -> 2320 | D31: Living + garage + covered porch
B32: Gable area SF | C32: 0 | D32: Added to siding labor/paint & material totals
B33: Assumptions
B34: Sales Tax % | C34: 0.079 | D34: Shown to customer; applied to taxable lines
B35: Default Markup % | C35: 0.2 | D35: INTERNAL margin - drives every non-passthrough line
B36: Project Start Date | C36: 46204 | D36: Schedule + milestones flow from this
B38: Company / Branding
B39: Company | C39: Ridgeline Construction
B40: Mailing | C40: PO Box 516, Longview, WA 98632
B41: Phone | C41: 360-200-1716
B43: Milestone Anchor Dates (auto from start; edit as needed)
B44: Financing | C44: =$C$36 -> 46204
B45: Permitting | C45: =EDATE($C$36,1) -> 46235
B46: Foundation | C46: =EDATE($C$36,2) -> 46266

Sheet Specifications
B1: SPECIFICATIONS
B2: =Settings!C40&" • "&Settings!C41 -> PO Box 516, Longview, WA 98632 • 360-200-1716
B3: ="Project: "&Settings!C8&" Estimate "&Settings!C10 -> Project: Truesdell SFD Estimate EST-1001
A5: Code | B5: Item & Specification
A6: 0100 | B6: General Conditions
A7: 0110 | B7: Permits (Allowance)
B8: Builder will prepare and submit applications for the standard building, mechanical, plumbing, and electrical permits required by the jurisdiction. The permit allowance covers typical permit fees and is billed at actual cost. Not included: planning/design review, SEPA or environmental review, impact, traffic, school, or park fees, and any plan-revision fees — these are billed in addition if required. Owner is responsible for HOA submittals and approvals.
A9: 0120 | B9: Electrical Utility Connections (Allowance)
B10: Electric: connection to public power including transformer and meter base. Service is assumed available at the road adjacent to the property line; trenching, conduit, or boring beyond that point is not included. Gas (if applicable): coordination of the gas service connection to the meter — confirm provider and tap location. Cable / phone / internet: owner coordinates underground installation with Comcast & CenturyLink and arranges activation after taking possession.
A11: 0130 | B11: Excavation (Allowance)
B12: Strip and stockpile existing topsoil on site where practical. Excavate for the foundation to plan bottom per the architectural drawings; spoils are stockpiled for backfill. Unknowns: unsuitable or unstable soils (rock, soft clay, sinkholes, high water table) cannot be priced before excavation and are billed as a change if encountered. Builder backfills with existing soils, rough-grades excess on site, and spreads stockpiled topsoil over disturbed areas. Owner is responsible for seeding, irrigation, fertilizing, and final yard. Not included: import of additional topsoil, off-site haul of excess spoils (except demolition debris), hidden/undisclosed wells, tanks, or pits. Erosion control (silt fence) installed and maintained per permit.
A13: 0140 | B13: Septic system design & install (Allowance)
B14: Design, permitting, and installation of an on-site septic system, assumed to be a pressure-distribution system without pretreatment. Includes tank, pump, drainfield, control panel, and float alarm. Final engineered design and health-department approval are required to confirm system type, size, and cost; pretreatment (if required by the site/soils) is an added cost.
A15: 0150 | B15: Well setup (Allowance)
B16: Well pump, pressure tank, controller/pressure switch, and wiring from the panel to the well. Not included unless noted: well drilling, well house/pump house, and water treatment — coordinate with the well driller. *(Currently $0 — confirm whether the lot is on a well or public water.)*
A17: 0190 | B17: Job site services
B18: General conditions for the duration of the project: temporary toilet maintained on site, dumpsters/debris removal as needed, and ongoing site cleanup. Professional rough and final cleaning, with a detailed final clean before the owner orientation/walkthrough. Temporary power and water as needed during construction.
A19: 0200 | B19: Site Work
A20: 0210 | B20: Footing And Foundation
B21: Form and pour concrete footings and foundation walls per the structural drawings and IRC, including rebar, anchor bolts, and hold-downs. Includes footing/perimeter drain, damp-proofing of below-grade walls, and under-slab vapor barrier where slabs occur. Pricing is based on the current drawings; additional steps, taller walls, or engineered changes are billed as a change.
A22: 0300 | B22: Rough Structure
A23: 0310 | B23: Framing Materials (Allowance)
B24: All lumber and framing materials sized and spaced per the approved construction drawings; lumber to be #2 or better, kiln-dried. Floor sheathing 1‑1/8″ Edge Gold T&G OSB; wall and roof sheathing 7/16″ OSB with H-clips where applicable. Floor framing engineered I-joist or per plan; roof trusses/rafters per plan with vaults as drawn. Includes structural connectors, hangers, hold-downs, and fasteners.
A25: 0320 | B25: Framing Labor
B26: Construct the rough structure per the plans and engineering: floor system, walls, roof structure, and wall/roof sheathing. Includes setting exterior doors and windows, installing structural hardware, and providing solid backing for cabinets, railings, and bath fixtures. Includes shear-nail and framing inspections.
A27: 0400 | B27: Windows & Doors, Exterior
A28: 0410 | B28: Front Door (Allowance)
B29: Entry door per the drawings — allowance covers the door slab/unit, jamb, weatherstripping, and exterior hardware/lockset. Sample: 3/0 × 8/0 knotty alder. Decorative glass or custom sizes may affect the allowance.
A30: 0420 | B30: Other exterior doors
B31: Remaining exterior doors per plan (e.g., man-doors, patio/utility), including jambs, weatherstripping, and hardware. Sliding/French patio doors are itemized under Windows.
A32: 0430 | B32: Garage Doors
B33: Garage door(s) sized and quantity per plan. Spec: Clopay Bridgeport, steel, 2-layer insulated (R-6.3), white — e.g., 18′×8′. Includes track, springs, weather seal, and opener(s) with two remotes and exterior keypad (confirm opener count = door count).
A34: 0440 | B34: Windows (Allowance)
B35: Windows per plan — Milgard vinyl, white standard (other colors available at added cost). Includes Low-E / argon insulated glass, screens, and tempered glass where required by code (near doors, in wet areas, large/low units). Includes sliding glass door(s) per plan. Egress windows sized per code at sleeping rooms.
A36: 0500 | B36: Exterior Finishes
A37: 0510 | B37: Siding Materials
B38: Fiber-cement lap siding (Hardie), 7″ reveal; finger-joint primed cypress trim at corners and windows; primed cypress fascia/barge; cedar tongue-and-groove porch ceilings; LP soffits. Includes weather-resistive barrier (house wrap) and flashing/trim accessories.
A39: 0520 | B39: Siding Labor
B40: Install the weather-resistive barrier, window/door flashing, exterior trim, siding, soffits, and post wraps per the drawings, including all caulking and sealing.
A41: 0530 | B41: Roofing Specifications (Allowance)
B42: 30-year architectural composition shingles over synthetic underlayment, with ice-and-water shield at eaves/valleys, drip edge, step/counter flashing, and ridge ventilation. Pipe boots and roof penetrations flashed and sealed. Color per owner selection.
A43: 0540 | B43: Gutters
B44: 5″ K-style seamless aluminum gutters with downspouts, white standard (colors available; paintable to match trim). Includes hangers and splash blocks; downspouts discharged to daylight or drains per grade.
A45: 0550 | B45: Exterior Masonry
B46: Manufactured (cultured) stone veneer at locations shown — includes lath, scratch coat, stone, and sealing. *(Currently $0 — confirm scope/locations.)*
A47: 0560 | B47: Exterior Painting
B48: Two coats exterior latex on all trim and siding — one color per siding type and one trim color. Exposed natural wood receives one coat semi-transparent sealer. Includes surface prep and caulking touch-up.
A49: 0570 | B49: Concrete Flatwork (Allowance)
B50: Exterior flatwork per plan — driveway apron, front patio, and walkways. Minimum 3.5″ thick, 3,000 psi concrete over a compacted gravel base, with fiber/wire reinforcement, control joints, and a broom finish. Confirm driveway scope (full vs. apron only).
A51: 0600 | B51: HVAC
A52: 0610 | B52: HVAC
B53: Complete heating and cooling system per plan, sized per a Manual J load calc — equipment, supply/return ductwork, registers, and programmable thermostat(s). Includes whole-house ventilation, bath exhaust fans, range-hood and dryer venting to exterior. Confirm system type (heat pump / gas furnace + AC) and number of zones.
A54: 0620 | B54: Fireplace (Allowance)
B55: Gas fireplace insert/unit per plan and owner selection, including direct-vent termination and install. Gas line to the unit is provided under Plumbing. Surround, mantel, and hearth finish are under Interior Masonry (1160).
A56: 0700 | B56: Plumbing
A57: 0710 | B57: Plumbing (Allowance)
B58: Complete plumbing system per code: PVC DWV drainage, PEX water distribution, two frost-proof exterior hose bibs, and fixtures/trim per plan. Includes water heater, pressure-reducing valve, and gas piping to furnace, water heater, fireplace, range, and dryer as applicable. Confirm water heater type (tank vs. tankless) and fixture allowance.
A59: 0800 | B59: Electrical
A60: 0810 | B60: Electrical (Allowance)
B61: Complete electrical per plan: 200A panel and meter, branch wiring, and all 240V circuits for listed appliances. Standard lighting layout — recessed cans in kitchen, dining, master, and covered porches; surface fixtures elsewhere; white tamper-resistant devices and rocker switches; white LED trims on cans. Includes smoke/CO detectors per code, exterior GFCI outlets, and bath/kitchen GFCI/AFCI protection. Surface-mount fixtures are owner-provided (see 0720); installation is included.
A62: 0820 | B62: Electrical Fixtures (Allowance)
B63: Decorative/surface-mount fixtures — ceiling fans, dome lights, chandeliers, pendants, sconces, vanity lights, outdoor lanterns, and security lights — are owner-provided. Builder installs owner-supplied fixtures (labor included under Electrical). Provide fixtures on site before trim-out.
A64: 0900 | B64: Insulation
A65: 0910 | B65: Insulation
B66: R-23 blown-in blanket (BIBS) in exterior walls, R-60 blown insulation at flat ceilings/attic, and R-38 in the crawl space where accessible. Includes air-sealing of penetrations, attic baffles for ventilation, and a vapor retarder per code/climate zone.
A67: 1000 | B67: Interior Wall & Ceiling Finishes
A68: 1010 | B68: Drywall
B69: 1/2″ gypsum board throughout — orange-peel texture on walls, machine brocade on ceilings; square, bullnose, or baby-bullnose corners per selection; 3-way drywall wrap at windows with sill trim. Moisture-resistant board at wet areas and 5/8″ Type-X at the garage/house separation per code.
A70: 1020 | B70: Interior Paint
B71: Prime, then spray and back-roll two finish coats — up to two wall colors, one ceiling color, and one trim color. Includes patch/prep and final touch-up after trim and flooring.
A72: 1030 | B72: Interior Paint Color(s)
B73: Owner color selections recorded here (no separate cost). Final selections due before paint to hold schedule.
A74: 1040 | B74: Bathroom accessories and mirrors (Allowance)
B75: Allowance for bath accessories — toilet-paper holders, towel rings/bars, robe hooks, and vanity mirrors — one set per bathroom. Builder installs owner selections.
A76: 1050 | B76: Masonry - Fireplace facade (Allowance)
B77: Cultured-stone facade on the fireplace wall, including lath, scratch coat, stone, and a wood mantel. *(Currently $0 — confirm scope/height.)*
A78: 1100 | B78: Flooring
A79: 1110 | B79: Flooring Labor (Allowance)
B80: Install owner-selected flooring throughout — includes subfloor prep, underlayment/pad, moisture barrier, transitions, and grout/sealants. Tile wet areas include waterproofing and shower pan/curb where applicable. Quantities: LVT/laminate ~1,400 sf, tile ~400 sf (adjust to final selections).
A81: 1120 | B81: Flooring material (Allowance)
B82: Owner flooring material allowance — final selections (LVT/laminate, tile, carpet) recorded here. Selections due before the flooring phase to hold schedule and lock pricing.
A83: 1200 | B83: Woodwork/Cabinets/Millwork
A84: 1210 | B84: Millwork
B85: Trim package: 5-1/2″ primed FJ baseboard; 3-1/2″ primed FJ door casing (mitered); primed FJ window sill and apron; custom closet shelving and rods. Paint-grade interior doors (6 standard styles, more available); solid-core doors at bathrooms and bedrooms. Includes door hardware (hinges, levers, stops) — finish per selection.
A86: 1220 | B86: Finish Carpentry
B87: Install all interior trim — baseboard, door casing, window surrounds, interior doors and hardware, stair railing/balustrade, and closet shelving/rods. Caulk and fill ready for paint.
A88: 1230 | B88: Cabinet Specifications (Allowance)
B89: Supply and install owner-selected cabinetry per plan — kitchen, baths, and any butler's pantry — including cabinet hardware and interior accessories. Allowance is based on preliminary plans and includes cabinets, hardware, accessories, tax, delivery, and installation. Countertops are itemized separately (1340).
A90: 1240 | B90: Countertops (Allowance)
B91: Hard-surface countertop allowance — kitchen, island, select bath vanities, and laundry; 3 cm quartz/granite slab. Includes templating, fabrication, edge profile, sink/cooktop cutouts, and installation. Tile backsplash included per the line item.
A92: 1300 | B92: Appliances/Equipment
A93: 1310 | B93: Appliance Specifications
B94: Optional appliance allowance — dishwasher, range, and refrigerator — included when required for financing. Builder coordinates delivery and hookup (electrical/plumbing/gas connections by the respective trades). Owner-supplied appliances must be on site before trim-out.
A95: 1320 | B95: Window Coverings (Allowance)
B96: Allowance for window coverings — blinds or shades at windows per owner selection, measured and installed. Motorized or specialty treatments may affect the allowance.
A97: 1500 | B97: Final Grade & Site
A98: 1510 | B98: Final Grade & Landscaping
B99: Final grading and rough landscaping after construction — spread stockpiled topsoil, rough-grade the lot to drain away from the house, and leave the site ready for the owner’s yard. Seeding, sod, irrigation, and plantings are by owner unless noted.

Sheet Estimate
D1: ESTIMATE
D2: =Settings!C40&" • "&Settings!C41 -> PO Box 516, Longview, WA 98632 • 360-200-1716
D3: ="Project: "&Settings!C8&" Estimate "&Settings!C10 -> Project: Truesdell SFD Estimate EST-1001
H4: INTERNAL — not printed
A5: Code | B5: Item / Description | C5: Ext Cost | D5: Sales Tax | E5: Line Total | F5: Category / Item Total | H5: My Cost | I5: Markup | J5: Tax? | K5: Allow? | L5: Excl? | M5: Suggested $ | N5: Logic / basis | O5: Sched?
A6: 0100 | B6: General Conditions | F6: =F7+F9+F12+F17+F21+F23 -> 0
A7: 0110 | B7: ="Permits"&IF($K7="Y"," (Allowance)","") -> Permits (Allowance) | F7: =SUM(E8) -> 0 | K7: Y | O7: Y
B8: Bldg. Permit | C8: =IF($L8="Y",0,H8*(1+I8)) -> 0 | D8: =IF(J8="Y",C8*Settings!$C$34,0) -> 0 | E8: =C8+D8 -> 0 | H8: 0 | I8: 0 | J8: N | L8: N | M8: 8000 | N8: Prior project basis / lump sum - confirm with sub
A9: 0120 | B9: ="Electrical Utility Connections"&IF($K9="Y"," (Allowance)","") -> Electrical Utility Connections (Allowance) | F9: =SUM(E10:E11) -> 0 | K9: Y | O9: Y
B10: PUD Quoted install | C10: =IF($L10="Y",0,H10*(1+I10)) -> 0 | D10: =IF(J10="Y",C10*Settings!$C$34,0) -> 0 | E10: =C10+D10 -> 0 | H10: 0 | I10: 0 | J10: N | L10: N | M10: 7500 | N10: Prior project basis / lump sum - confirm with sub
B11: Gas service connection | C11: =IF($L11="Y",0,H11*(1+I11)) -> 0 | D11: =IF(J11="Y",C11*Settings!$C$34,0) -> 0 | E11: =C11+D11 -> 0 | H11: 0 | I11: 0 | J11: N | L11: N | M11: =2500 -> 2500 | N11: Allowance - gas tap/meter; confirm provider
A12: 0130 | B12: ="Excavation"&IF($K12="Y"," (Allowance)","") -> Excavation (Allowance) | F12: =SUM(E13:E16) -> 0 | K12: Y | O12: Y
B13: Excavation | C13: =IF($L13="Y",0,H13*(1+I13)) -> 0 | D13: =IF(J13="Y",C13*Settings!$C$34,0) -> 0 | E13: =C13+D13 -> 0 | H13: 0 | I13: =Settings!$C$35 -> 0.2 | J13: Y | L13: N | M13: 4095 | N13: Prior project basis / lump sum - confirm with sub
B14: Excavation - utilities & contingency | C14: =IF($L14="Y",0,H14*(1+I14)) -> 0 | D14: =IF(J14="Y",C14*Settings!$C$34,0) -> 0 | E14: =C14+D14 -> 0 | H14: 0 | I14: =Settings!$C$35 -> 0.2 | J14: Y | L14: N | M14: 3510 | N14: Prior project basis / lump sum - confirm with sub
B15: Backfill - Labor | C15: =IF($L15="Y",0,H15*(1+I15)) -> 0 | D15: =IF(J15="Y",C15*Settings!$C$34,0) -> 0 | E15: =C15+D15 -> 0 | H15: 0 | I15: =Settings!$C$35 -> 0.2 | J15: Y | L15: N | M15: 5850 | N15: Prior project basis / lump sum - confirm with sub
B16: Backfill - Gravel and fill | C16: =IF($L16="Y",0,H16*(1+I16)) -> 0 | D16: =IF(J16="Y",C16*Settings!$C$34,0) -> 0 | E16: =C16+D16 -> 0 | H16: 0 | I16: =Settings!$C$35 -> 0.2 | J16: Y | L16: N | M16: 5850 | N16: Prior project basis / lump sum - confirm with sub
A17: 0140 | B17: ="Septic system design & install"&IF($K17="Y"," (Allowance)","") -> Septic system design & install (Allowance) | F17: =SUM(E18:E20) -> 0 | K17: Y | O17: Y
B18: Septic system install - Pressure distribution | C18: =IF($L18="Y",0,H18*(1+I18)) -> 0 | D18: =IF(J18="Y",C18*Settings!$C$34,0) -> 0 | E18: =C18+D18 -> 0 | H18: 0 | I18: =Settings!$C$35 -> 0.2 | J18: Y | L18: N | M18: 14040 | N18: Prior project basis / lump sum - confirm with sub
B19: Septic design | C19: =IF($L19="Y",0,H19*(1+I19)) -> 0 | D19: =IF(J19="Y",C19*Settings!$C$34,0) -> 0 | E19: =C19+D19 -> 0 | H19: 0 | I19: =Settings!$C$35 -> 0.2 | J19: Y | L19: N | M19: 1404 | N19: Prior project basis / lump sum - confirm with sub
B20: Septic permit | C20: =IF($L20="Y",0,H20*(1+I20)) -> 0 | D20: =IF(J20="Y",C20*Settings!$C$34,0) -> 0 | E20: =C20+D20 -> 0 | H20: 0 | I20: =Settings!$C$35 -> 0.2 | J20: Y | L20: N | M20: 1170 | N20: Prior project basis / lump sum - confirm with sub
A21: 0150 | B21: ="Well setup"&IF($K21="Y"," (Allowance)","") -> Well setup (Allowance) | F21: =SUM(E22) -> 0 | K21: Y | O21: N
B22: Well | C22: =IF($L22="Y",0,H22*(1+I22)) -> 0 | D22: =IF(J22="Y",C22*Settings!$C$34,0) -> 0 | E22: =C22+D22 -> 0 | H22: 0 | I22: 0 | J22: Y | L22: N | M22: 0 | N22: Owner-provided / allowance - set as needed
A23: 0190 | B23: ="Job site services"&IF($K23="Y"," (Allowance)","") -> Job site services | F23: =SUM(E24:E26) -> 0 | K23: N | O23: N
B24: Home Cleaning @ Final | C24: =IF($L24="Y",0,H24*(1+I24)) -> 0 | D24: =IF(J24="Y",C24*Settings!$C$34,0) -> 0 | E24: =C24+D24 -> 0 | H24: 0 | I24: =Settings!$C$35 -> 0.2 | J24: Y | L24: N | M24: 2925 | N24: Prior project basis / lump sum - confirm with sub
B25: Portable toilet | C25: =IF($L25="Y",0,H25*(1+I25)) -> 0 | D25: =IF(J25="Y",C25*Settings!$C$34,0) -> 0 | E25: =C25+D25 -> 0 | H25: 0 | I25: =Settings!$C$35 -> 0.2 | J25: Y | L25: N | M25: 1895.4 | N25: Prior project basis / lump sum - confirm with sub
B26: Dumping fees / site cleanup | C26: =IF($L26="Y",0,H26*(1+I26)) -> 0 | D26: =IF(J26="Y",C26*Settings!$C$34,0) -> 0 | E26: =C26+D26 -> 0 | H26: 0 | I26: =Settings!$C$35 -> 0.2 | J26: Y | L26: N | M26: 5850 | N26: Prior project basis / lump sum - confirm with sub
A27: 0200 | B27: Site Work | F27: =F28 -> 0
A28: 0210 | B28: ="Footing And Foundation"&IF($K28="Y"," (Allowance)","") -> Footing And Foundation | F28: =SUM(E29:E30) -> 0 | K28: N | O28: Y
B29: Foundation Labor/concrete | C29: =IF($L29="Y",0,H29*(1+I29)) -> 0 | D29: =IF(J29="Y",C29*Settings!$C$34,0) -> 0 | E29: =C29+D29 -> 0 | H29: 0 | I29: =Settings!$C$35 -> 0.2 | J29: Y | L29: N | M29: =CEILING(Settings!$C$20*Settings!$C$21*0.667/27,5)*440 -> 8800 | N29: Foundation CY (perim x ht x 0.67 /27, round up 5 yd) x $440/yd
B30: Pump Truck | C30: =IF($L30="Y",0,H30*(1+I30)) -> 0 | D30: =IF(J30="Y",C30*Settings!$C$34,0) -> 0 | E30: =C30+D30 -> 0 | H30: 0 | I30: =Settings!$C$35 -> 0.2 | J30: Y | L30: N | M30: 1872 | N30: Prior project basis / lump sum - confirm with sub
A31: 0300 | B31: Rough Structure | F31: =F32+F38 -> 0
A32: 0310 | B32: ="Framing Materials"&IF($K32="Y"," (Allowance)","") -> Framing Materials (Allowance) | F32: =SUM(E33:E37) -> 0 | K32: Y | O32: Y
B33: Materials - 1st floor - 9.5" TJI | C33: =IF($L33="Y",0,H33*(1+I33)) -> 0 | D33: =IF(J33="Y",C33*Settings!$C$34,0) -> 0 | E33: =C33+D33 -> 0 | H33: 0 | I33: =Settings!$C$35 -> 0.2 | J33: Y | L33: N | M33: ='Material Estimate'!$H$19 -> 9200.8976 | N33: From Material Takeoff: foundation & floor framing material
B34: Exterior Walls 9' PLT HT | C34: =IF($L34="Y",0,H34*(1+I34)) -> 0 | D34: =IF(J34="Y",C34*Settings!$C$34,0) -> 0 | E34: =C34+D34 -> 0 | H34: 0 | I34: =Settings!$C$35 -> 0.2 | J34: Y | L34: N | M34: ='Material Estimate'!$H$29 -> 3705.6653 | N34: From Material Takeoff: wall framing material
B35: Materials - Roof pack | C35: =IF($L35="Y",0,H35*(1+I35)) -> 0 | D35: =IF(J35="Y",C35*Settings!$C$34,0) -> 0 | E35: =C35+D35 -> 0 | H35: 0 | I35: =Settings!$C$35 -> 0.2 | J35: Y | L35: N | M35: ='Material Estimate'!$H$40 -> 4054.0079 | N35: From Material Takeoff: roof framing & trim material
B36: Materials - Trusses | C36: =IF($L36="Y",0,H36*(1+I36)) -> 0 | D36: =IF(J36="Y",C36*Settings!$C$34,0) -> 0 | E36: =C36+D36 -> 0 | H36: 0 | I36: =Settings!$C$35 -> 0.2 | J36: Y | L36: N | M36: 7020 | N36: Prior project basis / lump sum - confirm with sub
B37: Beams - hardware - Posts | C37: =IF($L37="Y",0,H37*(1+I37)) -> 0 | D37: =IF(J37="Y",C37*Settings!$C$34,0) -> 0 | E37: =C37+D37 -> 0 | H37: 0 | I37: =Settings!$C$35 -> 0.2 | J37: Y | L37: N | M37: 1404 | N37: Prior project basis / lump sum - confirm with sub
A38: 0320 | B38: ="Framing Labor"&IF($K38="Y"," (Allowance)","") -> Framing Labor | F38: =SUM(E39:E40) -> 0 | K38: N | O38: Y
B39: Framing labor - living space | C39: =IF($L39="Y",0,H39*(1+I39)) -> 0 | D39: =IF(J39="Y",C39*Settings!$C$34,0) -> 0 | E39: =C39+D39 -> 0 | H39: 0 | I39: =Settings!$C$35 -> 0.2 | J39: Y | L39: N | M39: =Settings!$C$13*12 -> 21600 | N39: Living SF x $12/sf framing labor
B40: Framing labor - Covered porch/Garage | C40: =IF($L40="Y",0,H40*(1+I40)) -> 0 | D40: =IF(J40="Y",C40*Settings!$C$34,0) -> 0 | E40: =C40+D40 -> 0 | H40: 0 | I40: =Settings!$C$35 -> 0.2 | J40: Y | L40: N | M40: =(Settings!$C$14+Settings!$C$15)*9 -> 4680 | N40: (Garage+porch) SF x $9/sf framing labor
A41: 0400 | B41: Windows & Doors, Exterior | F41: =F42+F44+F46+F49 -> 0
A42: 0410 | B42: ="Front Door"&IF($K42="Y"," (Allowance)","") -> Front Door (Allowance) | F42: =SUM(E43) -> 0 | K42: Y | O42: Y
B43: Front door 3080 - Knotty Alder | C43: =IF($L43="Y",0,H43*(1+I43)) -> 0 | D43: =IF(J43="Y",C43*Settings!$C$34,0) -> 0 | E43: =C43+D43 -> 0 | H43: 0 | I43: =Settings!$C$35 -> 0.2 | J43: Y | L43: N | M43: 5265 | N43: Prior project basis / lump sum - confirm with sub
A44: 0420 | B44: ="Other exterior doors"&IF($K44="Y"," (Allowance)","") -> Other exterior doors | F44: =SUM(E45) -> 0 | K44: N | O44: Y
B45: Exterior doors | C45: =IF($L45="Y",0,H45*(1+I45)) -> 0 | D45: =IF(J45="Y",C45*Settings!$C$34,0) -> 0 | E45: =C45+D45 -> 0 | H45: 0 | I45: =Settings!$C$35 -> 0.2 | J45: Y | L45: N | M45: =Settings!$C$28*650 -> 1950 | N45: Ext doors qty x $650 ea
A46: 0430 | B46: ="Garage Doors"&IF($K46="Y"," (Allowance)","") -> Garage Doors | F46: =SUM(E47:E48) -> 0 | K46: N | O46: Y
B47: 18*8 | C47: =IF($L47="Y",0,H47*(1+I47)) -> 0 | D47: =IF(J47="Y",C47*Settings!$C$34,0) -> 0 | E47: =C47+D47 -> 0 | H47: 0 | I47: =Settings!$C$35 -> 0.2 | J47: Y | L47: N | M47: =Settings!$C$30*1500 -> 1500 | N47: Garage doors qty x $1,500 ea
B48: Garage Door openers | C48: =IF($L48="Y",0,H48*(1+I48)) -> 0 | D48: =IF(J48="Y",C48*Settings!$C$34,0) -> 0 | E48: =C48+D48 -> 0 | H48: 0 | I48: =Settings!$C$35 -> 0.2 | J48: Y | L48: N | M48: =Settings!$C$30*450 -> 450 | N48: Garage doors qty x $450 opener ea
A49: 0440 | B49: ="Windows"&IF($K49="Y"," (Allowance)","") -> Windows (Allowance) | F49: =SUM(E50:E51) -> 0 | K49: Y | O49: Y
B50: Windows | C50: =IF($L50="Y",0,H50*(1+I50)) -> 0 | D50: =IF(J50="Y",C50*Settings!$C$34,0) -> 0 | E50: =C50+D50 -> 0 | H50: 0 | I50: =Settings!$C$35 -> 0.2 | J50: Y | L50: N | M50: =Settings!$C$27*380 -> 6840 | N50: Windows qty x $380 ea
B51: SGD (sliding glass door) | C51: =IF($L51="Y",0,H51*(1+I51)) -> 0 | D51: =IF(J51="Y",C51*Settings!$C$34,0) -> 0 | E51: =C51+D51 -> 0 | H51: 0 | I51: =Settings!$C$35 -> 0.2 | J51: Y | L51: N | M51: =Settings!$C$29*2200 -> 2200 | N51: Sliding doors qty x $2,200 ea
A52: 0500 | B52: Exterior Finishes | F52: =F53+F55+F59+F62+F64+F66+F68 -> 0
A53: 0510 | B53: ="Siding Materials"&IF($K53="Y"," (Allowance)","") -> Siding Materials | F53: =SUM(E54) -> 0 | K53: N | O53: Y
B54: Siding materials package | C54: =IF($L54="Y",0,H54*(1+I54)) -> 0 | D54: =IF(J54="Y",C54*Settings!$C$34,0) -> 0 | E54: =C54+D54 -> 0 | H54: 0 | I54: =Settings!$C$35 -> 0.2 | J54: Y | L54: N | M54: ='Material Estimate'!$H$57+Settings!$C$32*5.5 -> 5341.4518 | N54: Material Takeoff siding + gable (Settings) x $5.50/sf
A55: 0520 | B55: ="Siding Labor"&IF($K55="Y"," (Allowance)","") -> Siding Labor | F55: =SUM(E56:E58) -> 0 | K55: N | O55: Y
B56: Siding labor - 7" horizontal | C56: =IF($L56="Y",0,H56*(1+I56)) -> 0 | D56: =IF(J56="Y",C56*Settings!$C$34,0) -> 0 | E56: =C56+D56 -> 0 | H56: 0 | I56: =Settings!$C$35 -> 0.2 | J56: Y | L56: N | M56: =(Settings!$C$23+Settings!$C$32)*4 -> 6840 | N56: Exterior wall + gable SF x $4/sf siding labor
B57: Siding labor - Soffits | C57: =IF($L57="Y",0,H57*(1+I57)) -> 0 | D57: =IF(J57="Y",C57*Settings!$C$34,0) -> 0 | E57: =C57+D57 -> 0 | H57: 0 | I57: =Settings!$C$35 -> 0.2 | J57: Y | L57: N | M57: 2808 | N57: Prior project basis / lump sum - confirm with sub
B58: Siding labor - Post wraps | C58: =IF($L58="Y",0,H58*(1+I58)) -> 0 | D58: =IF(J58="Y",C58*Settings!$C$34,0) -> 0 | E58: =C58+D58 -> 0 | H58: 0 | I58: =Settings!$C$35 -> 0.2 | J58: Y | L58: N | M58: 1404 | N58: Prior project basis / lump sum - confirm with sub
A59: 0530 | B59: ="Roofing Specifications"&IF($K59="Y"," (Allowance)","") -> Roofing Specifications (Allowance) | F59: =SUM(E60:E61) -> 0 | K59: Y | O59: Y
B60: Roofing Material | C60: =IF($L60="Y",0,H60*(1+I60)) -> 0 | D60: =IF(J60="Y",C60*Settings!$C$34,0) -> 0 | E60: =C60+D60 -> 0 | H60: 0 | I60: =Settings!$C$35 -> 0.2 | J60: Y | L60: N | M60: =(Settings!$C$13+Settings!$C$14+Settings!$C$15)*1.4/100*425 -> 13804 | N60: Roof area (footprint x1.4) /100 sq x $425/sq material
B61: Roofing Labor | C61: =IF($L61="Y",0,H61*(1+I61)) -> 0 | D61: =IF(J61="Y",C61*Settings!$C$34,0) -> 0 | E61: =C61+D61 -> 0 | H61: 0 | I61: =Settings!$C$35 -> 0.2 | J61: Y | L61: N | M61: =(Settings!$C$13+Settings!$C$14+Settings!$C$15)*1.4/100*250 -> 8120 | N61: Roof squares (footprint x1.4) x $250/sq labor
A62: 0540 | B62: ="Gutters"&IF($K62="Y"," (Allowance)","") -> Gutters | F62: =SUM(E63) -> 0 | K62: N | O62: Y
B63: Gutters | C63: =IF($L63="Y",0,H63*(1+I63)) -> 0 | D63: =IF(J63="Y",C63*Settings!$C$34,0) -> 0 | E63: =C63+D63 -> 0 | H63: 0 | I63: =Settings!$C$35 -> 0.2 | J63: Y | L63: N | M63: =Settings!$C$20*6 -> 1140 | N63: Eave length ~ perimeter x $6/lf
A64: 0550 | B64: ="Exterior Masonry"&IF($K64="Y"," (Allowance)","") -> Exterior Masonry | F64: =SUM(E65) -> 0 | K64: N | O64: N
B65: Cultured stone | C65: =IF($L65="Y",0,H65*(1+I65)) -> 0 | D65: =IF(J65="Y",C65*Settings!$C$34,0) -> 0 | E65: =C65+D65 -> 0 | H65: 0 | I65: =Settings!$C$35 -> 0.2 | J65: Y | L65: N | M65: 0 | N65: Owner-provided / allowance - set as needed
A66: 0560 | B66: ="Exterior Painting"&IF($K66="Y"," (Allowance)","") -> Exterior Painting | F66: =SUM(E67) -> 0 | K66: N | O66: Y
B67: Exterior Painting Material & Labor | C67: =IF($L67="Y",0,H67*(1+I67)) -> 0 | D67: =IF(J67="Y",C67*Settings!$C$34,0) -> 0 | E67: =C67+D67 -> 0 | H67: 0 | I67: =Settings!$C$35 -> 0.2 | J67: Y | L67: N | M67: =(Settings!$C$23+Settings!$C$32)*1.6 -> 2736 | N67: Exterior wall + gable SF x $1.60/sf paint
A68: 0570 | B68: ="Concrete Flatwork"&IF($K68="Y"," (Allowance)","") -> Concrete Flatwork (Allowance) | F68: =SUM(E69:E71) -> 0 | K68: Y | O68: Y
B69: Driveway | C69: =IF($L69="Y",0,H69*(1+I69)) -> 0 | D69: =IF(J69="Y",C69*Settings!$C$34,0) -> 0 | E69: =C69+D69 -> 0 | H69: 0 | I69: =Settings!$C$35 -> 0.2 | J69: Y | L69: N | M69: =Settings!$C$19*11*7 -> 3080 | N69: Driveway length x 11 ft x $7/sf
B70: Exterior concrete patio & walkway | C70: =IF($L70="Y",0,H70*(1+I70)) -> 0 | D70: =IF(J70="Y",C70*Settings!$C$34,0) -> 0 | E70: =C70+D70 -> 0 | H70: 0 | I70: =Settings!$C$35 -> 0.2 | J70: Y | L70: N | M70: =Settings!$C$18*6 -> 3600 | N70: Exterior concrete SF x $6/sf
B71: Garage slab | C71: =IF($L71="Y",0,H71*(1+I71)) -> 0 | D71: =IF(J71="Y",C71*Settings!$C$34,0) -> 0 | E71: =C71+D71 -> 0 | H71: 0 | I71: =Settings!$C$35 -> 0.2 | J71: Y | L71: N | M71: =Settings!$C$14*6 -> 2400 | N71: Garage SF x $6/sf slab
A72: 0600 | B72: HVAC | F72: =F73+F75 -> 0
A73: 0610 | B73: ="HVAC"&IF($K73="Y"," (Allowance)","") -> HVAC | F73: =SUM(E74) -> 0 | K73: N | O73: Y
B74: HVAC system | C74: =IF($L74="Y",0,H74*(1+I74)) -> 0 | D74: =IF(J74="Y",C74*Settings!$C$34,0) -> 0 | E74: =C74+D74 -> 0 | H74: 0 | I74: =Settings!$C$35 -> 0.2 | J74: Y | L74: N | M74: =Settings!$C$13*9.5 -> 17100 | N74: Living SF x $9.50/sf complete HVAC
A75: 0620 | B75: ="Fireplace"&IF($K75="Y"," (Allowance)","") -> Fireplace (Allowance) | F75: =SUM(E76) -> 0 | K75: Y | O75: Y
B76: Fireplace - install only + stove pipe parts | C76: =IF($L76="Y",0,H76*(1+I76)) -> 0 | D76: =IF(J76="Y",C76*Settings!$C$34,0) -> 0 | E76: =C76+D76 -> 0 | H76: 0 | I76: =Settings!$C$35 -> 0.2 | J76: Y | L76: N | M76: 5850 | N76: Prior project basis / lump sum - confirm with sub
A77: 0700 | B77: Plumbing | F77: =F78 -> 0
A78: 0710 | B78: ="Plumbing"&IF($K78="Y"," (Allowance)","") -> Plumbing (Allowance) | F78: =SUM(E79) -> 0 | K78: Y | O78: Y
B79: Plumbing quote complete | C79: =IF($L79="Y",0,H79*(1+I79)) -> 0 | D79: =IF(J79="Y",C79*Settings!$C$34,0) -> 0 | E79: =C79+D79 -> 0 | H79: 0 | I79: =Settings!$C$35 -> 0.2 | J79: Y | L79: N | M79: =Settings!$C$13*9.75 -> 17550 | N79: Living SF x $9.75/sf (or by fixture count)
A80: 0800 | B80: Electrical | F80: =F81+F85 -> 0
A81: 0810 | B81: ="Electrical"&IF($K81="Y"," (Allowance)","") -> Electrical (Allowance) | F81: =SUM(E82:E84) -> 0 | K81: Y | O81: Y
B82: Electrical System | C82: =IF($L82="Y",0,H82*(1+I82)) -> 0 | D82: =IF(J82="Y",C82*Settings!$C$34,0) -> 0 | E82: =C82+D82 -> 0 | H82: 0 | I82: =Settings!$C$35 -> 0.2 | J82: Y | L82: N | M82: =Settings!$C$13*11.7 -> 21060 | N82: Living SF x $11.70/sf electrical
B83: Low-voltage rough-in (data / cable / TV) | C83: =IF($L83="Y",0,H83*(1+I83)) -> 0 | D83: =IF(J83="Y",C83*Settings!$C$34,0) -> 0 | E83: =C83+D83 -> 0 | H83: 0 | I83: =Settings!$C$35 -> 0.2 | J83: Y | L83: N | M83: =1500 -> 1500 | N83: Allowance - data/cable/TV drops
B84: EV charger circuit (rough-in) | C84: =IF($L84="Y",0,H84*(1+I84)) -> 0 | D84: =IF(J84="Y",C84*Settings!$C$34,0) -> 0 | E84: =C84+D84 -> 0 | H84: 0 | I84: =Settings!$C$35 -> 0.2 | J84: Y | L84: N | M84: =900 -> 900 | N84: Allowance - 240V EV rough-in
A85: 0820 | B85: ="Electrical Fixtures"&IF($K85="Y"," (Allowance)","") -> Electrical Fixtures (Allowance) | F85: =SUM(E86) -> 0 | K85: Y | O85: N
B86: Fixture allowance | C86: =IF($L86="Y",0,H86*(1+I86)) -> 0 | D86: =IF(J86="Y",C86*Settings!$C$34,0) -> 0 | E86: =C86+D86 -> 0 | H86: 0 | I86: 0 | J86: Y | L86: N | M86: 0 | N86: Owner-provided / allowance - set as needed
A87: 0900 | B87: Insulation | F87: =F88 -> 0
A88: 0910 | B88: ="Insulation"&IF($K88="Y"," (Allowance)","") -> Insulation | F88: =SUM(E89) -> 0 | K88: N | O88: Y
B89: Insulation | C89: =IF($L89="Y",0,H89*(1+I89)) -> 0 | D89: =IF(J89="Y",C89*Settings!$C$34,0) -> 0 | E89: =C89+D89 -> 0 | H89: 0 | I89: =Settings!$C$35 -> 0.2 | J89: Y | L89: N | M89: =Settings!$C$23*2.25+Settings!$C$13*1.5 -> 6547.5 | N89: Walls SFx$2.25 + ceiling(living SF)x$1.50
A90: 1000 | B90: Interior Wall & Ceiling Finishes | F90: =F91+F93+F95+F96+F99 -> 0
A91: 1010 | B91: ="Drywall"&IF($K91="Y"," (Allowance)","") -> Drywall | F91: =SUM(E92) -> 0 | K91: N | O91: Y
B92: Drywall, hang, tape, texture | C92: =IF($L92="Y",0,H92*(1+I92)) -> 0 | D92: =IF(J92="Y",C92*Settings!$C$34,0) -> 0 | E92: =C92+D92 -> 0 | H92: 0 | I92: =Settings!$C$35 -> 0.2 | J92: Y | L92: N | M92: =Settings!$C$13*3.5*2.1 -> 13230 | N92: Living SF x 3.5 (drywall area factor) x $2.10/sf
A93: 1020 | B93: ="Interior Paint"&IF($K93="Y"," (Allowance)","") -> Interior Paint | F93: =SUM(E94) -> 0 | K93: N | O93: Y
B94: Interior wall/ceiling/trim painting | C94: =IF($L94="Y",0,H94*(1+I94)) -> 0 | D94: =IF(J94="Y",C94*Settings!$C$34,0) -> 0 | E94: =C94+D94 -> 0 | H94: 0 | I94: =Settings!$C$35 -> 0.2 | J94: Y | L94: N | M94: =Settings!$C$13*3.5*1.1 -> 6930 | N94: Drywall area (livingx3.5) x $1.10/sf
A95: 1030 | B95: ="Interior Paint Color(s)"&IF($K95="Y"," (Allowance)","") -> Interior Paint Color(s) | F95: 0 | K95: N | O95: N
A96: 1040 | B96: ="Bathroom accessories and mirrors"&IF($K96="Y"," (Allowance)","") -> Bathroom accessories and mirrors (Allowance) | F96: =SUM(E97:E98) -> 0 | K96: Y | O96: Y
B97: Bathroom mirrors | C97: =IF($L97="Y",0,H97*(1+I97)) -> 0 | D97: =IF(J97="Y",C97*Settings!$C$34,0) -> 0 | E97: =C97+D97 -> 0 | H97: 0 | I97: =Settings!$C$35 -> 0.2 | J97: Y | L97: N | M97: 0 | N97: Owner-provided / allowance - set as needed
B98: TP holders, towel rod, towel ring per bath | C98: =IF($L98="Y",0,H98*(1+I98)) -> 0 | D98: =IF(J98="Y",C98*Settings!$C$34,0) -> 0 | E98: =C98+D98 -> 0 | H98: 0 | I98: =Settings!$C$35 -> 0.2 | J98: Y | L98: N | M98: 0 | N98: Owner-provided / allowance - set as needed
A99: 1050 | B99: ="Masonry - Fireplace facade"&IF($K99="Y"," (Allowance)","") -> Masonry - Fireplace facade (Allowance) | F99: =SUM(E100:E101) -> 0 | K99: Y | O99: N
B100: Stone | C100: =IF($L100="Y",0,H100*(1+I100)) -> 0 | D100: =IF(J100="Y",C100*Settings!$C$34,0) -> 0 | E100: =C100+D100 -> 0 | H100: 0 | I100: =Settings!$C$35 -> 0.2 | J100: Y | L100: N | M100: 0 | N100: Owner-provided / allowance - set as needed
...

Sheet Allowances
D1: ALLOWANCES
D2: =Settings!C40&" • "&Settings!C41 -> PO Box 516, Longview, WA 98632 • 360-200-1716
D3: ="Project: "&Settings!C8&" Estimate "&Settings!C10 -> Project: Truesdell SFD Estimate EST-1001
A4: Items toggled Allow? = Y on the Estimate. Enter the actual selected cost to track budget vs. spend.
A5: Code | B5: Category | C5: Item | D5: Allow? | E5: Allowance $ | F5: Actual $ | G5: Variance | H5: Notes
A6: =Estimate!A7 -> 0110 | B6: General Conditions | C6: Permits | D6: =Estimate!K7 -> Y | E6: =Estimate!F7 -> 0 | G6: =IF(F6="","",E6-F6)
A7: =Estimate!A9 -> 0120 | B7: General Conditions | C7: Electrical Utility Connections | D7: =Estimate!K9 -> Y | E7: =Estimate!F9 -> 0 | G7: =IF(F7="","",E7-F7)
A8: =Estimate!A12 -> 0130 | B8: General Conditions | C8: Excavation | D8: =Estimate!K12 -> Y | E8: =Estimate!F12 -> 0 | G8: =IF(F8="","",E8-F8)
A9: =Estimate!A17 -> 0140 | B9: General Conditions | C9: Septic system design & install | D9: =Estimate!K17 -> Y | E9: =Estimate!F17 -> 0 | G9: =IF(F9="","",E9-F9)
A10: =Estimate!A21 -> 0150 | B10: General Conditions | C10: Well setup | D10: =Estimate!K21 -> Y | E10: =Estimate!F21 -> 0 | G10: =IF(F10="","",E10-F10)
A11: =Estimate!A23 -> 0190 | B11: General Conditions | C11: Job site services | D11: =Estimate!K23 -> N | E11: =Estimate!F23 -> 0 | G11: =IF(F11="","",E11-F11)
A12: =Estimate!A28 -> 0210 | B12: Site Work | C12: Footing And Foundation | D12: =Estimate!K28 -> N | E12: =Estimate!F28 -> 0 | G12: =IF(F12="","",E12-F12)
A13: =Estimate!A32 -> 0310 | B13: Rough Structure | C13: Framing Materials | D13: =Estimate!K32 -> Y | E13: =Estimate!F32 -> 0 | G13: =IF(F13="","",E13-F13)
A14: =Estimate!A38 -> 0320 | B14: Rough Structure | C14: Framing Labor | D14: =Estimate!K38 -> N | E14: =Estimate!F38 -> 0 | G14: =IF(F14="","",E14-F14)
A15: =Estimate!A42 -> 0410 | B15: Windows & Doors, Exterior | C15: Front Door | D15: =Estimate!K42 -> Y | E15: =Estimate!F42 -> 0 | G15: =IF(F15="","",E15-F15)
A16: =Estimate!A44 -> 0420 | B16: Windows & Doors, Exterior | C16: Other exterior doors | D16: =Estimate!K44 -> N | E16: =Estimate!F44 -> 0 | G16: =IF(F16="","",E16-F16)
A17: =Estimate!A46 -> 0430 | B17: Windows & Doors, Exterior | C17: Garage Doors | D17: =Estimate!K46 -> N | E17: =Estimate!F46 -> 0 | G17: =IF(F17="","",E17-F17)
A18: =Estimate!A49 -> 0440 | B18: Windows & Doors, Exterior | C18: Windows | D18: =Estimate!K49 -> Y | E18: =Estimate!F49 -> 0 | G18: =IF(F18="","",E18-F18)
A19: =Estimate!A53 -> 0510 | B19: Exterior Finishes | C19: Siding Materials | D19: =Estimate!K53 -> N | E19: =Estimate!F53 -> 0 | G19: =IF(F19="","",E19-F19)
A20: =Estimate!A55 -> 0520 | B20: Exterior Finishes | C20: Siding Labor | D20: =Estimate!K55 -> N | E20: =Estimate!F55 -> 0 | G20: =IF(F20="","",E20-F20)
A21: =Estimate!A59 -> 0530 | B21: Exterior Finishes | C21: Roofing Specifications | D21: =Estimate!K59 -> Y | E21: =Estimate!F59 -> 0 | G21: =IF(F21="","",E21-F21)
A22: =Estimate!A62 -> 0540 | B22: Exterior Finishes | C22: Gutters | D22: =Estimate!K62 -> N | E22: =Estimate!F62 -> 0 | G22: =IF(F22="","",E22-F22)
A23: =Estimate!A64 -> 0550 | B23: Exterior Finishes | C23: Exterior Masonry | D23: =Estimate!K64 -> N | E23: =Estimate!F64 -> 0 | G23: =IF(F23="","",E23-F23)
A24: =Estimate!A66 -> 0560 | B24: Exterior Finishes | C24: Exterior Painting | D24: =Estimate!K66 -> N | E24: =Estimate!F66 -> 0 | G24: =IF(F24="","",E24-F24)
A25: =Estimate!A68 -> 0570 | B25: Exterior Finishes | C25: Concrete Flatwork | D25: =Estimate!K68 -> Y | E25: =Estimate!F68 -> 0 | G25: =IF(F25="","",E25-F25)
A26: =Estimate!A73 -> 0610 | B26: HVAC | C26: HVAC | D26: =Estimate!K73 -> N | E26: =Estimate!F73 -> 0 | G26: =IF(F26="","",E26-F26)
A27: =Estimate!A75 -> 0620 | B27: HVAC | C27: Fireplace | D27: =Estimate!K75 -> Y | E27: =Estimate!F75 -> 0 | G27: =IF(F27="","",E27-F27)
A28: =Estimate!A78 -> 0710 | B28: Plumbing | C28: Plumbing | D28: =Estimate!K78 -> Y | E28: =Estimate!F78 -> 0 | G28: =IF(F28="","",E28-F28)
A29: =Estimate!A81 -> 0810 | B29: Electrical | C29: Electrical | D29: =Estimate!K81 -> Y | E29: =Estimate!F81 -> 0 | G29: =IF(F29="","",E29-F29)
A30: =Estimate!A85 -> 0820 | B30: Electrical | C30: Electrical Fixtures | D30: =Estimate!K85 -> Y | E30: =Estimate!F85 -> 0 | G30: =IF(F30="","",E30-F30)
A31: =Estimate!A88 -> 0910 | B31: Insulation | C31: Insulation | D31: =Estimate!K88 -> N | E31: =Estimate!F88 -> 0 | G31: =IF(F31="","",E31-F31)
A32: =Estimate!A91 -> 1010 | B32: Interior Wall & Ceiling Finishes | C32: Drywall | D32: =Estimate!K91 -> N | E32: =Estimate!F91 -> 0 | G32: =IF(F32="","",E32-F32)
A33: =Estimate!A93 -> 1020 | B33: Interior Wall & Ceiling Finishes | C33: Interior Paint | D33: =Estimate!K93 -> N | E33: =Estimate!F93 -> 0 | G33: =IF(F33="","",E33-F33)
A34: =Estimate!A95 -> 1030 | B34: Interior Wall & Ceiling Finishes | C34: Interior Paint Color(s) | D34: =Estimate!K95 -> N | E34: =Estimate!F95 -> 0 | G34: =IF(F34="","",E34-F34)
A35: =Estimate!A96 -> 1040 | B35: Interior Wall & Ceiling Finishes | C35: Bathroom accessories and mirrors | D35: =Estimate!K96 -> Y | E35: =Estimate!F96 -> 0 | G35: =IF(F35="","",E35-F35)
A36: =Estimate!A99 -> 1050 | B36: Interior Wall & Ceiling Finishes | C36: Masonry - Fireplace facade | D36: =Estimate!K99 -> Y | E36: =Estimate!F99 -> 0 | G36: =IF(F36="","",E36-F36)
A37: =Estimate!A103 -> 1110 | B37: Flooring | C37: Flooring Labor | D37: =Estimate!K103 -> Y | E37: =Estimate!F103 -> 0 | G37: =IF(F37="","",E37-F37)
A38: =Estimate!A108 -> 1120 | B38: Flooring | C38: Flooring material | D38: =Estimate!K108 -> Y | E38: =Estimate!F108 -> 0 | G38: =IF(F38="","",E38-F38)
A39: =Estimate!A112 -> 1210 | B39: Woodwork/Cabinets/Millwork | C39: Millwork | D39: =Estimate!K112 -> N | E39: =Estimate!F112 -> 0 | G39: =IF(F39="","",E39-F39)
A40: =Estimate!A114 -> 1220 | B40: Woodwork/Cabinets/Millwork | C40: Finish Carpentry | D40: =Estimate!K114 -> N | E40: =Estimate!F114 -> 0 | G40: =IF(F40="","",E40-F40)
A41: =Estimate!A116 -> 1230 | B41: Woodwork/Cabinets/Millwork | C41: Cabinet Specifications | D41: =Estimate!K116 -> Y | E41: =Estimate!F116 -> 0 | G41: =IF(F41="","",E41-F41)
A42: =Estimate!A118 -> 1240 | B42: Woodwork/Cabinets/Millwork | C42: Countertops | D42: =Estimate!K118 -> Y | E42: =Estimate!F118 -> 0 | G42: =IF(F42="","",E42-F42)
A43: =Estimate!A122 -> 1310 | B43: Appliances/Equipment | C43: Appliance Specifications | D43: =Estimate!K122 -> N | E43: =Estimate!F122 -> 0 | G43: =IF(F43="","",E43-F43)
A44: =Estimate!A124 -> 1320 | B44: Appliances/Equipment | C44: Window Coverings | D44: =Estimate!K124 -> Y | E44: =Estimate!F124 -> 0 | G44: =IF(F44="","",E44-F44)
A45: =Estimate!A127 -> 1510 | B45: Final Grade & Site | C45: Final Grade & Landscaping | D45: =Estimate!K127 -> N | E45: =Estimate!F127 -> 0 | G45: =IF(F45="","",E45-F45)
C46: TOTAL ALLOWANCES | E46: =SUMIF(D6:D45,"Y",E6:E45) -> 0 | F46: =SUMIF(D6:D45,"Y",F6:F45) -> 0 | G46: =E46-F46 -> 0

Sheet Schedule
A1: PROJECT SCHEDULE (one line per estimate item — add the items below as each job needs them)
A3: ID | B3: Task | C3: Dur | D3: Start | E3: Finish | F3: Pred | G3: Anchor | H3: Status | I3: % Done
A4: 1 | B4: 0110 Permits | C4: =IFERROR(NETWORKDAYS(D4,E4),"") | D4: =IF(COUNT(D5:D6)=0,"",MIN(D5:D6)) | E4: =IF(COUNT(E5:E6)=0,"",MAX(E5:E6)) | H4: =IF(I4>=1,"Complete",IF(I4>0,"In Progress","Not Started")) -> Not Started | I4: =IFERROR(SUMPRODUCT((B5:B6<>"")*I5:I6)/SUMPRODUCT((B5:B6<>"")*1),0) -> 0
D5: =IF(C5="","",Settings!$C$36) | E5: =IF(D5="","",WORKDAY(D5,MAX(C5,1)-1))
D6: =IF(C6="","",IF(G6<>"",G6,IF(ISNUMBER(E5),WORKDAY(E5,1),Settings!$C$36))) | E6: =IF(D6="","",WORKDAY(D6,MAX(C6,1)-1))
A7: 2 | B7: 0120 Electrical Utility Connections | C7: =IFERROR(NETWORKDAYS(D7,E7),"") | D7: =IF(COUNT(D8:D9)=0,"",MIN(D8:D9)) | E7: =IF(COUNT(E8:E9)=0,"",MAX(E8:E9)) | H7: =IF(I7>=1,"Complete",IF(I7>0,"In Progress","Not Started")) -> Not Started | I7: =IFERROR(SUMPRODUCT((B8:B9<>"")*I8:I9)/SUMPRODUCT((B8:B9<>"")*1),0) -> 0
D8: =IF(C8="","",IF(G8<>"",G8,IF(ISNUMBER(E6),WORKDAY(E6,1),Settings!$C$36))) | E8: =IF(D8="","",WORKDAY(D8,MAX(C8,1)-1))
D9: =IF(C9="","",IF(G9<>"",G9,IF(ISNUMBER(E8),WORKDAY(E8,1),Settings!$C$36))) | E9: =IF(D9="","",WORKDAY(D9,MAX(C9,1)-1))
A10: 3 | B10: 0130 Excavation | C10: =IFERROR(NETWORKDAYS(D10,E10),"") | D10: =IF(COUNT(D11:D12)=0,"",MIN(D11:D12)) | E10: =IF(COUNT(E11:E12)=0,"",MAX(E11:E12)) | H10: =IF(I10>=1,"Complete",IF(I10>0,"In Progress","Not Started")) -> Not Started | I10: =IFERROR(SUMPRODUCT((B11:B12<>"")*I11:I12)/SUMPRODUCT((B11:B12<>"")*1),0) -> 0
D11: =IF(C11="","",IF(G11<>"",G11,IF(ISNUMBER(E9),WORKDAY(E9,1),Settings!$C$36))) | E11: =IF(D11="","",WORKDAY(D11,MAX(C11,1)-1))
D12: =IF(C12="","",IF(G12<>"",G12,IF(ISNUMBER(E11),WORKDAY(E11,1),Settings!$C$36))) | E12: =IF(D12="","",WORKDAY(D12,MAX(C12,1)-1))
A13: 4 | B13: 0140 Septic system design & install | C13: =IFERROR(NETWORKDAYS(D13,E13),"") | D13: =IF(COUNT(D14:D15)=0,"",MIN(D14:D15)) | E13: =IF(COUNT(E14:E15)=0,"",MAX(E14:E15)) | H13: =IF(I13>=1,"Complete",IF(I13>0,"In Progress","Not Started")) -> Not Started | I13: =IFERROR(SUMPRODUCT((B14:B15<>"")*I14:I15)/SUMPRODUCT((B14:B15<>"")*1),0) -> 0
D14: =IF(C14="","",IF(G14<>"",G14,IF(ISNUMBER(E12),WORKDAY(E12,1),Settings!$C$36))) | E14: =IF(D14="","",WORKDAY(D14,MAX(C14,1)-1))
D15: =IF(C15="","",IF(G15<>"",G15,IF(ISNUMBER(E14),WORKDAY(E14,1),Settings!$C$36))) | E15: =IF(D15="","",WORKDAY(D15,MAX(C15,1)-1))
A16: 5 | B16: 0210 Footing And Foundation | C16: =IFERROR(NETWORKDAYS(D16,E16),"") | D16: =IF(COUNT(D17:D18)=0,"",MIN(D17:D18)) | E16: =IF(COUNT(E17:E18)=0,"",MAX(E17:E18)) | H16: =IF(I16>=1,"Complete",IF(I16>0,"In Progress","Not Started")) -> Not Started | I16: =IFERROR(SUMPRODUCT((B17:B18<>"")*I17:I18)/SUMPRODUCT((B17:B18<>"")*1),0) -> 0
D17: =IF(C17="","",IF(G17<>"",G17,IF(ISNUMBER(E15),WORKDAY(E15,1),Settings!$C$36))) | E17: =IF(D17="","",WORKDAY(D17,MAX(C17,1)-1))
D18: =IF(C18="","",IF(G18<>"",G18,IF(ISNUMBER(E17),WORKDAY(E17,1),Settings!$C$36))) | E18: =IF(D18="","",WORKDAY(D18,MAX(C18,1)-1))
A19: 6 | B19: 0310 Framing Materials | C19: =IFERROR(NETWORKDAYS(D19,E19),"") | D19: =IF(COUNT(D20:D21)=0,"",MIN(D20:D21)) | E19: =IF(COUNT(E20:E21)=0,"",MAX(E20:E21)) | H19: =IF(I19>=1,"Complete",IF(I19>0,"In Progress","Not Started")) -> Not Started | I19: =IFERROR(SUMPRODUCT((B20:B21<>"")*I20:I21)/SUMPRODUCT((B20:B21<>"")*1),0) -> 0
D20: =IF(C20="","",IF(G20<>"",G20,IF(ISNUMBER(E18),WORKDAY(E18,1),Settings!$C$36))) | E20: =IF(D20="","",WORKDAY(D20,MAX(C20,1)-1))
D21: =IF(C21="","",IF(G21<>"",G21,IF(ISNUMBER(E20),WORKDAY(E20,1),Settings!$C$36))) | E21: =IF(D21="","",WORKDAY(D21,MAX(C21,1)-1))
A22: 7 | B22: 0320 Framing Labor | C22: =IFERROR(NETWORKDAYS(D22,E22),"") | D22: =IF(COUNT(D23:D24)=0,"",MIN(D23:D24)) | E22: =IF(COUNT(E23:E24)=0,"",MAX(E23:E24)) | H22: =IF(I22>=1,"Complete",IF(I22>0,"In Progress","Not Started")) -> Not Started | I22: =IFERROR(SUMPRODUCT((B23:B24<>"")*I23:I24)/SUMPRODUCT((B23:B24<>"")*1),0) -> 0
D23: =IF(C23="","",IF(G23<>"",G23,IF(ISNUMBER(E21),WORKDAY(E21,1),Settings!$C$36))) | E23: =IF(D23="","",WORKDAY(D23,MAX(C23,1)-1))
D24: =IF(C24="","",IF(G24<>"",G24,IF(ISNUMBER(E23),WORKDAY(E23,1),Settings!$C$36))) | E24: =IF(D24="","",WORKDAY(D24,MAX(C24,1)-1))
A25: 8 | B25: 0410 Front Door | C25: =IFERROR(NETWORKDAYS(D25,E25),"") | D25: =IF(COUNT(D26:D27)=0,"",MIN(D26:D27)) | E25: =IF(COUNT(E26:E27)=0,"",MAX(E26:E27)) | H25: =IF(I25>=1,"Complete",IF(I25>0,"In Progress","Not Started")) -> Not Started | I25: =IFERROR(SUMPRODUCT((B26:B27<>"")*I26:I27)/SUMPRODUCT((B26:B27<>"")*1),0) -> 0
D26: =IF(C26="","",IF(G26<>"",G26,IF(ISNUMBER(E24),WORKDAY(E24,1),Settings!$C$36))) | E26: =IF(D26="","",WORKDAY(D26,MAX(C26,1)-1))
D27: =IF(C27="","",IF(G27<>"",G27,IF(ISNUMBER(E26),WORKDAY(E26,1),Settings!$C$36))) | E27: =IF(D27="","",WORKDAY(D27,MAX(C27,1)-1))
A28: 9 | B28: 0420 Other exterior doors | C28: =IFERROR(NETWORKDAYS(D28,E28),"") | D28: =IF(COUNT(D29:D30)=0,"",MIN(D29:D30)) | E28: =IF(COUNT(E29:E30)=0,"",MAX(E29:E30)) | H28: =IF(I28>=1,"Complete",IF(I28>0,"In Progress","Not Started")) -> Not Started | I28: =IFERROR(SUMPRODUCT((B29:B30<>"")*I29:I30)/SUMPRODUCT((B29:B30<>"")*1),0) -> 0
D29: =IF(C29="","",IF(G29<>"",G29,IF(ISNUMBER(E27),WORKDAY(E27,1),Settings!$C$36))) | E29: =IF(D29="","",WORKDAY(D29,MAX(C29,1)-1))
D30: =IF(C30="","",IF(G30<>"",G30,IF(ISNUMBER(E29),WORKDAY(E29,1),Settings!$C$36))) | E30: =IF(D30="","",WORKDAY(D30,MAX(C30,1)-1))
A31: 10 | B31: 0430 Garage Doors | C31: =IFERROR(NETWORKDAYS(D31,E31),"") | D31: =IF(COUNT(D32:D33)=0,"",MIN(D32:D33)) | E31: =IF(COUNT(E32:E33)=0,"",MAX(E32:E33)) | H31: =IF(I31>=1,"Complete",IF(I31>0,"In Progress","Not Started")) -> Not Started | I31: =IFERROR(SUMPRODUCT((B32:B33<>"")*I32:I33)/SUMPRODUCT((B32:B33<>"")*1),0) -> 0
D32: =IF(C32="","",IF(G32<>"",G32,IF(ISNUMBER(E30),WORKDAY(E30,1),Settings!$C$36))) | E32: =IF(D32="","",WORKDAY(D32,MAX(C32,1)-1))
D33: =IF(C33="","",IF(G33<>"",G33,IF(ISNUMBER(E32),WORKDAY(E32,1),Settings!$C$36))) | E33: =IF(D33="","",WORKDAY(D33,MAX(C33,1)-1))
A34: 11 | B34: 0440 Windows | C34: =IFERROR(NETWORKDAYS(D34,E34),"") | D34: =IF(COUNT(D35:D36)=0,"",MIN(D35:D36)) | E34: =IF(COUNT(E35:E36)=0,"",MAX(E35:E36)) | H34: =IF(I34>=1,"Complete",IF(I34>0,"In Progress","Not Started")) -> Not Started | I34: =IFERROR(SUMPRODUCT((B35:B36<>"")*I35:I36)/SUMPRODUCT((B35:B36<>"")*1),0) -> 0
D35: =IF(C35="","",IF(G35<>"",G35,IF(ISNUMBER(E33),WORKDAY(E33,1),Settings!$C$36))) | E35: =IF(D35="","",WORKDAY(D35,MAX(C35,1)-1))
D36: =IF(C36="","",IF(G36<>"",G36,IF(ISNUMBER(E35),WORKDAY(E35,1),Settings!$C$36))) | E36: =IF(D36="","",WORKDAY(D36,MAX(C36,1)-1))
A37: 12 | B37: 0510 Siding Materials | C37: =IFERROR(NETWORKDAYS(D37,E37),"") | D37: =IF(COUNT(D38:D39)=0,"",MIN(D38:D39)) | E37: =IF(COUNT(E38:E39)=0,"",MAX(E38:E39)) | H37: =IF(I37>=1,"Complete",IF(I37>0,"In Progress","Not Started")) -> Not Started | I37: =IFERROR(SUMPRODUCT((B38:B39<>"")*I38:I39)/SUMPRODUCT((B38:B39<>"")*1),0) -> 0
D38: =IF(C38="","",IF(G38<>"",G38,IF(ISNUMBER(E36),WORKDAY(E36,1),Settings!$C$36))) | E38: =IF(D38="","",WORKDAY(D38,MAX(C38,1)-1))
D39: =IF(C39="","",IF(G39<>"",G39,IF(ISNUMBER(E38),WORKDAY(E38,1),Settings!$C$36))) | E39: =IF(D39="","",WORKDAY(D39,MAX(C39,1)-1))
A40: 13 | B40: 0520 Siding Labor | C40: =IFERROR(NETWORKDAYS(D40,E40),"") | D40: =IF(COUNT(D41:D42)=0,"",MIN(D41:D42)) | E40: =IF(COUNT(E41:E42)=0,"",MAX(E41:E42)) | H40: =IF(I40>=1,"Complete",IF(I40>0,"In Progress","Not Started")) -> Not Started | I40: =IFERROR(SUMPRODUCT((B41:B42<>"")*I41:I42)/SUMPRODUCT((B41:B42<>"")*1),0) -> 0
D41: =IF(C41="","",IF(G41<>"",G41,IF(ISNUMBER(E39),WORKDAY(E39,1),Settings!$C$36))) | E41: =IF(D41="","",WORKDAY(D41,MAX(C41,1)-1))
D42: =IF(C42="","",IF(G42<>"",G42,IF(ISNUMBER(E41),WORKDAY(E41,1),Settings!$C$36))) | E42: =IF(D42="","",WORKDAY(D42,MAX(C42,1)-1))
A43: 14 | B43: 0530 Roofing Specifications | C43: =IFERROR(NETWORKDAYS(D43,E43),"") | D43: =IF(COUNT(D44:D45)=0,"",MIN(D44:D45)) | E43: =IF(COUNT(E44:E45)=0,"",MAX(E44:E45)) | H43: =IF(I43>=1,"Complete",IF(I43>0,"In Progress","Not Started")) -> Not Started | I43: =IFERROR(SUMPRODUCT((B44:B45<>"")*I44:I45)/SUMPRODUCT((B44:B45<>"")*1),0) -> 0
D44: =IF(C44="","",IF(G44<>"",G44,IF(ISNUMBER(E42),WORKDAY(E42,1),Settings!$C$36))) | E44: =IF(D44="","",WORKDAY(D44,MAX(C44,1)-1))
D45: =IF(C45="","",IF(G45<>"",G45,IF(ISNUMBER(E44),WORKDAY(E44,1),Settings!$C$36))) | E45: =IF(D45="","",WORKDAY(D45,MAX(C45,1)-1))
A46: 15 | B46: 0540 Gutters | C46: =IFERROR(NETWORKDAYS(D46,E46),"") | D46: =IF(COUNT(D47:D48)=0,"",MIN(D47:D48)) | E46: =IF(COUNT(E47:E48)=0,"",MAX(E47:E48)) | H46: =IF(I46>=1,"Complete",IF(I46>0,"In Progress","Not Started")) -> Not Started | I46: =IFERROR(SUMPRODUCT((B47:B48<>"")*I47:I48)/SUMPRODUCT((B47:B48<>"")*1),0) -> 0
D47: =IF(C47="","",IF(G47<>"",G47,IF(ISNUMBER(E45),WORKDAY(E45,1),Settings!$C$36))) | E47: =IF(D47="","",WORKDAY(D47,MAX(C47,1)-1))
D48: =IF(C48="","",IF(G48<>"",G48,IF(ISNUMBER(E47),WORKDAY(E47,1),Settings!$C$36))) | E48: =IF(D48="","",WORKDAY(D48,MAX(C48,1)-1))
A49: 16 | B49: 0560 Exterior Painting | C49: =IFERROR(NETWORKDAYS(D49,E49),"") | D49: =IF(COUNT(D50:D51)=0,"",MIN(D50:D51)) | E49: =IF(COUNT(E50:E51)=0,"",MAX(E50:E51)) | H49: =IF(I49>=1,"Complete",IF(I49>0,"In Progress","Not Started")) -> Not Started | I49: =IFERROR(SUMPRODUCT((B50:B51<>"")*I50:I51)/SUMPRODUCT((B50:B51<>"")*1),0) -> 0
D50: =IF(C50="","",IF(G50<>"",G50,IF(ISNUMBER(E48),WORKDAY(E48,1),Settings!$C$36))) | E50: =IF(D50="","",WORKDAY(D50,MAX(C50,1)-1))
D51: =IF(C51="","",IF(G51<>"",G51,IF(ISNUMBER(E50),WORKDAY(E50,1),Settings!$C$36))) | E51: =IF(D51="","",WORKDAY(D51,MAX(C51,1)-1))
A52: 17 | B52: 0570 Concrete Flatwork | C52: =IFERROR(NETWORKDAYS(D52,E52),"") | D52: =IF(COUNT(D53:D54)=0,"",MIN(D53:D54)) | E52: =IF(COUNT(E53:E54)=0,"",MAX(E53:E54)) | H52: =IF(I52>=1,"Complete",IF(I52>0,"In Progress","Not Started")) -> Not Started | I52: =IFERROR(SUMPRODUCT((B53:B54<>"")*I53:I54)/SUMPRODUCT((B53:B54<>"")*1),0) -> 0
D53: =IF(C53="","",IF(G53<>"",G53,IF(ISNUMBER(E51),WORKDAY(E51,1),Settings!$C$36))) | E53: =IF(D53="","",WORKDAY(D53,MAX(C53,1)-1))
D54: =IF(C54="","",IF(G54<>"",G54,IF(ISNUMBER(E53),WORKDAY(E53,1),Settings!$C$36))) | E54: =IF(D54="","",WORKDAY(D54,MAX(C54,1)-1))
A55: 18 | B55: 0610 HVAC | C55: =IFERROR(NETWORKDAYS(D55,E55),"") | D55: =IF(COUNT(D56:D57)=0,"",MIN(D56:D57)) | E55: =IF(COUNT(E56:E57)=0,"",MAX(E56:E57)) | H55: =IF(I55>=1,"Complete",IF(I55>0,"In Progress","Not Started")) -> Not Started | I55: =IFERROR(SUMPRODUCT((B56:B57<>"")*I56:I57)/SUMPRODUCT((B56:B57<>"")*1),0) -> 0
D56: =IF(C56="","",IF(G56<>"",G56,IF(ISNUMBER(E54),WORKDAY(E54,1),Settings!$C$36))) | E56: =IF(D56="","",WORKDAY(D56,MAX(C56,1)-1))
D57: =IF(C57="","",IF(G57<>"",G57,IF(ISNUMBER(E56),WORKDAY(E56,1),Settings!$C$36))) | E57: =IF(D57="","",WORKDAY(D57,MAX(C57,1)-1))
A58: 19 | B58: 0620 Fireplace | C58: =IFERROR(NETWORKDAYS(D58,E58),"") | D58: =IF(COUNT(D59:D60)=0,"",MIN(D59:D60)) | E58: =IF(COUNT(E59:E60)=0,"",MAX(E59:E60)) | H58: =IF(I58>=1,"Complete",IF(I58>0,"In Progress","Not Started")) -> Not Started | I58: =IFERROR(SUMPRODUCT((B59:B60<>"")*I59:I60)/SUMPRODUCT((B59:B60<>"")*1),0) -> 0
D59: =IF(C59="","",IF(G59<>"",G59,IF(ISNUMBER(E57),WORKDAY(E57,1),Settings!$C$36))) | E59: =IF(D59="","",WORKDAY(D59,MAX(C59,1)-1))
D60: =IF(C60="","",IF(G60<>"",G60,IF(ISNUMBER(E59),WORKDAY(E59,1),Settings!$C$36))) | E60: =IF(D60="","",WORKDAY(D60,MAX(C60,1)-1))
A61: 20 | B61: 0710 Plumbing | C61: =IFERROR(NETWORKDAYS(D61,E61),"") | D61: =IF(COUNT(D62:D63)=0,"",MIN(D62:D63)) | E61: =IF(COUNT(E62:E63)=0,"",MAX(E62:E63)) | H61: =IF(I61>=1,"Complete",IF(I61>0,"In Progress","Not Started")) -> Not Started | I61: =IFERROR(SUMPRODUCT((B62:B63<>"")*I62:I63)/SUMPRODUCT((B62:B63<>"")*1),0) -> 0
D62: =IF(C62="","",IF(G62<>"",G62,IF(ISNUMBER(E60),WORKDAY(E60,1),Settings!$C$36))) | E62: =IF(D62="","",WORKDAY(D62,MAX(C62,1)-1))
D63: =IF(C63="","",IF(G63<>"",G63,IF(ISNUMBER(E62),WORKDAY(E62,1),Settings!$C$36))) | E63: =IF(D63="","",WORKDAY(D63,MAX(C63,1)-1))
A64: 21 | B64: 0810 Electrical | C64: =IFERROR(NETWORKDAYS(D64,E64),"") | D64: =IF(COUNT(D65:D66)=0,"",MIN(D65:D66)) | E64: =IF(COUNT(E65:E66)=0,"",MAX(E65:E66)) | H64: =IF(I64>=1,"Complete",IF(I64>0,"In Progress","Not Started")) -> Not Started | I64: =IFERROR(SUMPRODUCT((B65:B66<>"")*I65:I66)/SUMPRODUCT((B65:B66<>"")*1),0) -> 0
D65: =IF(C65="","",IF(G65<>"",G65,IF(ISNUMBER(E63),WORKDAY(E63,1),Settings!$C$36))) | E65: =IF(D65="","",WORKDAY(D65,MAX(C65,1)-1))
D66: =IF(C66="","",IF(G66<>"",G66,IF(ISNUMBER(E65),WORKDAY(E65,1),Settings!$C$36))) | E66: =IF(D66="","",WORKDAY(D66,MAX(C66,1)-1))
A67: 22 | B67: 0910 Insulation | C67: =IFERROR(NETWORKDAYS(D67,E67),"") | D67: =IF(COUNT(D68:D69)=0,"",MIN(D68:D69)) | E67: =IF(COUNT(E68:E69)=0,"",MAX(E68:E69)) | H67: =IF(I67>=1,"Complete",IF(I67>0,"In Progress","Not Started")) -> Not Started | I67: =IFERROR(SUMPRODUCT((B68:B69<>"")*I68:I69)/SUMPRODUCT((B68:B69<>"")*1),0) -> 0
D68: =IF(C68="","",IF(G68<>"",G68,IF(ISNUMBER(E66),WORKDAY(E66,1),Settings!$C$36))) | E68: =IF(D68="","",WORKDAY(D68,MAX(C68,1)-1))
D69: =IF(C69="","",IF(G69<>"",G69,IF(ISNUMBER(E68),WORKDAY(E68,1),Settings!$C$36))) | E69: =IF(D69="","",WORKDAY(D69,MAX(C69,1)-1))
A70: 23 | B70: 1010 Drywall | C70: =IFERROR(NETWORKDAYS(D70,E70),"") | D70: =IF(COUNT(D71:D72)=0,"",MIN(D71:D72)) | E70: =IF(COUNT(E71:E72)=0,"",MAX(E71:E72)) | H70: =IF(I70>=1,"Complete",IF(I70>0,"In Progress","Not Started")) -> Not Started | I70: =IFERROR(SUMPRODUCT((B71:B72<>"")*I71:I72)/SUMPRODUCT((B71:B72<>"")*1),0) -> 0
D71: =IF(C71="","",IF(G71<>"",G71,IF(ISNUMBER(E69),WORKDAY(E69,1),Settings!$C$36))) | E71: =IF(D71="","",WORKDAY(D71,MAX(C71,1)-1))
D72: =IF(C72="","",IF(G72<>"",G72,IF(ISNUMBER(E71),WORKDAY(E71,1),Settings!$C$36))) | E72: =IF(D72="","",WORKDAY(D72,MAX(C72,1)-1))
A73: 24 | B73: 1020 Interior Paint | C73: =IFERROR(NETWORKDAYS(D73,E73),"") | D73: =IF(COUNT(D74:D75)=0,"",MIN(D74:D75)) | E73: =IF(COUNT(E74:E75)=0,"",MAX(E74:E75)) | H73: =IF(I73>=1,"Complete",IF(I73>0,"In Progress","Not Started")) -> Not Started | I73: =IFERROR(SUMPRODUCT((B74:B75<>"")*I74:I75)/SUMPRODUCT((B74:B75<>"")*1),0) -> 0
D74: =IF(C74="","",IF(G74<>"",G74,IF(ISNUMBER(E72),WORKDAY(E72,1),Settings!$C$36))) | E74: =IF(D74="","",WORKDAY(D74,MAX(C74,1)-1))
D75: =IF(C75="","",IF(G75<>"",G75,IF(ISNUMBER(E74),WORKDAY(E74,1),Settings!$C$36))) | E75: =IF(D75="","",WORKDAY(D75,MAX(C75,1)-1))
A76: 25 | B76: 1040 Bathroom accessories and mirrors | C76: =IFERROR(NETWORKDAYS(D76,E76),"") | D76: =IF(COUNT(D77:D78)=0,"",MIN(D77:D78)) | E76: =IF(COUNT(E77:E78)=0,"",MAX(E77:E78)) | H76: =IF(I76>=1,"Complete",IF(I76>0,"In Progress","Not Started")) -> Not Started | I76: =IFERROR(SUMPRODUCT((B77:B78<>"")*I77:I78)/SUMPRODUCT((B77:B78<>"")*1),0) -> 0
D77: =IF(C77="","",IF(G77<>"",G77,IF(ISNUMBER(E75),WORKDAY(E75,1),Settings!$C$36))) | E77: =IF(D77="","",WORKDAY(D77,MAX(C77,1)-1))
D78: =IF(C78="","",IF(G78<>"",G78,IF(ISNUMBER(E77),WORKDAY(E77,1),Settings!$C$36))) | E78: =IF(D78="","",WORKDAY(D78,MAX(C78,1)-1))
A79: 26 | B79: 1110 Flooring Labor | C79: =IFERROR(NETWORKDAYS(D79,E79),"") | D79: =IF(COUNT(D80:D81)=0,"",MIN(D80:D81)) | E79: =IF(COUNT(E80:E81)=0,"",MAX(E80:E81)) | H79: =IF(I79>=1,"Complete",IF(I79>0,"In Progress","Not Started")) -> Not Started | I79: =IFERROR(SUMPRODUCT((B80:B81<>"")*I80:I81)/SUMPRODUCT((B80:B81<>"")*1),0) -> 0
D80: =IF(C80="","",IF(G80<>"",G80,IF(ISNUMBER(E78),WORKDAY(E78,1),Settings!$C$36))) | E80: =IF(D80="","",WORKDAY(D80,MAX(C80,1)-1))
D81: =IF(C81="","",IF(G81<>"",G81,IF(ISNUMBER(E80),WORKDAY(E80,1),Settings!$C$36))) | E81: =IF(D81="","",WORKDAY(D81,MAX(C81,1)-1))
A82: 27 | B82: 1210 Millwork | C82: =IFERROR(NETWORKDAYS(D82,E82),"") | D82: =IF(COUNT(D83:D84)=0,"",MIN(D83:D84)) | E82: =IF(COUNT(E83:E84)=0,"",MAX(E83:E84)) | H82: =IF(I82>=1,"Complete",IF(I82>0,"In Progress","Not Started")) -> Not Started | I82: =IFERROR(SUMPRODUCT((B83:B84<>"")*I83:I84)/SUMPRODUCT((B83:B84<>"")*1),0) -> 0
D83: =IF(C83="","",IF(G83<>"",G83,IF(ISNUMBER(E81),WORKDAY(E81,1),Settings!$C$36))) | E83: =IF(D83="","",WORKDAY(D83,MAX(C83,1)-1))
D84: =IF(C84="","",IF(G84<>"",G84,IF(ISNUMBER(E83),WORKDAY(E83,1),Settings!$C$36))) | E84: =IF(D84="","",WORKDAY(D84,MAX(C84,1)-1))
A85: 28 | B85: 1220 Finish Carpentry | C85: =IFERROR(NETWORKDAYS(D85,E85),"") | D85: =IF(COUNT(D86:D87)=0,"",MIN(D86:D87)) | E85: =IF(COUNT(E86:E87)=0,"",MAX(E86:E87)) | H85: =IF(I85>=1,"Complete",IF(I85>0,"In Progress","Not Started")) -> Not Started | I85: =IFERROR(SUMPRODUCT((B86:B87<>"")*I86:I87)/SUMPRODUCT((B86:B87<>"")*1),0) -> 0
D86: =IF(C86="","",IF(G86<>"",G86,IF(ISNUMBER(E84),WORKDAY(E84,1),Settings!$C$36))) | E86: =IF(D86="","",WORKDAY(D86,MAX(C86,1)-1))
D87: =IF(C87="","",IF(G87<>"",G87,IF(ISNUMBER(E86),WORKDAY(E86,1),Settings!$C$36))) | E87: =IF(D87="","",WORKDAY(D87,MAX(C87,1)-1))
A88: 29 | B88: 1230 Cabinet Specifications | C88: =IFERROR(NETWORKDAYS(D88,E88),"") | D88: =IF(COUNT(D89:D90)=0,"",MIN(D89:D90)) | E88: =IF(COUNT(E89:E90)=0,"",MAX(E89:E90)) | H88: =IF(I88>=1,"Complete",IF(I88>0,"In Progress","Not Started")) -> Not Started | I88: =IFERROR(SUMPRODUCT((B89:B90<>"")*I89:I90)/SUMPRODUCT((B89:B90<>"")*1),0) -> 0
D89: =IF(C89="","",IF(G89<>"",G89,IF(ISNUMBER(E87),WORKDAY(E87,1),Settings!$C$36))) | E89: =IF(D89="","",WORKDAY(D89,MAX(C89,1)-1))
D90: =IF(C90="","",IF(G90<>"",G90,IF(ISNUMBER(E89),WORKDAY(E89,1),Settings!$C$36))) | E90: =IF(D90="","",WORKDAY(D90,MAX(C90,1)-1))
A91: 30 | B91: 1240 Countertops | C91: =IFERROR(NETWORKDAYS(D91,E91),"") | D91: =IF(COUNT(D92:D93)=0,"",MIN(D92:D93)) | E91: =IF(COUNT(E92:E93)=0,"",MAX(E92:E93)) | H91: =IF(I91>=1,"Complete",IF(I91>0,"In Progress","Not Started")) -> Not Started | I91: =IFERROR(SUMPRODUCT((B92:B93<>"")*I92:I93)/SUMPRODUCT((B92:B93<>"")*1),0) -> 0
D92: =IF(C92="","",IF(G92<>"",G92,IF(ISNUMBER(E90),WORKDAY(E90,1),Settings!$C$36))) | E92: =IF(D92="","",WORKDAY(D92,MAX(C92,1)-1))
D93: =IF(C93="","",IF(G93<>"",G93,IF(ISNUMBER(E92),WORKDAY(E92,1),Settings!$C$36))) | E93: =IF(D93="","",WORKDAY(D93,MAX(C93,1)-1))
A94: 31 | B94: 1510 Final Grade & Landscaping | C94: =IFERROR(NETWORKDAYS(D94,E94),"") | D94: =IF(COUNT(D95:D96)=0,"",MIN(D95:D96)) | E94: =IF(COUNT(E95:E96)=0,"",MAX(E95:E96)) | H94: =IF(I94>=1,"Complete",IF(I94>0,"In Progress","Not Started")) -> Not Started | I94: =IFERROR(SUMPRODUCT((B95:B96<>"")*I95:I96)/SUMPRODUCT((B95:B96<>"")*1),0) -> 0
D95: =IF(C95="","",IF(G95<>"",G95,IF(ISNUMBER(E93),WORKDAY(E93,1),Settings!$C$36))) | E95: =IF(D95="","",WORKDAY(D95,MAX(C95,1)-1))
D96: =IF(C96="","",IF(G96<>"",G96,IF(ISNUMBER(E95),WORKDAY(E95,1),Settings!$C$36))) | E96: =IF(D96="","",WORKDAY(D96,MAX(C96,1)-1))

Sheet Calendar
A1: PROJECT CALENDAR (auto from the Schedule — shaded = work happening; label = task starting that day)
A3: Week of | B3: Mon | C3: Tue | D3: Wed | E3: Thu | F3: Fri | G3: Sat | H3: Sun
A4: =(Settings!$C$36-(WEEKDAY(Settings!$C$36,2)-1))+0 -> 46202 | B4: =$A4+0 -> 46202 | C4: =$A4+1 -> 46203 | D4: =$A4+2 -> 46204 | E4: =$A4+3 -> 46205 | F4: =$A4+4 -> 46206 | G4: =$A4+5 -> 46207 | H4: =$A4+6 -> 46208
B5: =IFERROR(INDEX(Schedule!$B$4:$B$200,MATCH(B4,Schedule!$D$4:$D$200,0))&IF(COUNTIF(Schedule!$D$4:$D$200,B4)>1," +"&(COUNTIF(Schedule!$D$4:$D$200,B4)-1)&" more",""),"") | C5: =IFERROR(INDEX(Schedule!$B$4:$B$200,MATCH(C4,Schedule!$D$4:$D$200,0))&IF(COUNTIF(Schedule!$D$4:$D$200,C4)>1," +"&(COUNTIF(Schedule!$D$4:$D$200,C4)-1)&" more",""),"") | D5: =IFERROR(INDEX(Schedule!$B$4:$B$200,MATCH(D4,Schedule!$D$4:$D$200,0))&IF(COUNTIF(Schedule!$D$4:$D$200,D4)>1," +"&(COUNTIF(Schedule!$D$4:$D$200,D4)-1)&" more",""),"") | E5: =IFERROR(INDEX(Schedule!$B$4:$B$200,MATCH(E4,Schedule!$D$4:$D$200,0))&IF(COUNTIF(Schedule!$D$4:$D$200,E4)>1," +"&(COUNTIF(Schedule!$D$4:$D$200,E4)-1)&" more",""),"") | F5: =IFERROR(INDEX(Schedule!$B$4:$B$200,MATCH(F4,Schedule!$D$4:$D$200,0))&IF(COUNTIF(Schedule!$D$4:$D$200,F4)>1," +"&(COUNTIF(Schedule!$D$4:$D$200,F4)-1)&" more",""),"") | G5: =IFERROR(INDEX(Schedule!$B$4:$B$200,MATCH(G4,Schedule!$D$4:$D$200,0))&IF(COUNTIF(Schedule!$D$4:$D$200,G4)>1," +"&(COUNTIF(Schedule!$D$4:$D$200,G4)-1)&" more",""),"") | H5: =IFERROR(INDEX(Schedule!$B$4:$B$200,MATCH(H4,Schedule!$D$4:$D$200,0))&IF(COUNTIF(Schedule!$D$4:$D$200,H4)>1," +"&(COUNTIF(Schedule!$D$4:$D$200,H4)-1)&" more",""),"")
A6: =(Settings!$C$36-(WEEKDAY(Settings!$C$36,2)-1))+7 -> 46209 | B6: =$A6+0 -> 46209 | C6: =$A6+1 -> 46210 | D6: =$A6+2 -> 46211 | E6: =$A6+3 -> 46212 | F6: =$A6+4 -> 46213 | G6: =$A6+5 -> 46214 | H6: =$A6+6 -> 46215
B7: =IFERROR(INDEX(Schedule!$B$4:$B$200,MATCH(B6,Schedule!$D$4:$D$200,0))&IF(COUNTIF(Schedule!$D$4:$D$200,B6)>1," +"&(COUNTIF(Schedule!$D$4:$D$200,B6)-1)&" more",""),"") | C7: =IFERROR(INDEX(Schedule!$B$4:$B$200,MATCH(C6,Schedule!$D$4:$D$200,0))&IF(COUNTIF(Schedule!$D$4:$D$200,C6)>1," +"&(COUNTIF(Schedule!$D$4:$D$200,C6)-1)&" more",""),"") | D7: =IFERROR(INDEX(Schedule!$B$4:$B$200,MATCH(D6,Schedule!$D$4:$D$200,0))&IF(COUNTIF(Schedule!$D$4:$D$200,D6)>1," +"&(COUNTIF(Schedule!$D$4:$D$200,D6)-1)&" more",""),"") | E7: =IFERROR(INDEX(Schedule!$B$4:$B$200,MATCH(E6,Schedule!$D$4:$D$200,0))&IF(COUNTIF(Schedule!$D$4:$D$200,E6)>1," +"&(COUNTIF(Schedule!$D$4:$D$200,E6)-1)&" more",""),"") | F7: =IFERROR(INDEX(Schedule!$B$4:$B$200,MATCH(F6,Schedule!$D$4:$D$200,0))&IF(COUNTIF(Schedule!$D$4:$D$200,F6)>1," +"&(COUNTIF(Schedule!$D$4:$D$200,F6)-1)&" more",""),"") | G7: =IFERROR(INDEX(Schedule!$B$4:$B$200,MATCH(G6,Schedule!$D$4:$D$200,0))&IF(COUNTIF(Schedule!$D$4:$D$200,G6)>1," +"&(COUNTIF(Schedule!$D$4:$D$200,G6)-1)&" more",""),"") | H7: =IFERROR(INDEX(Schedule!$B$4:$B$200,MATCH(H6,Schedule!$D$4:$D$200,0))&IF(COUNTIF(Schedule!$D$4:$D$200,H6)>1," +"&(COUNTIF(Schedule!$D$4:$D$200,H6)-1)&" more",""),"")
A8: =(Settings!$C$36-(WEEKDAY(Settings!$C$36,2)-1))+14 -> 46216 | B8: =$A8+0 -> 46216 | C8: =$A8+1 -> 46217 | D8: =$A8+2 -> 46218 | E8: =$A8+3 -> 46219 | F8: =$A8+4 -> 46220 | G8: =$A8+5 -> 46221 | H8: =$A8+6 -> 46222
B9: =IFERROR(INDEX(Schedule!$B$4:$B$200,MATCH(B8,Schedule!$D$4:$D$200,0))&IF(COUNTIF(Schedule!$D$4:$D$200,B8)>1," +"&(COUNTIF(Schedule!$D$4:$D$200,B8)-1)&" more",""),"") | C9: =IFERROR(INDEX(Schedule!$B$4:$B$200,MATCH(C8,Schedule!$D$4:$D$200,0))&IF(COUNTIF(Schedule!$D$4:$D$200,C8)>1," +"&(COUNTIF(Schedule!$D$4:$D$200,C8)-1)&" more",""),"") | D9: =IFERROR(INDEX(Schedule!$B$4:$B$200,MATCH(D8,Schedule!$D$4:$D$200,0))&IF(COUNTIF(Schedule!$D$4:$D$200,D8)>1," +"&(COUNTIF(Schedule!$D$4:$D$200,D8)-1)&" more",""),"") | E9: =IFERROR(INDEX(Schedule!$B$4:$B$200,MATCH(E8,Schedule!$D$4:$D$200,0))&IF(COUNTIF(Schedule!$D$4:$D$200,E8)>1," +"&(COUNTIF(Schedule!$D$4:$D$200,E8)-1)&" more",""),"") | F9: =IFERROR(INDEX(Schedule!$B$4:$B$200,MATCH(F8,Schedule!$D$4:$D$200,0))&IF(COUNTIF(Schedule!$D$4:$D$200,F8)>1," +"&(COUNTIF(Schedule!$D$4:$D$200,F8)-1)&" more",""),"") | G9: =IFERROR(INDEX(Schedule!$B$4:$B$200,MATCH(G8,Schedule!$D$4:$D$200,0))&IF(COUNTIF(Schedule!$D$4:$D$200,G8)>1," +"&(COUNTIF(Schedule!$D$4:$D$200,G8)-1)&" more",""),"") | H9: =IFERROR(INDEX(Schedule!$B$4:$B$200,MATCH(H8,Schedule!$D$4:$D$200,0))&IF(COUNTIF(Schedule!$D$4:$D$200,H8)>1," +"&(COUNTIF(Schedule!$D$4:$D$200,H8)-1)&" more",""),"")
A10: =(Settings!$C$36-(WEEKDAY(Settings!$C$36,2)-1))+21 -> 46223 | B10: =$A10+0 -> 46223 | C10: =$A10+1 -> 46224 | D10: =$A10+2 -> 46225 | E10: =$A10+3 -> 46226 | F10: =$A10+4 -> 46227 | G10: =$A10+5 -> 46228 | H10: =$A10+6 -> 46229
B11: =IFERROR(INDEX(Schedule!$B$4:$B$200,MATCH(B10,Schedule!$D$4:$D$200,0))&IF(COUNTIF(Schedule!$D$4:$D$200,B10)>1," +"&(COUNTIF(Schedule!$D$4:$D$200,B10)-1)&" more",""),"") | C11: =IFERROR(INDEX(Schedule!$B$4:$B$200,MATCH(C10,Schedule!$D$4:$D$200,0))&IF(COUNTIF(Schedule!$D$4:$D$200,C10)>1," +"&(COUNTIF(Schedule!$D$4:$D$200,C10)-1)&" more",""),"") | D11: =IFERROR(INDEX(Schedule!$B$4:$B$200,MATCH(D10,Schedule!$D$4:$D$200,0))&IF(COUNTIF(Schedule!$D$4:$D$200,D10)>1," +"&(COUNTIF(Schedule!$D$4:$D$200,D10)-1)&" more",""),"") | E11: =IFERROR(INDEX(Schedule!$B$4:$B$200,MATCH(E10,Schedule!$D$4:$D$200,0))&IF(COUNTIF(Schedule!$D$4:$D$200,E10)>1," +"&(COUNTIF(Schedule!$D$4:$D$200,E10)-1)&" more",""),"") | F11: =IFERROR(INDEX(Schedule!$B$4:$B$200,MATCH(F10,Schedule!$D$4:$D$200,0))&IF(COUNTIF(Schedule!$D$4:$D$200,F10)>1," +"&(COUNTIF(Schedule!$D$4:$D$200,F10)-1)&" more",""),"") | G11: =IFERROR(INDEX(Schedule!$B$4:$B$200,MATCH(G10,Schedule!$D$4:$D$200,0))&IF(COUNTIF(Schedule!$D$4:$D$200,G10)>1," +"&(COUNTIF(Schedule!$D$4:$D$200,G10)-1)&" more",""),"") | H11: =IFERROR(INDEX(Schedule!$B$4:$B$200,MATCH(H10,Schedule!$D$4:$D$200,0))&IF(COUNTIF(Schedule!$D$4:$D$200,H10)>1," +"&(COUNTIF(Schedule!$D$4:$D$200,H10)-1)&" more",""),"")
A12: =(Settings!$C$36-(WEEKDAY(Settings!$C$36,2)-1))+28 -> 46230 | B12: =$A12+0 -> 46230 | C12: =$A12+1 -> 46231 | D12: =$A12+2 -> 46232 | E12: =$A12+3 -> 46233 | F12: =$A12+4 -> 46234 | G12: =$A12+5 -> 46235 | H12: =$A12+6 -> 46236
B13: =IFERROR(INDEX(Schedule!$B$4:$B$200,MATCH(B12,Schedule!$D$4:$D$200,0))&IF(COUNTIF(Schedule!$D$4:$D$200,B12)>1," +"&(COUNTIF(Schedule!$D$4:$D$200,B12)-1)&" more",""),"") | C13: =IFERROR(INDEX(Schedule!$B$4:$B$200,MATCH(C12,Schedule!$D$4:$D$200,0))&IF(COUNTIF(Schedule!$D$4:$D$200,C12)>1," +"&(COUNTIF(Schedule!$D$4:$D$200,C12)-1)&" more",""),"") | D13: =IFERROR(INDEX(Schedule!$B$4:$B$200,MATCH(D12,Schedule!$D$4:$D$200,0))&IF(COUNTIF(Schedule!$D$4:$D$200,D12)>1," +"&(COUNTIF(Schedule!$D$4:$D$200,D12)-1)&" more",""),"") | E13: =IFERROR(INDEX(Schedule!$B$4:$B$200,MATCH(E12,Schedule!$D$4:$D$200,0))&IF(COUNTIF(Schedule!$D$4:$D$200,E12)>1," +"&(COUNTIF(Schedule!$D$4:$D$200,E12)-1)&" more",""),"") | F13: =IFERROR(INDEX(Schedule!$B$4:$B$200,MATCH(F12,Schedule!$D$4:$D$200,0))&IF(COUNTIF(Schedule!$D$4:$D$200,F12)>1," +"&(COUNTIF(Schedule!$D$4:$D$200,F12)-1)&" more",""),"") | G13: =IFERROR(INDEX(Schedule!$B$4:$B$200,MATCH(G12,Schedule!$D$4:$D$200,0))&IF(COUNTIF(Schedule!$D$4:$D$200,G12)>1," +"&(COUNTIF(Schedule!$D$4:$D$200,G12)-1)&" more",""),"") | H13: =IFERROR(INDEX(Schedule!$B$4:$B$200,MATCH(H12,Schedule!$D$4:$D$200,0))&IF(COUNTIF(Schedule!$D$4:$D$200,H12)>1," +"&(COUNTIF(Schedule!$D$4:$D$200,H12)-1)&" more",""),"")
A14: =(Settings!$C$36-(WEEKDAY(Settings!$C$36,2)-1))+35 -> 46237 | B14: =$A14+0 -> 46237 | C14: =$A14+1 -> 46238 | D14: =$A14+2 -> 46239 | E14: =$A14+3 -> 46240 | F14: =$A14+4 -> 46241 | G14: =$A14+5 -> 46242 | H14: =$A14+6 -> 46243
B15: =IFERROR(INDEX(Schedule!$B$4:$B$200,MATCH(B14,Schedule!$D$4:$D$200,0))&IF(COUNTIF(Schedule!$D$4:$D$200,B14)>1," +"&(COUNTIF(Schedule!$D$4:$D$200,B14)-1)&" more",""),"") | C15: =IFERROR(INDEX(Schedule!$B$4:$B$200,MATCH(C14,Schedule!$D$4:$D$200,0))&IF(COUNTIF(Schedule!$D$4:$D$200,C14)>1," +"&(COUNTIF(Schedule!$D$4:$D$200,C14)-1)&" more",""),"") | D15: =IFERROR(INDEX(Schedule!$B$4:$B$200,MATCH(D14,Schedule!$D$4:$D$200,0))&IF(COUNTIF(Schedule!$D$4:$D$200,D14)>1," +"&(COUNTIF(Schedule!$D$4:$D$200,D14)-1)&" more",""),"") | E15: =IFERROR(INDEX(Schedule!$B$4:$B$200,MATCH(E14,Schedule!$D$4:$D$200,0))&IF(COUNTIF(Schedule!$D$4:$D$200,E14)>1," +"&(COUNTIF(Schedule!$D$4:$D$200,E14)-1)&" more",""),"") | F15: =IFERROR(INDEX(Schedule!$B$4:$B$200,MATCH(F14,Schedule!$D$4:$D$200,0))&IF(COUNTIF(Schedule!$D$4:$D$200,F14)>1," +"&(COUNTIF(Schedule!$D$4:$D$200,F14)-1)&" more",""),"") | G15: =IFERROR(INDEX(Schedule!$B$4:$B$200,MATCH(G14,Schedule!$D$4:$D$200,0))&IF(COUNTIF(Schedule!$D$4:$D$200,G14)>1," +"&(COUNTIF(Schedule!$D$4:$D$200,G14)-1)&" more",""),"") | H15: =IFERROR(INDEX(Schedule!$B$4:$B$200,MATCH(H14,Schedule!$D$4:$D$200,0))&IF(COUNTIF(Schedule!$D$4:$D$200,H14)>1," +"&(COUNTIF(Schedule!$D$4:$D$200,H14)-1)&" more",""),"")
A16: =(Settings!$C$36-(WEEKDAY(Settings!$C$36,2)-1))+42 -> 46244 | B16: =$A16+0 -> 46244 | C16: =$A16+1 -> 46245 | D16: =$A16+2 -> 46246 | E16: =$A16+3 -> 46247 | F16: =$A16+4 -> 46248 | G16: =$A16+5 -> 46249 | H16: =$A16+6 -> 46250
B17: =IFERROR(INDEX(Schedule!$B$4:$B$200,MATCH(B16,Schedule!$D$4:$D$200,0))&IF(COUNTIF(Schedule!$D$4:$D$200,B16)>1," +"&(COUNTIF(Schedule!$D$4:$D$200,B16)-1)&" more",""),"") | C17: =IFERROR(INDEX(Schedule!$B$4:$B$200,MATCH(C16,Schedule!$D$4:$D$200,0))&IF(COUNTIF(Schedule!$D$4:$D$200,C16)>1," +"&(COUNTIF(Schedule!$D$4:$D$200,C16)-1)&" more",""),"") | D17: =IFERROR(INDEX(Schedule!$B$4:$B$200,MATCH(D16,Schedule!$D$4:$D$200,0))&IF(COUNTIF(Schedule!$D$4:$D$200,D16)>1," +"&(COUNTIF(Schedule!$D$4:$D$200,D16)-1)&" more",""),"") | E17: =IFERROR(INDEX(Schedule!$B$4:$B$200,MATCH(E16,Schedule!$D$4:$D$200,0))&IF(COUNTIF(Schedule!$D$4:$D$200,E16)>1," +"&(COUNTIF(Schedule!$D$4:$D$200,E16)-1)&" more",""),"") | F17: =IFERROR(INDEX(Schedule!$B$4:$B$200,MATCH(F16,Schedule!$D$4:$D$200,0))&IF(COUNTIF(Schedule!$D$4:$D$200,F16)>1," +"&(COUNTIF(Schedule!$D$4:$D$200,F16)-1)&" more",""),"") | G17: =IFERROR(INDEX(Schedule!$B$4:$B$200,MATCH(G16,Schedule!$D$4:$D$200,0))&IF(COUNTIF(Schedule!$D$4:$D$200,G16)>1," +"&(COUNTIF(Schedule!$D$4:$D$200,G16)-1)&" more",""),"") | H17: =IFERROR(INDEX(Schedule!$B$4:$B$200,MATCH(H16,Schedule!$D$4:$D$200,0))&IF(COUNTIF(Schedule!$D$4:$D$200,H16)>1," +"&(COUNTIF(Schedule!$D$4:$D$200,H16)-1)&" more",""),"")
A18: =(Settings!$C$36-(WEEKDAY(Settings!$C$36,2)-1))+49 -> 46251 | B18: =$A18+0 -> 46251 | C18: =$A18+1 -> 46252 | D18: =$A18+2 -> 46253 | E18: =$A18+3 -> 46254 | F18: =$A18+4 -> 46255 | G18: =$A18+5 -> 46256 | H18: =$A18+6 -> 46257
B19: =IFERROR(INDEX(Schedule!$B$4:$B$200,MATCH(B18,Schedule!$D$4:$D$200,0))&IF(COUNTIF(Schedule!$D$4:$D$200,B18)>1," +"&(COUNTIF(Schedule!$D$4:$D$200,B18)-1)&" more",""),"") | C19: =IFERROR(INDEX(Schedule!$B$4:$B$200,MATCH(C18,Schedule!$D$4:$D$200,0))&IF(COUNTIF(Schedule!$D$4:$D$200,C18)>1," +"&(COUNTIF(Schedule!$D$4:$D$200,C18)-1)&" more",""),"") | D19: =IFERROR(INDEX(Schedule!$B$4:$B$200,MATCH(D18,Schedule!$D$4:$D$200,0))&IF(COUNTIF(Schedule!$D$4:$D$200,D18)>1," +"&(COUNTIF(Schedule!$D$4:$D$200,D18)-1)&" more",""),"") | E19: =IFERROR(INDEX(Schedule!$B$4:$B$200,MATCH(E18,Schedule!$D$4:$D$200,0))&IF(COUNTIF(Schedule!$D$4:$D$200,E18)>1," +"&(COUNTIF(Schedule!$D$4:$D$200,E18)-1)&" more",""),"") | F19: =IFERROR(INDEX(Schedule!$B$4:$B$200,MATCH(F18,Schedule!$D$4:$D$200,0))&IF(COUNTIF(Schedule!$D$4:$D$200,F18)>1," +"&(COUNTIF(Schedule!$D$4:$D$200,F18)-1)&" more",""),"") | G19: =IFERROR(INDEX(Schedule!$B$4:$B$200,MATCH(G18,Schedule!$D$4:$D$200,0))&IF(COUNTIF(Schedule!$D$4:$D$200,G18)>1," +"&(COUNTIF(Schedule!$D$4:$D$200,G18)-1)&" more",""),"") | H19: =IFERROR(INDEX(Schedule!$B$4:$B$200,MATCH(H18,Schedule!$D$4:$D$200,0))&IF(COUNTIF(Schedule!$D$4:$D$200,H18)>1," +"&(COUNTIF(Schedule!$D$4:$D$200,H18)-1)&" more",""),"")
A20: =(Settings!$C$36-(WEEKDAY(Settings!$C$36,2)-1))+56 -> 46258 | B20: =$A20+0 -> 46258 | C20: =$A20+1 -> 46259 | D20: =$A20+2 -> 46260 | E20: =$A20+3 -> 46261 | F20: =$A20+4 -> 46262 | G20: =$A20+5 -> 46263 | H20: =$A20+6 -> 46264
B21: =IFERROR(INDEX(Schedule!$B$4:$B$200,MATCH(B20,Schedule!$D$4:$D$200,0))&IF(COUNTIF(Schedule!$D$4:$D$200,B20)>1," +"&(COUNTIF(Schedule!$D$4:$D$200,B20)-1)&" more",""),"") | C21: =IFERROR(INDEX(Schedule!$B$4:$B$200,MATCH(C20,Schedule!$D$4:$D$200,0))&IF(COUNTIF(Schedule!$D$4:$D$200,C20)>1," +"&(COUNTIF(Schedule!$D$4:$D$200,C20)-1)&" more",""),"") | D21: =IFERROR(INDEX(Schedule!$B$4:$B$200,MATCH(D20,Schedule!$D$4:$D$200,0))&IF(COUNTIF(Schedule!$D$4:$D$200,D20)>1," +"&(COUNTIF(Schedule!$D$4:$D$200,D20)-1)&" more",""),"") | E21: =IFERROR(INDEX(Schedule!$B$4:$B$200,MATCH(E20,Schedule!$D$4:$D$200,0))&IF(COUNTIF(Schedule!$D$4:$D$200,E20)>1," +"&(COUNTIF(Schedule!$D$4:$D$200,E20)-1)&" more",""),"") | F21: =IFERROR(INDEX(Schedule!$B$4:$B$200,MATCH(F20,Schedule!$D$4:$D$200,0))&IF(COUNTIF(Schedule!$D$4:$D$200,F20)>1," +"&(COUNTIF(Schedule!$D$4:$D$200,F20)-1)&" more",""),"") | G21: =IFERROR(INDEX(Schedule!$B$4:$B$200,MATCH(G20,Schedule!$D$4:$D$200,0))&IF(COUNTIF(Schedule!$D$4:$D$200,G20)>1," +"&(COUNTIF(Schedule!$D$4:$D$200,G20)-1)&" more",""),"") | H21: =IFERROR(INDEX(Schedule!$B$4:$B$200,MATCH(H20,Schedule!$D$4:$D$200,0))&IF(COUNTIF(Schedule!$D$4:$D$200,H20)>1," +"&(COUNTIF(Schedule!$D$4:$D$200,H20)-1)&" more",""),"")
A22: =(Settings!$C$36-(WEEKDAY(Settings!$C$36,2)-1))+63 -> 46265 | B22: =$A22+0 -> 46265 | C22: =$A22+1 -> 46266 | D22: =$A22+2 -> 46267 | E22: =$A22+3 -> 46268 | F22: =$A22+4 -> 46269 | G22: =$A22+5 -> 46270 | H22: =$A22+6 -> 46271
B23: =IFERROR(INDEX(Schedule!$B$4:$B$200,MATCH(B22,Schedule!$D$4:$D$200,0))&IF(COUNTIF(Schedule!$D$4:$D$200,B22)>1," +"&(COUNTIF(Schedule!$D$4:$D$200,B22)-1)&" more",""),"") | C23: =IFERROR(INDEX(Schedule!$B$4:$B$200,MATCH(C22,Schedule!$D$4:$D$200,0))&IF(COUNTIF(Schedule!$D$4:$D$200,C22)>1," +"&(COUNTIF(Schedule!$D$4:$D$200,C22)-1)&" more",""),"") | D23: =IFERROR(INDEX(Schedule!$B$4:$B$200,MATCH(D22,Schedule!$D$4:$D$200,0))&IF(COUNTIF(Schedule!$D$4:$D$200,D22)>1," +"&(COUNTIF(Schedule!$D$4:$D$200,D22)-1)&" more",""),"") | E23: =IFERROR(INDEX(Schedule!$B$4:$B$200,MATCH(E22,Schedule!$D$4:$D$200,0))&IF(COUNTIF(Schedule!$D$4:$D$200,E22)>1," +"&(COUNTIF(Schedule!$D$4:$D$200,E22)-1)&" more",""),"") | F23: =IFERROR(INDEX(Schedule!$B$4:$B$200,MATCH(F22,Schedule!$D$4:$D$200,0))&IF(COUNTIF(Schedule!$D$4:$D$200,F22)>1," +"&(COUNTIF(Schedule!$D$4:$D$200,F22)-1)&" more",""),"") | G23: =IFERROR(INDEX(Schedule!$B$4:$B$200,MATCH(G22,Schedule!$D$4:$D$200,0))&IF(COUNTIF(Schedule!$D$4:$D$200,G22)>1," +"&(COUNTIF(Schedule!$D$4:$D$200,G22)-1)&" more",""),"") | H23: =IFERROR(INDEX(Schedule!$B$4:$B$200,MATCH(H22,Schedule!$D$4:$D$200,0))&IF(COUNTIF(Schedule!$D$4:$D$200,H22)>1," +"&(COUNTIF(Schedule!$D$4:$D$200,H22)-1)&" more",""),"")
A24: =(Settings!$C$36-(WEEKDAY(Settings!$C$36,2)-1))+70 -> 46272 | B24: =$A24+0 -> 46272 | C24: =$A24+1 -> 46273 | D24: =$A24+2 -> 46274 | E24: =$A24+3 -> 46275 | F24: =$A24+4 -> 46276 | G24: =$A24+5 -> 46277 | H24: =$A24+6 -> 46278
B25: =IFERROR(INDEX(Schedule!$B$4:$B$200,MATCH(B24,Schedule!$D$4:$D$200,0))&IF(COUNTIF(Schedule!$D$4:$D$200,B24)>1," +"&(COUNTIF(Schedule!$D$4:$D$200,B24)-1)&" more",""),"") | C25: =IFERROR(INDEX(Schedule!$B$4:$B$200,MATCH(C24,Schedule!$D$4:$D$200,0))&IF(COUNTIF(Schedule!$D$4:$D$200,C24)>1," +"&(COUNTIF(Schedule!$D$4:$D$200,C24)-1)&" more",""),"") | D25: =IFERROR(INDEX(Schedule!$B$4:$B$200,MATCH(D24,Schedule!$D$4:$D$200,0))&IF(COUNTIF(Schedule!$D$4:$D$200,D24)>1," +"&(COUNTIF(Schedule!$D$4:$D$200,D24)-1)&" more",""),"") | E25: =IFERROR(INDEX(Schedule!$B$4:$B$200,MATCH(E24,Schedule!$D$4:$D$200,0))&IF(COUNTIF(Schedule!$D$4:$D$200,E24)>1," +"&(COUNTIF(Schedule!$D$4:$D$200,E24)-1)&" more",""),"") | F25: =IFERROR(INDEX(Schedule!$B$4:$B$200,MATCH(F24,Schedule!$D$4:$D$200,0))&IF(COUNTIF(Schedule!$D$4:$D$200,F24)>1," +"&(COUNTIF(Schedule!$D$4:$D$200,F24)-1)&" more",""),"") | G25: =IFERROR(INDEX(Schedule!$B$4:$B$200,MATCH(G24,Schedule!$D$4:$D$200,0))&IF(COUNTIF(Schedule!$D$4:$D$200,G24)>1," +"&(COUNTIF(Schedule!$D$4:$D$200,G24)-1)&" more",""),"") | H25: =IFERROR(INDEX(Schedule!$B$4:$B$200,MATCH(H24,Schedule!$D$4:$D$200,0))&IF(COUNTIF(Schedule!$D$4:$D$200,H24)>1," +"&(COUNTIF(Schedule!$D$4:$D$200,H24)-1)&" more",""),"")
A26: =(Settings!$C$36-(WEEKDAY(Settings!$C$36,2)-1))+77 -> 46279 | B26: =$A26+0 -> 46279 | C26: =$A26+1 -> 46280 | D26: =$A26+2 -> 46281 | E26: =$A26+3 -> 46282 | F26: =$A26+4 -> 46283 | G26: =$A26+5 -> 46284 | H26: =$A26+6 -> 46285
B27: =IFERROR(INDEX(Schedule!$B$4:$B$200,MATCH(B26,Schedule!$D$4:$D$200,0))&IF(COUNTIF(Schedule!$D$4:$D$200,B26)>1," +"&(COUNTIF(Schedule!$D$4:$D$200,B26)-1)&" more",""),"") | C27: =IFERROR(INDEX(Schedule!$B$4:$B$200,MATCH(C26,Schedule!$D$4:$D$200,0))&IF(COUNTIF(Schedule!$D$4:$D$200,C26)>1," +"&(COUNTIF(Schedule!$D$4:$D$200,C26)-1)&" more",""),"") | D27: =IFERROR(INDEX(Schedule!$B$4:$B$200,MATCH(D26,Schedule!$D$4:$D$200,0))&IF(COUNTIF(Schedule!$D$4:$D$200,D26)>1," +"&(COUNTIF(Schedule!$D$4:$D$200,D26)-1)&" more",""),"") | E27: =IFERROR(INDEX(Schedule!$B$4:$B$200,MATCH(E26,Schedule!$D$4:$D$200,0))&IF(COUNTIF(Schedule!$D$4:$D$200,E26)>1," +"&(COUNTIF(Schedule!$D$4:$D$200,E26)-1)&" more",""),"") | F27: =IFERROR(INDEX(Schedule!$B$4:$B$200,MATCH(F26,Schedule!$D$4:$D$200,0))&IF(COUNTIF(Schedule!$D$4:$D$200,F26)>1," +"&(COUNTIF(Schedule!$D$4:$D$200,F26)-1)&" more",""),"") | G27: =IFERROR(INDEX(Schedule!$B$4:$B$200,MATCH(G26,Schedule!$D$4:$D$200,0))&IF(COUNTIF(Schedule!$D$4:$D$200,G26)>1," +"&(COUNTIF(Schedule!$D$4:$D$200,G26)-1)&" more",""),"") | H27: =IFERROR(INDEX(Schedule!$B$4:$B$200,MATCH(H26,Schedule!$D$4:$D$200,0))&IF(COUNTIF(Schedule!$D$4:$D$200,H26)>1," +"&(COUNTIF(Schedule!$D$4:$D$200,H26)-1)&" more",""),"")
A28: =(Settings!$C$36-(WEEKDAY(Settings!$C$36,2)-1))+84 -> 46286 | B28: =$A28+0 -> 46286 | C28: =$A28+1 -> 46287 | D28: =$A28+2 -> 46288 | E28: =$A28+3 -> 46289 | F28: =$A28+4 -> 46290 | G28: =$A28+5 -> 46291 | H28: =$A28+6 -> 46292
B29: =IFERROR(INDEX(Schedule!$B$4:$B$200,MATCH(B28,Schedule!$D$4:$D$200,0))&IF(COUNTIF(Schedule!$D$4:$D$200,B28)>1," +"&(COUNTIF(Schedule!$D$4:$D$200,B28)-1)&" more",""),"") | C29: =IFERROR(INDEX(Schedule!$B$4:$B$200,MATCH(C28,Schedule!$D$4:$D$200,0))&IF(COUNTIF(Schedule!$D$4:$D$200,C28)>1," +"&(COUNTIF(Schedule!$D$4:$D$200,C28)-1)&" more",""),"") | D29: =IFERROR(INDEX(Schedule!$B$4:$B$200,MATCH(D28,Schedule!$D$4:$D$200,0))&IF(COUNTIF(Schedule!$D$4:$D$200,D28)>1," +"&(COUNTIF(Schedule!$D$4:$D$200,D28)-1)&" more",""),"") | E29: =IFERROR(INDEX(Schedule!$B$4:$B$200,MATCH(E28,Schedule!$D$4:$D$200,0))&IF(COUNTIF(Schedule!$D$4:$D$200,E28)>1," +"&(COUNTIF(Schedule!$D$4:$D$200,E28)-1)&" more",""),"") | F29: =IFERROR(INDEX(Schedule!$B$4:$B$200,MATCH(F28,Schedule!$D$4:$D$200,0))&IF(COUNTIF(Schedule!$D$4:$D$200,F28)>1," +"&(COUNTIF(Schedule!$D$4:$D$200,F28)-1)&" more",""),"") | G29: =IFERROR(INDEX(Schedule!$B$4:$B$200,MATCH(G28,Schedule!$D$4:$D$200,0))&IF(COUNTIF(Schedule!$D$4:$D$200,G28)>1," +"&(COUNTIF(Schedule!$D$4:$D$200,G28)-1)&" more",""),"") | H29: =IFERROR(INDEX(Schedule!$B$4:$B$200,MATCH(H28,Schedule!$D$4:$D$200,0))&IF(COUNTIF(Schedule!$D$4:$D$200,H28)>1," +"&(COUNTIF(Schedule!$D$4:$D$200,H28)-1)&" more",""),"")
A30: =(Settings!$C$36-(WEEKDAY(Settings!$C$36,2)-1))+91 -> 46293 | B30: =$A30+0 -> 46293 | C30: =$A30+1 -> 46294 | D30: =$A30+2 -> 46295 | E30: =$A30+3 -> 46296 | F30: =$A30+4 -> 46297 | G30: =$A30+5 -> 46298 | H30: =$A30+6 -> 46299
B31: =IFERROR(INDEX(Schedule!$B$4:$B$200,MATCH(B30,Schedule!$D$4:$D$200,0))&IF(COUNTIF(Schedule!$D$4:$D$200,B30)>1," +"&(COUNTIF(Schedule!$D$4:$D$200,B30)-1)&" more",""),"") | C31: =IFERROR(INDEX(Schedule!$B$4:$B$200,MATCH(C30,Schedule!$D$4:$D$200,0))&IF(COUNTIF(Schedule!$D$4:$D$200,C30)>1," +"&(COUNTIF(Schedule!$D$4:$D$200,C30)-1)&" more",""),"") | D31: =IFERROR(INDEX(Schedule!$B$4:$B$200,MATCH(D30,Schedule!$D$4:$D$200,0))&IF(COUNTIF(Schedule!$D$4:$D$200,D30)>1," +"&(COUNTIF(Schedule!$D$4:$D$200,D30)-1)&" more",""),"") | E31: =IFERROR(INDEX(Schedule!$B$4:$B$200,MATCH(E30,Schedule!$D$4:$D$200,0))&IF(COUNTIF(Schedule!$D$4:$D$200,E30)>1," +"&(COUNTIF(Schedule!$D$4:$D$200,E30)-1)&" more",""),"") | F31: =IFERROR(INDEX(Schedule!$B$4:$B$200,MATCH(F30,Schedule!$D$4:$D$200,0))&IF(COUNTIF(Schedule!$D$4:$D$200,F30)>1," +"&(COUNTIF(Schedule!$D$4:$D$200,F30)-1)&" more",""),"") | G31: =IFERROR(INDEX(Schedule!$B$4:$B$200,MATCH(G30,Schedule!$D$4:$D$200,0))&IF(COUNTIF(Schedule!$D$4:$D$200,G30)>1," +"&(COUNTIF(Schedule!$D$4:$D$200,G30)-1)&" more",""),"") | H31: =IFERROR(INDEX(Schedule!$B$4:$B$200,MATCH(H30,Schedule!$D$4:$D$200,0))&IF(COUNTIF(Schedule!$D$4:$D$200,H30)>1," +"&(COUNTIF(Schedule!$D$4:$D$200,H30)-1)&" more",""),"")
A32: =(Settings!$C$36-(WEEKDAY(Settings!$C$36,2)-1))+98 -> 46300 | B32: =$A32+0 -> 46300 | C32: =$A32+1 -> 46301 | D32: =$A32+2 -> 46302 | E32: =$A32+3 -> 46303 | F32: =$A32+4 -> 46304 | G32: =$A32+5 -> 46305 | H32: =$A32+6 -> 46306
B33: =IFERROR(INDEX(Schedule!$B$4:$B$200,MATCH(B32,Schedule!$D$4:$D$200,0))&IF(COUNTIF(Schedule!$D$4:$D$200,B32)>1," +"&(COUNTIF(Schedule!$D$4:$D$200,B32)-1)&" more",""),"") | C33: =IFERROR(INDEX(Schedule!$B$4:$B$200,MATCH(C32,Schedule!$D$4:$D$200,0))&IF(COUNTIF(Schedule!$D$4:$D$200,C32)>1," +"&(COUNTIF(Schedule!$D$4:$D$200,C32)-1)&" more",""),"") | D33: =IFERROR(INDEX(Schedule!$B$4:$B$200,MATCH(D32,Schedule!$D$4:$D$200,0))&IF(COUNTIF(Schedule!$D$4:$D$200,D32)>1," +"&(COUNTIF(Schedule!$D$4:$D$200,D32)-1)&" more",""),"") | E33: =IFERROR(INDEX(Schedule!$B$4:$B$200,MATCH(E32,Schedule!$D$4:$D$200,0))&IF(COUNTIF(Schedule!$D$4:$D$200,E32)>1," +"&(COUNTIF(Schedule!$D$4:$D$200,E32)-1)&" more",""),"") | F33: =IFERROR(INDEX(Schedule!$B$4:$B$200,MATCH(F32,Schedule!$D$4:$D$200,0))&IF(COUNTIF(Schedule!$D$4:$D$200,F32)>1," +"&(COUNTIF(Schedule!$D$4:$D$200,F32)-1)&" more",""),"") | G33: =IFERROR(INDEX(Schedule!$B$4:$B$200,MATCH(G32,Schedule!$D$4:$D$200,0))&IF(COUNTIF(Schedule!$D$4:$D$200,G32)>1," +"&(COUNTIF(Schedule!$D$4:$D$200,G32)-1)&" more",""),"") | H33: =IFERROR(INDEX(Schedule!$B$4:$B$200,MATCH(H32,Schedule!$D$4:$D$200,0))&IF(COUNTIF(Schedule!$D$4:$D$200,H32)>1," +"&(COUNTIF(Schedule!$D$4:$D$200,H32)-1)&" more",""),"")
A34: =(Settings!$C$36-(WEEKDAY(Settings!$C$36,2)-1))+105 -> 46307 | B34: =$A34+0 -> 46307 | C34: =$A34+1 -> 46308 | D34: =$A34+2 -> 46309 | E34: =$A34+3 -> 46310 | F34: =$A34+4 -> 46311 | G34: =$A34+5 -> 46312 | H34: =$A34+6 -> 46313
B35: =IFERROR(INDEX(Schedule!$B$4:$B$200,MATCH(B34,Schedule!$D$4:$D$200,0))&IF(COUNTIF(Schedule!$D$4:$D$200,B34)>1," +"&(COUNTIF(Schedule!$D$4:$D$200,B34)-1)&" more",""),"") | C35: =IFERROR(INDEX(Schedule!$B$4:$B$200,MATCH(C34,Schedule!$D$4:$D$200,0))&IF(COUNTIF(Schedule!$D$4:$D$200,C34)>1," +"&(COUNTIF(Schedule!$D$4:$D$200,C34)-1)&" more",""),"") | D35: =IFERROR(INDEX(Schedule!$B$4:$B$200,MATCH(D34,Schedule!$D$4:$D$200,0))&IF(COUNTIF(Schedule!$D$4:$D$200,D34)>1," +"&(COUNTIF(Schedule!$D$4:$D$200,D34)-1)&" more",""),"") | E35: =IFERROR(INDEX(Schedule!$B$4:$B$200,MATCH(E34,Schedule!$D$4:$D$200,0))&IF(COUNTIF(Schedule!$D$4:$D$200,E34)>1," +"&(COUNTIF(Schedule!$D$4:$D$200,E34)-1)&" more",""),"") | F35: =IFERROR(INDEX(Schedule!$B$4:$B$200,MATCH(F34,Schedule!$D$4:$D$200,0))&IF(COUNTIF(Schedule!$D$4:$D$200,F34)>1," +"&(COUNTIF(Schedule!$D$4:$D$200,F34)-1)&" more",""),"") | G35: =IFERROR(INDEX(Schedule!$B$4:$B$200,MATCH(G34,Schedule!$D$4:$D$200,0))&IF(COUNTIF(Schedule!$D$4:$D$200,G34)>1," +"&(COUNTIF(Schedule!$D$4:$D$200,G34)-1)&" more",""),"") | H35: =IFERROR(INDEX(Schedule!$B$4:$B$200,MATCH(H34,Schedule!$D$4:$D$200,0))&IF(COUNTIF(Schedule!$D$4:$D$200,H34)>1," +"&(COUNTIF(Schedule!$D$4:$D$200,H34)-1)&" more",""),"")
A36: =(Settings!$C$36-(WEEKDAY(Settings!$C$36,2)-1))+112 -> 46314 | B36: =$A36+0 -> 46314 | C36: =$A36+1 -> 46315 | D36: =$A36+2 -> 46316 | E36: =$A36+3 -> 46317 | F36: =$A36+4 -> 46318 | G36: =$A36+5 -> 46319 | H36: =$A36+6 -> 46320
B37: =IFERROR(INDEX(Schedule!$B$4:$B$200,MATCH(B36,Schedule!$D$4:$D$200,0))&IF(COUNTIF(Schedule!$D$4:$D$200,B36)>1," +"&(COUNTIF(Schedule!$D$4:$D$200,B36)-1)&" more",""),"") | C37: =IFERROR(INDEX(Schedule!$B$4:$B$200,MATCH(C36,Schedule!$D$4:$D$200,0))&IF(COUNTIF(Schedule!$D$4:$D$200,C36)>1," +"&(COUNTIF(Schedule!$D$4:$D$200,C36)-1)&" more",""),"") | D37: =IFERROR(INDEX(Schedule!$B$4:$B$200,MATCH(D36,Schedule!$D$4:$D$200,0))&IF(COUNTIF(Schedule!$D$4:$D$200,D36)>1," +"&(COUNTIF(Schedule!$D$4:$D$200,D36)-1)&" more",""),"") | E37: =IFERROR(INDEX(Schedule!$B$4:$B$200,MATCH(E36,Schedule!$D$4:$D$200,0))&IF(COUNTIF(Schedule!$D$4:$D$200,E36)>1," +"&(COUNTIF(Schedule!$D$4:$D$200,E36)-1)&" more",""),"") | F37: =IFERROR(INDEX(Schedule!$B$4:$B$200,MATCH(F36,Schedule!$D$4:$D$200,0))&IF(COUNTIF(Schedule!$D$4:$D$200,F36)>1," +"&(COUNTIF(Schedule!$D$4:$D$200,F36)-1)&" more",""),"") | G37: =IFERROR(INDEX(Schedule!$B$4:$B$200,MATCH(G36,Schedule!$D$4:$D$200,0))&IF(COUNTIF(Schedule!$D$4:$D$200,G36)>1," +"&(COUNTIF(Schedule!$D$4:$D$200,G36)-1)&" more",""),"") | H37: =IFERROR(INDEX(Schedule!$B$4:$B$200,MATCH(H36,Schedule!$D$4:$D$200,0))&IF(COUNTIF(Schedule!$D$4:$D$200,H36)>1," +"&(COUNTIF(Schedule!$D$4:$D$200,H36)-1)&" more",""),"")
A38: =(Settings!$C$36-(WEEKDAY(Settings!$C$36,2)-1))+119 -> 46321 | B38: =$A38+0 -> 46321 | C38: =$A38+1 -> 46322 | D38: =$A38+2 -> 46323 | E38: =$A38+3 -> 46324 | F38: =$A38+4 -> 46325 | G38: =$A38+5 -> 46326 | H38: =$A38+6 -> 46327
B39: =IFERROR(INDEX(Schedule!$B$4:$B$200,MATCH(B38,Schedule!$D$4:$D$200,0))&IF(COUNTIF(Schedule!$D$4:$D$200,B38)>1," +"&(COUNTIF(Schedule!$D$4:$D$200,B38)-1)&" more",""),"") | C39: =IFERROR(INDEX(Schedule!$B$4:$B$200,MATCH(C38,Schedule!$D$4:$D$200,0))&IF(COUNTIF(Schedule!$D$4:$D$200,C38)>1," +"&(COUNTIF(Schedule!$D$4:$D$200,C38)-1)&" more",""),"") | D39: =IFERROR(INDEX(Schedule!$B$4:$B$200,MATCH(D38,Schedule!$D$4:$D$200,0))&IF(COUNTIF(Schedule!$D$4:$D$200,D38)>1," +"&(COUNTIF(Schedule!$D$4:$D$200,D38)-1)&" more",""),"") | E39: =IFERROR(INDEX(Schedule!$B$4:$B$200,MATCH(E38,Schedule!$D$4:$D$200,0))&IF(COUNTIF(Schedule!$D$4:$D$200,E38)>1," +"&(COUNTIF(Schedule!$D$4:$D$200,E38)-1)&" more",""),"") | F39: =IFERROR(INDEX(Schedule!$B$4:$B$200,MATCH(F38,Schedule!$D$4:$D$200,0))&IF(COUNTIF(Schedule!$D$4:$D$200,F38)>1," +"&(COUNTIF(Schedule!$D$4:$D$200,F38)-1)&" more",""),"") | G39: =IFERROR(INDEX(Schedule!$B$4:$B$200,MATCH(G38,Schedule!$D$4:$D$200,0))&IF(COUNTIF(Schedule!$D$4:$D$200,G38)>1," +"&(COUNTIF(Schedule!$D$4:$D$200,G38)-1)&" more",""),"") | H39: =IFERROR(INDEX(Schedule!$B$4:$B$200,MATCH(H38,Schedule!$D$4:$D$200,0))&IF(COUNTIF(Schedule!$D$4:$D$200,H38)>1," +"&(COUNTIF(Schedule!$D$4:$D$200,H38)-1)&" more",""),"")
A40: =(Settings!$C$36-(WEEKDAY(Settings!$C$36,2)-1))+126 -> 46328 | B40: =$A40+0 -> 46328 | C40: =$A40+1 -> 46329 | D40: =$A40+2 -> 46330 | E40: =$A40+3 -> 46331 | F40: =$A40+4 -> 46332 | G40: =$A40+5 -> 46333 | H40: =$A40+6 -> 46334
B41: =IFERROR(INDEX(Schedule!$B$4:$B$200,MATCH(B40,Schedule!$D$4:$D$200,0))&IF(COUNTIF(Schedule!$D$4:$D$200,B40)>1," +"&(COUNTIF(Schedule!$D$4:$D$200,B40)-1)&" more",""),"") | C41: =IFERROR(INDEX(Schedule!$B$4:$B$200,MATCH(C40,Schedule!$D$4:$D$200,0))&IF(COUNTIF(Schedule!$D$4:$D$200,C40)>1," +"&(COUNTIF(Schedule!$D$4:$D$200,C40)-1)&" more",""),"") | D41: =IFERROR(INDEX(Schedule!$B$4:$B$200,MATCH(D40,Schedule!$D$4:$D$200,0))&IF(COUNTIF(Schedule!$D$4:$D$200,D40)>1," +"&(COUNTIF(Schedule!$D$4:$D$200,D40)-1)&" more",""),"") | E41: =IFERROR(INDEX(Schedule!$B$4:$B$200,MATCH(E40,Schedule!$D$4:$D$200,0))&IF(COUNTIF(Schedule!$D$4:$D$200,E40)>1," +"&(COUNTIF(Schedule!$D$4:$D$200,E40)-1)&" more",""),"") | F41: =IFERROR(INDEX(Schedule!$B$4:$B$200,MATCH(F40,Schedule!$D$4:$D$200,0))&IF(COUNTIF(Schedule!$D$4:$D$200,F40)>1," +"&(COUNTIF(Schedule!$D$4:$D$200,F40)-1)&" more",""),"") | G41: =IFERROR(INDEX(Schedule!$B$4:$B$200,MATCH(G40,Schedule!$D$4:$D$200,0))&IF(COUNTIF(Schedule!$D$4:$D$200,G40)>1," +"&(COUNTIF(Schedule!$D$4:$D$200,G40)-1)&" more",""),"") | H41: =IFERROR(INDEX(Schedule!$B$4:$B$200,MATCH(H40,Schedule!$D$4:$D$200,0))&IF(COUNTIF(Schedule!$D$4:$D$200,H40)>1," +"&(COUNTIF(Schedule!$D$4:$D$200,H40)-1)&" more",""),"")
A42: =(Settings!$C$36-(WEEKDAY(Settings!$C$36,2)-1))+133 -> 46335 | B42: =$A42+0 -> 46335 | C42: =$A42+1 -> 46336 | D42: =$A42+2 -> 46337 | E42: =$A42+3 -> 46338 | F42: =$A42+4 -> 46339 | G42: =$A42+5 -> 46340 | H42: =$A42+6 -> 46341
B43: =IFERROR(INDEX(Schedule!$B$4:$B$200,MATCH(B42,Schedule!$D$4:$D$200,0))&IF(COUNTIF(Schedule!$D$4:$D$200,B42)>1," +"&(COUNTIF(Schedule!$D$4:$D$200,B42)-1)&" more",""),"") | C43: =IFERROR(INDEX(Schedule!$B$4:$B$200,MATCH(C42,Schedule!$D$4:$D$200,0))&IF(COUNTIF(Schedule!$D$4:$D$200,C42)>1," +"&(COUNTIF(Schedule!$D$4:$D$200,C42)-1)&" more",""),"") | D43: =IFERROR(INDEX(Schedule!$B$4:$B$200,MATCH(D42,Schedule!$D$4:$D$200,0))&IF(COUNTIF(Schedule!$D$4:$D$200,D42)>1," +"&(COUNTIF(Schedule!$D$4:$D$200,D42)-1)&" more",""),"") | E43: =IFERROR(INDEX(Schedule!$B$4:$B$200,MATCH(E42,Schedule!$D$4:$D$200,0))&IF(COUNTIF(Schedule!$D$4:$D$200,E42)>1," +"&(COUNTIF(Schedule!$D$4:$D$200,E42)-1)&" more",""),"") | F43: =IFERROR(INDEX(Schedule!$B$4:$B$200,MATCH(F42,Schedule!$D$4:$D$200,0))&IF(COUNTIF(Schedule!$D$4:$D$200,F42)>1," +"&(COUNTIF(Schedule!$D$4:$D$200,F42)-1)&" more",""),"") | G43: =IFERROR(INDEX(Schedule!$B$4:$B$200,MATCH(G42,Schedule!$D$4:$D$200,0))&IF(COUNTIF(Schedule!$D$4:$D$200,G42)>1," +"&(COUNTIF(Schedule!$D$4:$D$200,G42)-1)&" more",""),"") | H43: =IFERROR(INDEX(Schedule!$B$4:$B$200,MATCH(H42,Schedule!$D$4:$D$200,0))&IF(COUNTIF(Schedule!$D$4:$D$200,H42)>1," +"&(COUNTIF(Schedule!$D$4:$D$200,H42)-1)&" more",""),"")
A44: =(Settings!$C$36-(WEEKDAY(Settings!$C$36,2)-1))+140 -> 46342 | B44: =$A44+0 -> 46342 | C44: =$A44+1 -> 46343 | D44: =$A44+2 -> 46344 | E44: =$A44+3 -> 46345 | F44: =$A44+4 -> 46346 | G44: =$A44+5 -> 46347 | H44: =$A44+6 -> 46348
B45: =IFERROR(INDEX(Schedule!$B$4:$B$200,MATCH(B44,Schedule!$D$4:$D$200,0))&IF(COUNTIF(Schedule!$D$4:$D$200,B44)>1," +"&(COUNTIF(Schedule!$D$4:$D$200,B44)-1)&" more",""),"") | C45: =IFERROR(INDEX(Schedule!$B$4:$B$200,MATCH(C44,Schedule!$D$4:$D$200,0))&IF(COUNTIF(Schedule!$D$4:$D$200,C44)>1," +"&(COUNTIF(Schedule!$D$4:$D$200,C44)-1)&" more",""),"") | D45: =IFERROR(INDEX(Schedule!$B$4:$B$200,MATCH(D44,Schedule!$D$4:$D$200,0))&IF(COUNTIF(Schedule!$D$4:$D$200,D44)>1," +"&(COUNTIF(Schedule!$D$4:$D$200,D44)-1)&" more",""),"") | E45: =IFERROR(INDEX(Schedule!$B$4:$B$200,MATCH(E44,Schedule!$D$4:$D$200,0))&IF(COUNTIF(Schedule!$D$4:$D$200,E44)>1," +"&(COUNTIF(Schedule!$D$4:$D$200,E44)-1)&" more",""),"") | F45: =IFERROR(INDEX(Schedule!$B$4:$B$200,MATCH(F44,Schedule!$D$4:$D$200,0))&IF(COUNTIF(Schedule!$D$4:$D$200,F44)>1," +"&(COUNTIF(Schedule!$D$4:$D$200,F44)-1)&" more",""),"") | G45: =IFERROR(INDEX(Schedule!$B$4:$B$200,MATCH(G44,Schedule!$D$4:$D$200,0))&IF(COUNTIF(Schedule!$D$4:$D$200,G44)>1," +"&(COUNTIF(Schedule!$D$4:$D$200,G44)-1)&" more",""),"") | H45: =IFERROR(INDEX(Schedule!$B$4:$B$200,MATCH(H44,Schedule!$D$4:$D$200,0))&IF(COUNTIF(Schedule!$D$4:$D$200,H44)>1," +"&(COUNTIF(Schedule!$D$4:$D$200,H44)-1)&" more",""),"")
A46: =(Settings!$C$36-(WEEKDAY(Settings!$C$36,2)-1))+147 -> 46349 | B46: =$A46+0 -> 46349 | C46: =$A46+1 -> 46350 | D46: =$A46+2 -> 46351 | E46: =$A46+3 -> 46352 | F46: =$A46+4 -> 46353 | G46: =$A46+5 -> 46354 | H46: =$A46+6 -> 46355
B47: =IFERROR(INDEX(Schedule!$B$4:$B$200,MATCH(B46,Schedule!$D$4:$D$200,0))&IF(COUNTIF(Schedule!$D$4:$D$200,B46)>1," +"&(COUNTIF(Schedule!$D$4:$D$200,B46)-1)&" more",""),"") | C47: =IFERROR(INDEX(Schedule!$B$4:$B$200,MATCH(C46,Schedule!$D$4:$D$200,0))&IF(COUNTIF(Schedule!$D$4:$D$200,C46)>1," +"&(COUNTIF(Schedule!$D$4:$D$200,C46)-1)&" more",""),"") | D47: =IFERROR(INDEX(Schedule!$B$4:$B$200,MATCH(D46,Schedule!$D$4:$D$200,0))&IF(COUNTIF(Schedule!$D$4:$D$200,D46)>1," +"&(COUNTIF(Schedule!$D$4:$D$200,D46)-1)&" more",""),"") | E47: =IFERROR(INDEX(Schedule!$B$4:$B$200,MATCH(E46,Schedule!$D$4:$D$200,0))&IF(COUNTIF(Schedule!$D$4:$D$200,E46)>1," +"&(COUNTIF(Schedule!$D$4:$D$200,E46)-1)&" more",""),"") | F47: =IFERROR(INDEX(Schedule!$B$4:$B$200,MATCH(F46,Schedule!$D$4:$D$200,0))&IF(COUNTIF(Schedule!$D$4:$D$200,F46)>1," +"&(COUNTIF(Schedule!$D$4:$D$200,F46)-1)&" more",""),"") | G47: =IFERROR(INDEX(Schedule!$B$4:$B$200,MATCH(G46,Schedule!$D$4:$D$200,0))&IF(COUNTIF(Schedule!$D$4:$D$200,G46)>1," +"&(COUNTIF(Schedule!$D$4:$D$200,G46)-1)&" more",""),"") | H47: =IFERROR(INDEX(Schedule!$B$4:$B$200,MATCH(H46,Schedule!$D$4:$D$200,0))&IF(COUNTIF(Schedule!$D$4:$D$200,H46)>1," +"&(COUNTIF(Schedule!$D$4:$D$200,H46)-1)&" more",""),"")
A48: =(Settings!$C$36-(WEEKDAY(Settings!$C$36,2)-1))+154 -> 46356 | B48: =$A48+0 -> 46356 | C48: =$A48+1 -> 46357 | D48: =$A48+2 -> 46358 | E48: =$A48+3 -> 46359 | F48: =$A48+4 -> 46360 | G48: =$A48+5 -> 46361 | H48: =$A48+6 -> 46362
B49: =IFERROR(INDEX(Schedule!$B$4:$B$200,MATCH(B48,Schedule!$D$4:$D$200,0))&IF(COUNTIF(Schedule!$D$4:$D$200,B48)>1," +"&(COUNTIF(Schedule!$D$4:$D$200,B48)-1)&" more",""),"") | C49: =IFERROR(INDEX(Schedule!$B$4:$B$200,MATCH(C48,Schedule!$D$4:$D$200,0))&IF(COUNTIF(Schedule!$D$4:$D$200,C48)>1," +"&(COUNTIF(Schedule!$D$4:$D$200,C48)-1)&" more",""),"") | D49: =IFERROR(INDEX(Schedule!$B$4:$B$200,MATCH(D48,Schedule!$D$4:$D$200,0))&IF(COUNTIF(Schedule!$D$4:$D$200,D48)>1," +"&(COUNTIF(Schedule!$D$4:$D$200,D48)-1)&" more",""),"") | E49: =IFERROR(INDEX(Schedule!$B$4:$B$200,MATCH(E48,Schedule!$D$4:$D$200,0))&IF(COUNTIF(Schedule!$D$4:$D$200,E48)>1," +"&(COUNTIF(Schedule!$D$4:$D$200,E48)-1)&" more",""),"") | F49: =IFERROR(INDEX(Schedule!$B$4:$B$200,MATCH(F48,Schedule!$D$4:$D$200,0))&IF(COUNTIF(Schedule!$D$4:$D$200,F48)>1," +"&(COUNTIF(Schedule!$D$4:$D$200,F48)-1)&" more",""),"") | G49: =IFERROR(INDEX(Schedule!$B$4:$B$200,MATCH(G48,Schedule!$D$4:$D$200,0))&IF(COUNTIF(Schedule!$D$4:$D$200,G48)>1," +"&(COUNTIF(Schedule!$D$4:$D$200,G48)-1)&" more",""),"") | H49: =IFERROR(INDEX(Schedule!$B$4:$B$200,MATCH(H48,Schedule!$D$4:$D$200,0))&IF(COUNTIF(Schedule!$D$4:$D$200,H48)>1," +"&(COUNTIF(Schedule!$D$4:$D$200,H48)-1)&" more",""),"")
A50: =(Settings!$C$36-(WEEKDAY(Settings!$C$36,2)-1))+161 -> 46363 | B50: =$A50+0 -> 46363 | C50: =$A50+1 -> 46364 | D50: =$A50+2 -> 46365 | E50: =$A50+3 -> 46366 | F50: =$A50+4 -> 46367 | G50: =$A50+5 -> 46368 | H50: =$A50+6 -> 46369
B51: =IFERROR(INDEX(Schedule!$B$4:$B$200,MATCH(B50,Schedule!$D$4:$D$200,0))&IF(COUNTIF(Schedule!$D$4:$D$200,B50)>1," +"&(COUNTIF(Schedule!$D$4:$D$200,B50)-1)&" more",""),"") | C51: =IFERROR(INDEX(Schedule!$B$4:$B$200,MATCH(C50,Schedule!$D$4:$D$200,0))&IF(COUNTIF(Schedule!$D$4:$D$200,C50)>1," +"&(COUNTIF(Schedule!$D$4:$D$200,C50)-1)&" more",""),"") | D51: =IFERROR(INDEX(Schedule!$B$4:$B$200,MATCH(D50,Schedule!$D$4:$D$200,0))&IF(COUNTIF(Schedule!$D$4:$D$200,D50)>1," +"&(COUNTIF(Schedule!$D$4:$D$200,D50)-1)&" more",""),"") | E51: =IFERROR(INDEX(Schedule!$B$4:$B$200,MATCH(E50,Schedule!$D$4:$D$200,0))&IF(COUNTIF(Schedule!$D$4:$D$200,E50)>1," +"&(COUNTIF(Schedule!$D$4:$D$200,E50)-1)&" more",""),"") | F51: =IFERROR(INDEX(Schedule!$B$4:$B$200,MATCH(F50,Schedule!$D$4:$D$200,0))&IF(COUNTIF(Schedule!$D$4:$D$200,F50)>1," +"&(COUNTIF(Schedule!$D$4:$D$200,F50)-1)&" more",""),"") | G51: =IFERROR(INDEX(Schedule!$B$4:$B$200,MATCH(G50,Schedule!$D$4:$D$200,0))&IF(COUNTIF(Schedule!$D$4:$D$200,G50)>1," +"&(COUNTIF(Schedule!$D$4:$D$200,G50)-1)&" more",""),"") | H51: =IFERROR(INDEX(Schedule!$B$4:$B$200,MATCH(H50,Schedule!$D$4:$D$200,0))&IF(COUNTIF(Schedule!$D$4:$D$200,H50)>1," +"&(COUNTIF(Schedule!$D$4:$D$200,H50)-1)&" more",""),"")
A52: =(Settings!$C$36-(WEEKDAY(Settings!$C$36,2)-1))+168 -> 46370 | B52: =$A52+0 -> 46370 | C52: =$A52+1 -> 46371 | D52: =$A52+2 -> 46372 | E52: =$A52+3 -> 46373 | F52: =$A52+4 -> 46374 | G52: =$A52+5 -> 46375 | H52: =$A52+6 -> 46376
B53: =IFERROR(INDEX(Schedule!$B$4:$B$200,MATCH(B52,Schedule!$D$4:$D$200,0))&IF(COUNTIF(Schedule!$D$4:$D$200,B52)>1," +"&(COUNTIF(Schedule!$D$4:$D$200,B52)-1)&" more",""),"") | C53: =IFERROR(INDEX(Schedule!$B$4:$B$200,MATCH(C52,Schedule!$D$4:$D$200,0))&IF(COUNTIF(Schedule!$D$4:$D$200,C52)>1," +"&(COUNTIF(Schedule!$D$4:$D$200,C52)-1)&" more",""),"") | D53: =IFERROR(INDEX(Schedule!$B$4:$B$200,MATCH(D52,Schedule!$D$4:$D$200,0))&IF(COUNTIF(Schedule!$D$4:$D$200,D52)>1," +"&(COUNTIF(Schedule!$D$4:$D$200,D52)-1)&" more",""),"") | E53: =IFERROR(INDEX(Schedule!$B$4:$B$200,MATCH(E52,Schedule!$D$4:$D$200,0))&IF(COUNTIF(Schedule!$D$4:$D$200,E52)>1," +"&(COUNTIF(Schedule!$D$4:$D$200,E52)-1)&" more",""),"") | F53: =IFERROR(INDEX(Schedule!$B$4:$B$200,MATCH(F52,Schedule!$D$4:$D$200,0))&IF(COUNTIF(Schedule!$D$4:$D$200,F52)>1," +"&(COUNTIF(Schedule!$D$4:$D$200,F52)-1)&" more",""),"") | G53: =IFERROR(INDEX(Schedule!$B$4:$B$200,MATCH(G52,Schedule!$D$4:$D$200,0))&IF(COUNTIF(Schedule!$D$4:$D$200,G52)>1," +"&(COUNTIF(Schedule!$D$4:$D$200,G52)-1)&" more",""),"") | H53: =IFERROR(INDEX(Schedule!$B$4:$B$200,MATCH(H52,Schedule!$D$4:$D$200,0))&IF(COUNTIF(Schedule!$D$4:$D$200,H52)>1," +"&(COUNTIF(Schedule!$D$4:$D$200,H52)-1)&" more",""),"")
A54: =(Settings!$C$36-(WEEKDAY(Settings!$C$36,2)-1))+175 -> 46377 | B54: =$A54+0 -> 46377 | C54: =$A54+1 -> 46378 | D54: =$A54+2 -> 46379 | E54: =$A54+3 -> 46380 | F54: =$A54+4 -> 46381 | G54: =$A54+5 -> 46382 | H54: =$A54+6 -> 46383
B55: =IFERROR(INDEX(Schedule!$B$4:$B$200,MATCH(B54,Schedule!$D$4:$D$200,0))&IF(COUNTIF(Schedule!$D$4:$D$200,B54)>1," +"&(COUNTIF(Schedule!$D$4:$D$200,B54)-1)&" more",""),"") | C55: =IFERROR(INDEX(Schedule!$B$4:$B$200,MATCH(C54,Schedule!$D$4:$D$200,0))&IF(COUNTIF(Schedule!$D$4:$D$200,C54)>1," +"&(COUNTIF(Schedule!$D$4:$D$200,C54)-1)&" more",""),"") | D55: =IFERROR(INDEX(Schedule!$B$4:$B$200,MATCH(D54,Schedule!$D$4:$D$200,0))&IF(COUNTIF(Schedule!$D$4:$D$200,D54)>1," +"&(COUNTIF(Schedule!$D$4:$D$200,D54)-1)&" more",""),"") | E55: =IFERROR(INDEX(Schedule!$B$4:$B$200,MATCH(E54,Schedule!$D$4:$D$200,0))&IF(COUNTIF(Schedule!$D$4:$D$200,E54)>1," +"&(COUNTIF(Schedule!$D$4:$D$200,E54)-1)&" more",""),"") | F55: =IFERROR(INDEX(Schedule!$B$4:$B$200,MATCH(F54,Schedule!$D$4:$D$200,0))&IF(COUNTIF(Schedule!$D$4:$D$200,F54)>1," +"&(COUNTIF(Schedule!$D$4:$D$200,F54)-1)&" more",""),"") | G55: =IFERROR(INDEX(Schedule!$B$4:$B$200,MATCH(G54,Schedule!$D$4:$D$200,0))&IF(COUNTIF(Schedule!$D$4:$D$200,G54)>1," +"&(COUNTIF(Schedule!$D$4:$D$200,G54)-1)&" more",""),"") | H55: =IFERROR(INDEX(Schedule!$B$4:$B$200,MATCH(H54,Schedule!$D$4:$D$200,0))&IF(COUNTIF(Schedule!$D$4:$D$200,H54)>1," +"&(COUNTIF(Schedule!$D$4:$D$200,H54)-1)&" more",""),"")
A56: =(Settings!$C$36-(WEEKDAY(Settings!$C$36,2)-1))+182 -> 46384 | B56: =$A56+0 -> 46384 | C56: =$A56+1 -> 46385 | D56: =$A56+2 -> 46386 | E56: =$A56+3 -> 46387 | F56: =$A56+4 -> 46388 | G56: =$A56+5 -> 46389 | H56: =$A56+6 -> 46390
B57: =IFERROR(INDEX(Schedule!$B$4:$B$200,MATCH(B56,Schedule!$D$4:$D$200,0))&IF(COUNTIF(Schedule!$D$4:$D$200,B56)>1," +"&(COUNTIF(Schedule!$D$4:$D$200,B56)-1)&" more",""),"") | C57: =IFERROR(INDEX(Schedule!$B$4:$B$200,MATCH(C56,Schedule!$D$4:$D$200,0))&IF(COUNTIF(Schedule!$D$4:$D$200,C56)>1," +"&(COUNTIF(Schedule!$D$4:$D$200,C56)-1)&" more",""),"") | D57: =IFERROR(INDEX(Schedule!$B$4:$B$200,MATCH(D56,Schedule!$D$4:$D$200,0))&IF(COUNTIF(Schedule!$D$4:$D$200,D56)>1," +"&(COUNTIF(Schedule!$D$4:$D$200,D56)-1)&" more",""),"") | E57: =IFERROR(INDEX(Schedule!$B$4:$B$200,MATCH(E56,Schedule!$D$4:$D$200,0))&IF(COUNTIF(Schedule!$D$4:$D$200,E56)>1," +"&(COUNTIF(Schedule!$D$4:$D$200,E56)-1)&" more",""),"") | F57: =IFERROR(INDEX(Schedule!$B$4:$B$200,MATCH(F56,Schedule!$D$4:$D$200,0))&IF(COUNTIF(Schedule!$D$4:$D$200,F56)>1," +"&(COUNTIF(Schedule!$D$4:$D$200,F56)-1)&" more",""),"") | G57: =IFERROR(INDEX(Schedule!$B$4:$B$200,MATCH(G56,Schedule!$D$4:$D$200,0))&IF(COUNTIF(Schedule!$D$4:$D$200,G56)>1," +"&(COUNTIF(Schedule!$D$4:$D$200,G56)-1)&" more",""),"") | H57: =IFERROR(INDEX(Schedule!$B$4:$B$200,MATCH(H56,Schedule!$D$4:$D$200,0))&IF(COUNTIF(Schedule!$D$4:$D$200,H56)>1," +"&(COUNTIF(Schedule!$D$4:$D$200,H56)-1)&" more",""),"")
A58: =(Settings!$C$36-(WEEKDAY(Settings!$C$36,2)-1))+189 -> 46391 | B58: =$A58+0 -> 46391 | C58: =$A58+1 -> 46392 | D58: =$A58+2 -> 46393 | E58: =$A58+3 -> 46394 | F58: =$A58+4 -> 46395 | G58: =$A58+5 -> 46396 | H58: =$A58+6 -> 46397
B59: =IFERROR(INDEX(Schedule!$B$4:$B$200,MATCH(B58,Schedule!$D$4:$D$200,0))&IF(COUNTIF(Schedule!$D$4:$D$200,B58)>1," +"&(COUNTIF(Schedule!$D$4:$D$200,B58)-1)&" more",""),"") | C59: =IFERROR(INDEX(Schedule!$B$4:$B$200,MATCH(C58,Schedule!$D$4:$D$200,0))&IF(COUNTIF(Schedule!$D$4:$D$200,C58)>1," +"&(COUNTIF(Schedule!$D$4:$D$200,C58)-1)&" more",""),"") | D59: =IFERROR(INDEX(Schedule!$B$4:$B$200,MATCH(D58,Schedule!$D$4:$D$200,0))&IF(COUNTIF(Schedule!$D$4:$D$200,D58)>1," +"&(COUNTIF(Schedule!$D$4:$D$200,D58)-1)&" more",""),"") | E59: =IFERROR(INDEX(Schedule!$B$4:$B$200,MATCH(E58,Schedule!$D$4:$D$200,0))&IF(COUNTIF(Schedule!$D$4:$D$200,E58)>1," +"&(COUNTIF(Schedule!$D$4:$D$200,E58)-1)&" more",""),"") | F59: =IFERROR(INDEX(Schedule!$B$4:$B$200,MATCH(F58,Schedule!$D$4:$D$200,0))&IF(COUNTIF(Schedule!$D$4:$D$200,F58)>1," +"&(COUNTIF(Schedule!$D$4:$D$200,F58)-1)&" more",""),"") | G59: =IFERROR(INDEX(Schedule!$B$4:$B$200,MATCH(G58,Schedule!$D$4:$D$200,0))&IF(COUNTIF(Schedule!$D$4:$D$200,G58)>1," +"&(COUNTIF(Schedule!$D$4:$D$200,G58)-1)&" more",""),"") | H59: =IFERROR(INDEX(Schedule!$B$4:$B$200,MATCH(H58,Schedule!$D$4:$D$200,0))&IF(COUNTIF(Schedule!$D$4:$D$200,H58)>1," +"&(COUNTIF(Schedule!$D$4:$D$200,H58)-1)&" more",""),"")
A60: =(Settings!$C$36-(WEEKDAY(Settings!$C$36,2)-1))+196 -> 46398 | B60: =$A60+0 -> 46398 | C60: =$A60+1 -> 46399 | D60: =$A60+2 -> 46400 | E60: =$A60+3 -> 46401 | F60: =$A60+4 -> 46402 | G60: =$A60+5 -> 46403 | H60: =$A60+6 -> 46404
B61: =IFERROR(INDEX(Schedule!$B$4:$B$200,MATCH(B60,Schedule!$D$4:$D$200,0))&IF(COUNTIF(Schedule!$D$4:$D$200,B60)>1," +"&(COUNTIF(Schedule!$D$4:$D$200,B60)-1)&" more",""),"") | C61: =IFERROR(INDEX(Schedule!$B$4:$B$200,MATCH(C60,Schedule!$D$4:$D$200,0))&IF(COUNTIF(Schedule!$D$4:$D$200,C60)>1," +"&(COUNTIF(Schedule!$D$4:$D$200,C60)-1)&" more",""),"") | D61: =IFERROR(INDEX(Schedule!$B$4:$B$200,MATCH(D60,Schedule!$D$4:$D$200,0))&IF(COUNTIF(Schedule!$D$4:$D$200,D60)>1," +"&(COUNTIF(Schedule!$D$4:$D$200,D60)-1)&" more",""),"") | E61: =IFERROR(INDEX(Schedule!$B$4:$B$200,MATCH(E60,Schedule!$D$4:$D$200,0))&IF(COUNTIF(Schedule!$D$4:$D$200,E60)>1," +"&(COUNTIF(Schedule!$D$4:$D$200,E60)-1)&" more",""),"") | F61: =IFERROR(INDEX(Schedule!$B$4:$B$200,MATCH(F60,Schedule!$D$4:$D$200,0))&IF(COUNTIF(Schedule!$D$4:$D$200,F60)>1," +"&(COUNTIF(Schedule!$D$4:$D$200,F60)-1)&" more",""),"") | G61: =IFERROR(INDEX(Schedule!$B$4:$B$200,MATCH(G60,Schedule!$D$4:$D$200,0))&IF(COUNTIF(Schedule!$D$4:$D$200,G60)>1," +"&(COUNTIF(Schedule!$D$4:$D$200,G60)-1)&" more",""),"") | H61: =IFERROR(INDEX(Schedule!$B$4:$B$200,MATCH(H60,Schedule!$D$4:$D$200,0))&IF(COUNTIF(Schedule!$D$4:$D$200,H60)>1," +"&(COUNTIF(Schedule!$D$4:$D$200,H60)-1)&" more",""),"")
A62: =(Settings!$C$36-(WEEKDAY(Settings!$C$36,2)-1))+203 -> 46405 | B62: =$A62+0 -> 46405 | C62: =$A62+1 -> 46406 | D62: =$A62+2 -> 46407 | E62: =$A62+3 -> 46408 | F62: =$A62+4 -> 46409 | G62: =$A62+5 -> 46410 | H62: =$A62+6 -> 46411
B63: =IFERROR(INDEX(Schedule!$B$4:$B$200,MATCH(B62,Schedule!$D$4:$D$200,0))&IF(COUNTIF(Schedule!$D$4:$D$200,B62)>1," +"&(COUNTIF(Schedule!$D$4:$D$200,B62)-1)&" more",""),"") | C63: =IFERROR(INDEX(Schedule!$B$4:$B$200,MATCH(C62,Schedule!$D$4:$D$200,0))&IF(COUNTIF(Schedule!$D$4:$D$200,C62)>1," +"&(COUNTIF(Schedule!$D$4:$D$200,C62)-1)&" more",""),"") | D63: =IFERROR(INDEX(Schedule!$B$4:$B$200,MATCH(D62,Schedule!$D$4:$D$200,0))&IF(COUNTIF(Schedule!$D$4:$D$200,D62)>1," +"&(COUNTIF(Schedule!$D$4:$D$200,D62)-1)&" more",""),"") | E63: =IFERROR(INDEX(Schedule!$B$4:$B$200,MATCH(E62,Schedule!$D$4:$D$200,0))&IF(COUNTIF(Schedule!$D$4:$D$200,E62)>1," +"&(COUNTIF(Schedule!$D$4:$D$200,E62)-1)&" more",""),"") | F63: =IFERROR(INDEX(Schedule!$B$4:$B$200,MATCH(F62,Schedule!$D$4:$D$200,0))&IF(COUNTIF(Schedule!$D$4:$D$200,F62)>1," +"&(COUNTIF(Schedule!$D$4:$D$200,F62)-1)&" more",""),"") | G63: =IFERROR(INDEX(Schedule!$B$4:$B$200,MATCH(G62,Schedule!$D$4:$D$200,0))&IF(COUNTIF(Schedule!$D$4:$D$200,G62)>1," +"&(COUNTIF(Schedule!$D$4:$D$200,G62)-1)&" more",""),"") | H63: =IFERROR(INDEX(Schedule!$B$4:$B$200,MATCH(H62,Schedule!$D$4:$D$200,0))&IF(COUNTIF(Schedule!$D$4:$D$200,H62)>1," +"&(COUNTIF(Schedule!$D$4:$D$200,H62)-1)&" more",""),"")
A64: =(Settings!$C$36-(WEEKDAY(Settings!$C$36,2)-1))+210 -> 46412 | B64: =$A64+0 -> 46412 | C64: =$A64+1 -> 46413 | D64: =$A64+2 -> 46414 | E64: =$A64+3 -> 46415 | F64: =$A64+4 -> 46416 | G64: =$A64+5 -> 46417 | H64: =$A64+6 -> 46418
B65: =IFERROR(INDEX(Schedule!$B$4:$B$200,MATCH(B64,Schedule!$D$4:$D$200,0))&IF(COUNTIF(Schedule!$D$4:$D$200,B64)>1," +"&(COUNTIF(Schedule!$D$4:$D$200,B64)-1)&" more",""),"") | C65: =IFERROR(INDEX(Schedule!$B$4:$B$200,MATCH(C64,Schedule!$D$4:$D$200,0))&IF(COUNTIF(Schedule!$D$4:$D$200,C64)>1," +"&(COUNTIF(Schedule!$D$4:$D$200,C64)-1)&" more",""),"") | D65: =IFERROR(INDEX(Schedule!$B$4:$B$200,MATCH(D64,Schedule!$D$4:$D$200,0))&IF(COUNTIF(Schedule!$D$4:$D$200,D64)>1," +"&(COUNTIF(Schedule!$D$4:$D$200,D64)-1)&" more",""),"") | E65: =IFERROR(INDEX(Schedule!$B$4:$B$200,MATCH(E64,Schedule!$D$4:$D$200,0))&IF(COUNTIF(Schedule!$D$4:$D$200,E64)>1," +"&(COUNTIF(Schedule!$D$4:$D$200,E64)-1)&" more",""),"") | F65: =IFERROR(INDEX(Schedule!$B$4:$B$200,MATCH(F64,Schedule!$D$4:$D$200,0))&IF(COUNTIF(Schedule!$D$4:$D$200,F64)>1," +"&(COUNTIF(Schedule!$D$4:$D$200,F64)-1)&" more",""),"") | G65: =IFERROR(INDEX(Schedule!$B$4:$B$200,MATCH(G64,Schedule!$D$4:$D$200,0))&IF(COUNTIF(Schedule!$D$4:$D$200,G64)>1," +"&(COUNTIF(Schedule!$D$4:$D$200,G64)-1)&" more",""),"") | H65: =IFERROR(INDEX(Schedule!$B$4:$B$200,MATCH(H64,Schedule!$D$4:$D$200,0))&IF(COUNTIF(Schedule!$D$4:$D$200,H64)>1," +"&(COUNTIF(Schedule!$D$4:$D$200,H64)-1)&" more",""),"")
A66: =(Settings!$C$36-(WEEKDAY(Settings!$C$36,2)-1))+217 -> 46419 | B66: =$A66+0 -> 46419 | C66: =$A66+1 -> 46420 | D66: =$A66+2 -> 46421 | E66: =$A66+3 -> 46422 | F66: =$A66+4 -> 46423 | G66: =$A66+5 -> 46424 | H66: =$A66+6 -> 46425
B67: =IFERROR(INDEX(Schedule!$B$4:$B$200,MATCH(B66,Schedule!$D$4:$D$200,0))&IF(COUNTIF(Schedule!$D$4:$D$200,B66)>1," +"&(COUNTIF(Schedule!$D$4:$D$200,B66)-1)&" more",""),"") | C67: =IFERROR(INDEX(Schedule!$B$4:$B$200,MATCH(C66,Schedule!$D$4:$D$200,0))&IF(COUNTIF(Schedule!$D$4:$D$200,C66)>1," +"&(COUNTIF(Schedule!$D$4:$D$200,C66)-1)&" more",""),"") | D67: =IFERROR(INDEX(Schedule!$B$4:$B$200,MATCH(D66,Schedule!$D$4:$D$200,0))&IF(COUNTIF(Schedule!$D$4:$D$200,D66)>1," +"&(COUNTIF(Schedule!$D$4:$D$200,D66)-1)&" more",""),"") | E67: =IFERROR(INDEX(Schedule!$B$4:$B$200,MATCH(E66,Schedule!$D$4:$D$200,0))&IF(COUNTIF(Schedule!$D$4:$D$200,E66)>1," +"&(COUNTIF(Schedule!$D$4:$D$200,E66)-1)&" more",""),"") | F67: =IFERROR(INDEX(Schedule!$B$4:$B$200,MATCH(F66,Schedule!$D$4:$D$200,0))&IF(COUNTIF(Schedule!$D$4:$D$200,F66)>1," +"&(COUNTIF(Schedule!$D$4:$D$200,F66)-1)&" more",""),"") | G67: =IFERROR(INDEX(Schedule!$B$4:$B$200,MATCH(G66,Schedule!$D$4:$D$200,0))&IF(COUNTIF(Schedule!$D$4:$D$200,G66)>1," +"&(COUNTIF(Schedule!$D$4:$D$200,G66)-1)&" more",""),"") | H67: =IFERROR(INDEX(Schedule!$B$4:$B$200,MATCH(H66,Schedule!$D$4:$D$200,0))&IF(COUNTIF(Schedule!$D$4:$D$200,H66)>1," +"&(COUNTIF(Schedule!$D$4:$D$200,H66)-1)&" more",""),"")
A68: =(Settings!$C$36-(WEEKDAY(Settings!$C$36,2)-1))+224 -> 46426 | B68: =$A68+0 -> 46426 | C68: =$A68+1 -> 46427 | D68: =$A68+2 -> 46428 | E68: =$A68+3 -> 46429 | F68: =$A68+4 -> 46430 | G68: =$A68+5 -> 46431 | H68: =$A68+6 -> 46432
B69: =IFERROR(INDEX(Schedule!$B$4:$B$200,MATCH(B68,Schedule!$D$4:$D$200,0))&IF(COUNTIF(Schedule!$D$4:$D$200,B68)>1," +"&(COUNTIF(Schedule!$D$4:$D$200,B68)-1)&" more",""),"") | C69: =IFERROR(INDEX(Schedule!$B$4:$B$200,MATCH(C68,Schedule!$D$4:$D$200,0))&IF(COUNTIF(Schedule!$D$4:$D$200,C68)>1," +"&(COUNTIF(Schedule!$D$4:$D$200,C68)-1)&" more",""),"") | D69: =IFERROR(INDEX(Schedule!$B$4:$B$200,MATCH(D68,Schedule!$D$4:$D$200,0))&IF(COUNTIF(Schedule!$D$4:$D$200,D68)>1," +"&(COUNTIF(Schedule!$D$4:$D$200,D68)-1)&" more",""),"") | E69: =IFERROR(INDEX(Schedule!$B$4:$B$200,MATCH(E68,Schedule!$D$4:$D$200,0))&IF(COUNTIF(Schedule!$D$4:$D$200,E68)>1," +"&(COUNTIF(Schedule!$D$4:$D$200,E68)-1)&" more",""),"") | F69: =IFERROR(INDEX(Schedule!$B$4:$B$200,MATCH(F68,Schedule!$D$4:$D$200,0))&IF(COUNTIF(Schedule!$D$4:$D$200,F68)>1," +"&(COUNTIF(Schedule!$D$4:$D$200,F68)-1)&" more",""),"") | G69: =IFERROR(INDEX(Schedule!$B$4:$B$200,MATCH(G68,Schedule!$D$4:$D$200,0))&IF(COUNTIF(Schedule!$D$4:$D$200,G68)>1," +"&(COUNTIF(Schedule!$D$4:$D$200,G68)-1)&" more",""),"") | H69: =IFERROR(INDEX(Schedule!$B$4:$B$200,MATCH(H68,Schedule!$D$4:$D$200,0))&IF(COUNTIF(Schedule!$D$4:$D$200,H68)>1," +"&(COUNTIF(Schedule!$D$4:$D$200,H68)-1)&" more",""),"")
A70: =(Settings!$C$36-(WEEKDAY(Settings!$C$36,2)-1))+231 -> 46433 | B70: =$A70+0 -> 46433 | C70: =$A70+1 -> 46434 | D70: =$A70+2 -> 46435 | E70: =$A70+3 -> 46436 | F70: =$A70+4 -> 46437 | G70: =$A70+5 -> 46438 | H70: =$A70+6 -> 46439
B71: =IFERROR(INDEX(Schedule!$B$4:$B$200,MATCH(B70,Schedule!$D$4:$D$200,0))&IF(COUNTIF(Schedule!$D$4:$D$200,B70)>1," +"&(COUNTIF(Schedule!$D$4:$D$200,B70)-1)&" more",""),"") | C71: =IFERROR(INDEX(Schedule!$B$4:$B$200,MATCH(C70,Schedule!$D$4:$D$200,0))&IF(COUNTIF(Schedule!$D$4:$D$200,C70)>1," +"&(COUNTIF(Schedule!$D$4:$D$200,C70)-1)&" more",""),"") | D71: =IFERROR(INDEX(Schedule!$B$4:$B$200,MATCH(D70,Schedule!$D$4:$D$200,0))&IF(COUNTIF(Schedule!$D$4:$D$200,D70)>1," +"&(COUNTIF(Schedule!$D$4:$D$200,D70)-1)&" more",""),"") | E71: =IFERROR(INDEX(Schedule!$B$4:$B$200,MATCH(E70,Schedule!$D$4:$D$200,0))&IF(COUNTIF(Schedule!$D$4:$D$200,E70)>1," +"&(COUNTIF(Schedule!$D$4:$D$200,E70)-1)&" more",""),"") | F71: =IFERROR(INDEX(Schedule!$B$4:$B$200,MATCH(F70,Schedule!$D$4:$D$200,0))&IF(COUNTIF(Schedule!$D$4:$D$200,F70)>1," +"&(COUNTIF(Schedule!$D$4:$D$200,F70)-1)&" more",""),"") | G71: =IFERROR(INDEX(Schedule!$B$4:$B$200,MATCH(G70,Schedule!$D$4:$D$200,0))&IF(COUNTIF(Schedule!$D$4:$D$200,G70)>1," +"&(COUNTIF(Schedule!$D$4:$D$200,G70)-1)&" more",""),"") | H71: =IFERROR(INDEX(Schedule!$B$4:$B$200,MATCH(H70,Schedule!$D$4:$D$200,0))&IF(COUNTIF(Schedule!$D$4:$D$200,H70)>1," +"&(COUNTIF(Schedule!$D$4:$D$200,H70)-1)&" more",""),"")
A72: =(Settings!$C$36-(WEEKDAY(Settings!$C$36,2)-1))+238 -> 46440 | B72: =$A72+0 -> 46440 | C72: =$A72+1 -> 46441 | D72: =$A72+2 -> 46442 | E72: =$A72+3 -> 46443 | F72: =$A72+4 -> 46444 | G72: =$A72+5 -> 46445 | H72: =$A72+6 -> 46446
B73: =IFERROR(INDEX(Schedule!$B$4:$B$200,MATCH(B72,Schedule!$D$4:$D$200,0))&IF(COUNTIF(Schedule!$D$4:$D$200,B72)>1," +"&(COUNTIF(Schedule!$D$4:$D$200,B72)-1)&" more",""),"") | C73: =IFERROR(INDEX(Schedule!$B$4:$B$200,MATCH(C72,Schedule!$D$4:$D$200,0))&IF(COUNTIF(Schedule!$D$4:$D$200,C72)>1," +"&(COUNTIF(Schedule!$D$4:$D$200,C72)-1)&" more",""),"") | D73: =IFERROR(INDEX(Schedule!$B$4:$B$200,MATCH(D72,Schedule!$D$4:$D$200,0))&IF(COUNTIF(Schedule!$D$4:$D$200,D72)>1," +"&(COUNTIF(Schedule!$D$4:$D$200,D72)-1)&" more",""),"") | E73: =IFERROR(INDEX(Schedule!$B$4:$B$200,MATCH(E72,Schedule!$D$4:$D$200,0))&IF(COUNTIF(Schedule!$D$4:$D$200,E72)>1," +"&(COUNTIF(Schedule!$D$4:$D$200,E72)-1)&" more",""),"") | F73: =IFERROR(INDEX(Schedule!$B$4:$B$200,MATCH(F72,Schedule!$D$4:$D$200,0))&IF(COUNTIF(Schedule!$D$4:$D$200,F72)>1," +"&(COUNTIF(Schedule!$D$4:$D$200,F72)-1)&" more",""),"") | G73: =IFERROR(INDEX(Schedule!$B$4:$B$200,MATCH(G72,Schedule!$D$4:$D$200,0))&IF(COUNTIF(Schedule!$D$4:$D$200,G72)>1," +"&(COUNTIF(Schedule!$D$4:$D$200,G72)-1)&" more",""),"") | H73: =IFERROR(INDEX(Schedule!$B$4:$B$200,MATCH(H72,Schedule!$D$4:$D$200,0))&IF(COUNTIF(Schedule!$D$4:$D$200,H72)>1," +"&(COUNTIF(Schedule!$D$4:$D$200,H72)-1)&" more",""),"")
A74: =(Settings!$C$36-(WEEKDAY(Settings!$C$36,2)-1))+245 -> 46447 | B74: =$A74+0 -> 46447 | C74: =$A74+1 -> 46448 | D74: =$A74+2 -> 46449 | E74: =$A74+3 -> 46450 | F74: =$A74+4 -> 46451 | G74: =$A74+5 -> 46452 | H74: =$A74+6 -> 46453
B75: =IFERROR(INDEX(Schedule!$B$4:$B$200,MATCH(B74,Schedule!$D$4:$D$200,0))&IF(COUNTIF(Schedule!$D$4:$D$200,B74)>1," +"&(COUNTIF(Schedule!$D$4:$D$200,B74)-1)&" more",""),"") | C75: =IFERROR(INDEX(Schedule!$B$4:$B$200,MATCH(C74,Schedule!$D$4:$D$200,0))&IF(COUNTIF(Schedule!$D$4:$D$200,C74)>1," +"&(COUNTIF(Schedule!$D$4:$D$200,C74)-1)&" more",""),"") | D75: =IFERROR(INDEX(Schedule!$B$4:$B$200,MATCH(D74,Schedule!$D$4:$D$200,0))&IF(COUNTIF(Schedule!$D$4:$D$200,D74)>1," +"&(COUNTIF(Schedule!$D$4:$D$200,D74)-1)&" more",""),"") | E75: =IFERROR(INDEX(Schedule!$B$4:$B$200,MATCH(E74,Schedule!$D$4:$D$200,0))&IF(COUNTIF(Schedule!$D$4:$D$200,E74)>1," +"&(COUNTIF(Schedule!$D$4:$D$200,E74)-1)&" more",""),"") | F75: =IFERROR(INDEX(Schedule!$B$4:$B$200,MATCH(F74,Schedule!$D$4:$D$200,0))&IF(COUNTIF(Schedule!$D$4:$D$200,F74)>1," +"&(COUNTIF(Schedule!$D$4:$D$200,F74)-1)&" more",""),"") | G75: =IFERROR(INDEX(Schedule!$B$4:$B$200,MATCH(G74,Schedule!$D$4:$D$200,0))&IF(COUNTIF(Schedule!$D$4:$D$200,G74)>1," +"&(COUNTIF(Schedule!$D$4:$D$200,G74)-1)&" more",""),"") | H75: =IFERROR(INDEX(Schedule!$B$4:$B$200,MATCH(H74,Schedule!$D$4:$D$200,0))&IF(COUNTIF(Schedule!$D$4:$D$200,H74)>1," +"&(COUNTIF(Schedule!$D$4:$D$200,H74)-1)&" more",""),"")
A76: =(Settings!$C$36-(WEEKDAY(Settings!$C$36,2)-1))+252 -> 46454 | B76: =$A76+0 -> 46454 | C76: =$A76+1 -> 46455 | D76: =$A76+2 -> 46456 | E76: =$A76+3 -> 46457 | F76: =$A76+4 -> 46458 | G76: =$A76+5 -> 46459 | H76: =$A76+6 -> 46460
B77: =IFERROR(INDEX(Schedule!$B$4:$B$200,MATCH(B76,Schedule!$D$4:$D$200,0))&IF(COUNTIF(Schedule!$D$4:$D$200,B76)>1," +"&(COUNTIF(Schedule!$D$4:$D$200,B76)-1)&" more",""),"") | C77: =IFERROR(INDEX(Schedule!$B$4:$B$200,MATCH(C76,Schedule!$D$4:$D$200,0))&IF(COUNTIF(Schedule!$D$4:$D$200,C76)>1," +"&(COUNTIF(Schedule!$D$4:$D$200,C76)-1)&" more",""),"") | D77: =IFERROR(INDEX(Schedule!$B$4:$B$200,MATCH(D76,Schedule!$D$4:$D$200,0))&IF(COUNTIF(Schedule!$D$4:$D$200,D76)>1," +"&(COUNTIF(Schedule!$D$4:$D$200,D76)-1)&" more",""),"") | E77: =IFERROR(INDEX(Schedule!$B$4:$B$200,MATCH(E76,Schedule!$D$4:$D$200,0))&IF(COUNTIF(Schedule!$D$4:$D$200,E76)>1," +"&(COUNTIF(Schedule!$D$4:$D$200,E76)-1)&" more",""),"") | F77: =IFERROR(INDEX(Schedule!$B$4:$B$200,MATCH(F76,Schedule!$D$4:$D$200,0))&IF(COUNTIF(Schedule!$D$4:$D$200,F76)>1," +"&(COUNTIF(Schedule!$D$4:$D$200,F76)-1)&" more",""),"") | G77: =IFERROR(INDEX(Schedule!$B$4:$B$200,MATCH(G76,Schedule!$D$4:$D$200,0))&IF(COUNTIF(Schedule!$D$4:$D$200,G76)>1," +"&(COUNTIF(Schedule!$D$4:$D$200,G76)-1)&" more",""),"") | H77: =IFERROR(INDEX(Schedule!$B$4:$B$200,MATCH(H76,Schedule!$D$4:$D$200,0))&IF(COUNTIF(Schedule!$D$4:$D$200,H76)>1," +"&(COUNTIF(Schedule!$D$4:$D$200,H76)-1)&" more",""),"")
A78: =(Settings!$C$36-(WEEKDAY(Settings!$C$36,2)-1))+259 -> 46461 | B78: =$A78+0 -> 46461 | C78: =$A78+1 -> 46462 | D78: =$A78+2 -> 46463 | E78: =$A78+3 -> 46464 | F78: =$A78+4 -> 46465 | G78: =$A78+5 -> 46466 | H78: =$A78+6 -> 46467
B79: =IFERROR(INDEX(Schedule!$B$4:$B$200,MATCH(B78,Schedule!$D$4:$D$200,0))&IF(COUNTIF(Schedule!$D$4:$D$200,B78)>1," +"&(COUNTIF(Schedule!$D$4:$D$200,B78)-1)&" more",""),"") | C79: =IFERROR(INDEX(Schedule!$B$4:$B$200,MATCH(C78,Schedule!$D$4:$D$200,0))&IF(COUNTIF(Schedule!$D$4:$D$200,C78)>1," +"&(COUNTIF(Schedule!$D$4:$D$200,C78)-1)&" more",""),"") | D79: =IFERROR(INDEX(Schedule!$B$4:$B$200,MATCH(D78,Schedule!$D$4:$D$200,0))&IF(COUNTIF(Schedule!$D$4:$D$200,D78)>1," +"&(COUNTIF(Schedule!$D$4:$D$200,D78)-1)&" more",""),"") | E79: =IFERROR(INDEX(Schedule!$B$4:$B$200,MATCH(E78,Schedule!$D$4:$D$200,0))&IF(COUNTIF(Schedule!$D$4:$D$200,E78)>1," +"&(COUNTIF(Schedule!$D$4:$D$200,E78)-1)&" more",""),"") | F79: =IFERROR(INDEX(Schedule!$B$4:$B$200,MATCH(F78,Schedule!$D$4:$D$200,0))&IF(COUNTIF(Schedule!$D$4:$D$200,F78)>1," +"&(COUNTIF(Schedule!$D$4:$D$200,F78)-1)&" more",""),"") | G79: =IFERROR(INDEX(Schedule!$B$4:$B$200,MATCH(G78,Schedule!$D$4:$D$200,0))&IF(COUNTIF(Schedule!$D$4:$D$200,G78)>1," +"&(COUNTIF(Schedule!$D$4:$D$200,G78)-1)&" more",""),"") | H79: =IFERROR(INDEX(Schedule!$B$4:$B$200,MATCH(H78,Schedule!$D$4:$D$200,0))&IF(COUNTIF(Schedule!$D$4:$D$200,H78)>1," +"&(COUNTIF(Schedule!$D$4:$D$200,H78)-1)&" more",""),"")

Sheet Exclusions
D1: EXCLUSIONS
D2: =Settings!C40&" • "&Settings!C41 -> PO Box 516, Longview, WA 98632 • 360-200-1716
D3: ="Project: "&Settings!C8&" Estimate "&Settings!C10 -> Project: Truesdell SFD Estimate EST-1001
A4: Lines toggled Excl? = Y on the Estimate are excluded (cost zeroed) and collected here for reference.
A5: Item | B5: Excluded line | C5: Value | D5: Excl?
A6: Permits | B6: =Estimate!B8 -> Bldg. Permit | C6: =Estimate!H8 -> 0 | D6: =Estimate!L8 -> N
A7: Electrical Utility Connections | B7: =Estimate!B10 -> PUD Quoted install | C7: =Estimate!H10 -> 0 | D7: =Estimate!L10 -> N
A8: Electrical Utility Connections | B8: =Estimate!B11 -> Gas service connection | C8: =Estimate!H11 -> 0 | D8: =Estimate!L11 -> N
A9: Excavation | B9: =Estimate!B13 -> Excavation | C9: =Estimate!H13 -> 0 | D9: =Estimate!L13 -> N
A10: Excavation | B10: =Estimate!B14 -> Excavation - utilities & contingency | C10: =Estimate!H14 -> 0 | D10: =Estimate!L14 -> N
A11: Excavation | B11: =Estimate!B15 -> Backfill - Labor | C11: =Estimate!H15 -> 0 | D11: =Estimate!L15 -> N
A12: Excavation | B12: =Estimate!B16 -> Backfill - Gravel and fill | C12: =Estimate!H16 -> 0 | D12: =Estimate!L16 -> N
A13: Septic system design & install | B13: =Estimate!B18 -> Septic system install - Pressure distribution | C13: =Estimate!H18 -> 0 | D13: =Estimate!L18 -> N
A14: Septic system design & install | B14: =Estimate!B19 -> Septic design | C14: =Estimate!H19 -> 0 | D14: =Estimate!L19 -> N
A15: Septic system design & install | B15: =Estimate!B20 -> Septic permit | C15: =Estimate!H20 -> 0 | D15: =Estimate!L20 -> N
A16: Well setup | B16: =Estimate!B22 -> Well | C16: =Estimate!H22 -> 0 | D16: =Estimate!L22 -> N
A17: Job site services | B17: =Estimate!B24 -> Home Cleaning @ Final | C17: =Estimate!H24 -> 0 | D17: =Estimate!L24 -> N
A18: Job site services | B18: =Estimate!B25 -> Portable toilet | C18: =Estimate!H25 -> 0 | D18: =Estimate!L25 -> N
A19: Job site services | B19: =Estimate!B26 -> Dumping fees / site cleanup | C19: =Estimate!H26 -> 0 | D19: =Estimate!L26 -> N
A20: Footing And Foundation | B20: =Estimate!B29 -> Foundation Labor/concrete | C20: =Estimate!H29 -> 0 | D20: =Estimate!L29 -> N
A21: Footing And Foundation | B21: =Estimate!B30 -> Pump Truck | C21: =Estimate!H30 -> 0 | D21: =Estimate!L30 -> N
A22: Framing Materials | B22: =Estimate!B33 -> Materials - 1st floor - 9.5" TJI | C22: =Estimate!H33 -> 0 | D22: =Estimate!L33 -> N
A23: Framing Materials | B23: =Estimate!B34 -> Exterior Walls 9' PLT HT | C23: =Estimate!H34 -> 0 | D23: =Estimate!L34 -> N
A24: Framing Materials | B24: =Estimate!B35 -> Materials - Roof pack | C24: =Estimate!H35 -> 0 | D24: =Estimate!L35 -> N
A25: Framing Materials | B25: =Estimate!B36 -> Materials - Trusses | C25: =Estimate!H36 -> 0 | D25: =Estimate!L36 -> N
A26: Framing Materials | B26: =Estimate!B37 -> Beams - hardware - Posts | C26: =Estimate!H37 -> 0 | D26: =Estimate!L37 -> N
A27: Framing Labor | B27: =Estimate!B39 -> Framing labor - living space | C27: =Estimate!H39 -> 0 | D27: =Estimate!L39 -> N
A28: Framing Labor | B28: =Estimate!B40 -> Framing labor - Covered porch/Garage | C28: =Estimate!H40 -> 0 | D28: =Estimate!L40 -> N
A29: Front Door | B29: =Estimate!B43 -> Front door 3080 - Knotty Alder | C29: =Estimate!H43 -> 0 | D29: =Estimate!L43 -> N
A30: Other exterior doors | B30: =Estimate!B45 -> Exterior doors | C30: =Estimate!H45 -> 0 | D30: =Estimate!L45 -> N
A31: Garage Doors | B31: =Estimate!B47 -> 18*8 | C31: =Estimate!H47 -> 0 | D31: =Estimate!L47 -> N
A32: Garage Doors | B32: =Estimate!B48 -> Garage Door openers | C32: =Estimate!H48 -> 0 | D32: =Estimate!L48 -> N
A33: Windows | B33: =Estimate!B50 -> Windows | C33: =Estimate!H50 -> 0 | D33: =Estimate!L50 -> N
A34: Windows | B34: =Estimate!B51 -> SGD (sliding glass door) | C34: =Estimate!H51 -> 0 | D34: =Estimate!L51 -> N
A35: Siding Materials | B35: =Estimate!B54 -> Siding materials package | C35: =Estimate!H54 -> 0 | D35: =Estimate!L54 -> N
A36: Siding Labor | B36: =Estimate!B56 -> Siding labor - 7" horizontal | C36: =Estimate!H56 -> 0 | D36: =Estimate!L56 -> N
A37: Siding Labor | B37: =Estimate!B57 -> Siding labor - Soffits | C37: =Estimate!H57 -> 0 | D37: =Estimate!L57 -> N
A38: Siding Labor | B38: =Estimate!B58 -> Siding labor - Post wraps | C38: =Estimate!H58 -> 0 | D38: =Estimate!L58 -> N
A39: Roofing Specifications | B39: =Estimate!B60 -> Roofing Material | C39: =Estimate!H60 -> 0 | D39: =Estimate!L60 -> N
A40: Roofing Specifications | B40: =Estimate!B61 -> Roofing Labor | C40: =Estimate!H61 -> 0 | D40: =Estimate!L61 -> N
A41: Gutters | B41: =Estimate!B63 -> Gutters | C41: =Estimate!H63 -> 0 | D41: =Estimate!L63 -> N
A42: Exterior Masonry | B42: =Estimate!B65 -> Cultured stone | C42: =Estimate!H65 -> 0 | D42: =Estimate!L65 -> N
A43: Exterior Painting | B43: =Estimate!B67 -> Exterior Painting Material & Labor | C43: =Estimate!H67 -> 0 | D43: =Estimate!L67 -> N
A44: Concrete Flatwork | B44: =Estimate!B69 -> Driveway | C44: =Estimate!H69 -> 0 | D44: =Estimate!L69 -> N
A45: Concrete Flatwork | B45: =Estimate!B70 -> Exterior concrete patio & walkway | C45: =Estimate!H70 -> 0 | D45: =Estimate!L70 -> N
A46: Concrete Flatwork | B46: =Estimate!B71 -> Garage slab | C46: =Estimate!H71 -> 0 | D46: =Estimate!L71 -> N
A47: HVAC | B47: =Estimate!B74 -> HVAC system | C47: =Estimate!H74 -> 0 | D47: =Estimate!L74 -> N
A48: Fireplace | B48: =Estimate!B76 -> Fireplace - install only + stove pipe parts | C48: =Estimate!H76 -> 0 | D48: =Estimate!L76 -> N
A49: Plumbing | B49: =Estimate!B79 -> Plumbing quote complete | C49: =Estimate!H79 -> 0 | D49: =Estimate!L79 -> N
A50: Electrical | B50: =Estimate!B82 -> Electrical System | C50: =Estimate!H82 -> 0 | D50: =Estimate!L82 -> N
A51: Electrical | B51: =Estimate!B83 -> Low-voltage rough-in (data / cable / TV) | C51: =Estimate!H83 -> 0 | D51: =Estimate!L83 -> N
A52: Electrical | B52: =Estimate!B84 -> EV charger circuit (rough-in) | C52: =Estimate!H84 -> 0 | D52: =Estimate!L84 -> N
A53: Electrical Fixtures | B53: =Estimate!B86 -> Fixture allowance | C53: =Estimate!H86 -> 0 | D53: =Estimate!L86 -> N
A54: Insulation | B54: =Estimate!B89 -> Insulation | C54: =Estimate!H89 -> 0 | D54: =Estimate!L89 -> N
A55: Drywall | B55: =Estimate!B92 -> Drywall, hang, tape, texture | C55: =Estimate!H92 -> 0 | D55: =Estimate!L92 -> N
A56: Interior Paint | B56: =Estimate!B94 -> Interior wall/ceiling/trim painting | C56: =Estimate!H94 -> 0 | D56: =Estimate!L94 -> N
A57: Bathroom accessories and mirrors | B57: =Estimate!B97 -> Bathroom mirrors | C57: =Estimate!H97 -> 0 | D57: =Estimate!L97 -> N
A58: Bathroom accessories and mirrors | B58: =Estimate!B98 -> TP holders, towel rod, towel ring per bath | C58: =Estimate!H98 -> 0 | D58: =Estimate!L98 -> N
A59: Masonry - Fireplace facade | B59: =Estimate!B100 -> Stone | C59: =Estimate!H100 -> 0 | D59: =Estimate!L100 -> N
A60: Masonry - Fireplace facade | B60: =Estimate!B101 -> Wood Mantel | C60: =Estimate!H101 -> 0 | D60: =Estimate!L101 -> N
A61: Flooring Labor | B61: =Estimate!B104 -> LVT/Laminate | C61: =Estimate!H104 -> 0 | D61: =Estimate!L104 -> N
A62: Flooring Labor | B62: =Estimate!B105 -> Tile (install) | C62: =Estimate!H105 -> 0 | D62: =Estimate!L105 -> N
A63: Flooring Labor | B63: =Estimate!B106 -> Shower pan / tile waterproofing | C63: =Estimate!H106 -> 0 | D63: =Estimate!L106 -> N
A64: Flooring Labor | B64: =Estimate!B107 -> Shower glass enclosure | C64: =Estimate!H107 -> 0 | D64: =Estimate!L107 -> N
A65: Flooring material | B65: =Estimate!B109 -> Tile Selection | C65: =Estimate!H109 -> 0 | D65: =Estimate!L109 -> N
A66: Flooring material | B66: =Estimate!B110 -> LVT/Laminate | C66: =Estimate!H110 -> 0 | D66: =Estimate!L110 -> N
A67: Millwork | B67: =Estimate!B113 -> Interior trim pack | C67: =Estimate!H113 -> 0 | D67: =Estimate!L113 -> N
A68: Finish Carpentry | B68: =Estimate!B115 -> Finish labor | C68: =Estimate!H115 -> 0 | D68: =Estimate!L115 -> N
A69: Cabinet Specifications | B69: =Estimate!B117 -> Supply and install cabinets complete | C69: =Estimate!H117 -> 0 | D69: =Estimate!L117 -> N
A70: Countertops | B70: =Estimate!B119 -> Countertops - Group B | C70: =Estimate!H119 -> 0 | D70: =Estimate!L119 -> N
A71: Countertops | B71: =Estimate!B120 -> Backsplash - Tile | C71: =Estimate!H120 -> 0 | D71: =Estimate!L120 -> N
A72: Appliance Specifications | B72: =Estimate!B123 -> Appliance purchase - delivery - install | C72: =Estimate!H123 -> 0 | D72: =Estimate!L123 -> N
A73: Window Coverings | B73: =Estimate!B125 -> Window coverings / blinds allowance | C73: =Estimate!H125 -> 0 | D73: =Estimate!L125 -> N
A74: Final Grade & Landscaping | B74: =Estimate!B128 -> Final grade and rough landscaping | C74: =Estimate!H128 -> 0 | D74: =Estimate!L128 -> N
B75: TOTAL EXCLUDED VALUE | C75: =SUMIF(D6:D74,"Y",C6:C74) -> 0

Sheet Draws
C1: DRAW SCHEDULE
C2: =Settings!C40&" • "&Settings!C41 -> PO Box 516, Longview, WA 98632 • 360-200-1716
C3: ="Project: "&Settings!C8 -> Project: Truesdell SFD
A5: Code | B5: Item / Description | C5: Contract | D5: Draw 1 | E5: Draw 2 | F5: Draw 3 | G5: Draw 4 | H5: Draw 5 | I5: Final Draw | J5: Total Drawn | K5: Remaining | L5: % Billed
A6: 0100 | B6: General Conditions | C6: =Estimate!F6 -> 0 | J6: =J7 -> 0 | K6: =C6-J6 -> 0 | L6: =IF(C6=0,0,J6/C6) -> 0
A7: 0110 | B7: ="Permits"&IF($K7="Y"," (Allowance)","") -> Permits | C7: =Estimate!F7 -> 0 | J7: 0 | K7: =C7-J7 -> 0 | L7: =IF(C7=0,0,J7/C7) -> 0
B8: Bldg. Permit | C8: =Estimate!F8 -> 0 | J8: =J9 -> 0 | K8: =C8-J8 -> 0 | L8: =IF(C8=0,0,J8/C8) -> 0
A9: 0120 | B9: ="Electrical Utility Connections"&IF($K9="Y"," (Allowance)","") -> Electrical Utility Connections | C9: =Estimate!F9 -> 0 | J9: 0 | K9: =C9-J9 -> 0 | L9: =IF(C9=0,0,J9/C9) -> 0
B10: PUD Quoted install | C10: =Estimate!F10 -> 0 | J10: 0 | K10: =C10-J10 -> 0 | L10: =IF(C10=0,0,J10/C10) -> 0
B11: Gas service connection | C11: =Estimate!F11 -> 0 | J11: =J12 -> 0 | K11: =C11-J11 -> 0 | L11: =IF(C11=0,0,J11/C11) -> 0
A12: 0130 | B12: ="Excavation"&IF($K12="Y"," (Allowance)","") -> Excavation | C12: =Estimate!F12 -> 0 | J12: 0 | K12: =C12-J12 -> 0 | L12: =IF(C12=0,0,J12/C12) -> 0
B13: Excavation | C13: =Estimate!F13 -> 0 | J13: 0 | K13: =C13-J13 -> 0 | L13: =IF(C13=0,0,J13/C13) -> 0
B14: Excavation - utilities & contingency | C14: =Estimate!F14 -> 0 | J14: 0 | K14: =C14-J14 -> 0 | L14: =IF(C14=0,0,J14/C14) -> 0
B15: Backfill - Labor | C15: =Estimate!F15 -> 0 | J15: 0 | K15: =C15-J15 -> 0 | L15: =IF(C15=0,0,J15/C15) -> 0
B16: Backfill - Gravel and fill | C16: =Estimate!F16 -> 0 | J16: =J17 -> 0 | K16: =C16-J16 -> 0 | L16: =IF(C16=0,0,J16/C16) -> 0
A17: 0140 | B17: ="Septic system design & install"&IF($K17="Y"," (Allowance)","") -> Septic system design & install | C17: =Estimate!F17 -> 0 | J17: 0 | K17: =C17-J17 -> 0 | L17: =IF(C17=0,0,J17/C17) -> 0
B18: Septic system install - Pressure distribution | C18: =Estimate!F18 -> 0 | J18: 0 | K18: =C18-J18 -> 0 | L18: =IF(C18=0,0,J18/C18) -> 0
B19: Septic design | C19: =Estimate!F19 -> 0 | J19: 0 | K19: =C19-J19 -> 0 | L19: =IF(C19=0,0,J19/C19) -> 0
B20: Septic permit | C20: =Estimate!F20 -> 0 | J20: 0 | K20: =C20-J20 -> 0 | L20: =IF(C20=0,0,J20/C20) -> 0
A21: 0150 | B21: ="Well setup"&IF($K21="Y"," (Allowance)","") -> Well setup | C21: =Estimate!F21 -> 0 | J21: 0 | K21: =C21-J21 -> 0 | L21: =IF(C21=0,0,J21/C21) -> 0
B22: Well | C22: =Estimate!F22 -> 0 | J22: 0 | K22: =C22-J22 -> 0 | L22: =IF(C22=0,0,J22/C22) -> 0
A23: 0190 | B23: ="Job site services"&IF($K23="Y"," (Allowance)","") -> Job site services | C23: =Estimate!F23 -> 0 | J23: 0 | K23: =C23-J23 -> 0 | L23: =IF(C23=0,0,J23/C23) -> 0
B24: Home Cleaning @ Final | C24: =Estimate!F24 -> 0 | J24: 0 | K24: =C24-J24 -> 0 | L24: =IF(C24=0,0,J24/C24) -> 0
B25: Portable toilet | C25: =Estimate!F25 -> 0 | J25: 0 | K25: =C25-J25 -> 0 | L25: =IF(C25=0,0,J25/C25) -> 0
B26: Dumping fees / site cleanup | C26: =Estimate!F26 -> 0 | J26: 0 | K26: =C26-J26 -> 0 | L26: =IF(C26=0,0,J26/C26) -> 0
A27: 0200 | B27: Site Work | C27: =Estimate!F27 -> 0 | J27: =J28 -> 0 | K27: =C27-J27 -> 0 | L27: =IF(C27=0,0,J27/C27) -> 0
A28: 0210 | B28: ="Footing And Foundation"&IF($K28="Y"," (Allowance)","") -> Footing And Foundation | C28: =Estimate!F28 -> 0 | J28: 0 | K28: =C28-J28 -> 0 | L28: =IF(C28=0,0,J28/C28) -> 0
B29: Foundation Labor/concrete | C29: =Estimate!F29 -> 0 | J29: 0 | K29: =C29-J29 -> 0 | L29: =IF(C29=0,0,J29/C29) -> 0
B30: Pump Truck | C30: =Estimate!F30 -> 0 | J30: 0 | K30: =C30-J30 -> 0 | L30: =IF(C30=0,0,J30/C30) -> 0
A31: 0300 | B31: Rough Structure | C31: =Estimate!F31 -> 0 | J31: =J32 -> 0 | K31: =C31-J31 -> 0 | L31: =IF(C31=0,0,J31/C31) -> 0
A32: 0310 | B32: ="Framing Materials"&IF($K32="Y"," (Allowance)","") -> Framing Materials | C32: =Estimate!F32 -> 0 | J32: 0 | K32: =C32-J32 -> 0 | L32: =IF(C32=0,0,J32/C32) -> 0
B33: Materials - 1st floor - 9.5" TJI | C33: =Estimate!F33 -> 0 | J33: 0 | K33: =C33-J33 -> 0 | L33: =IF(C33=0,0,J33/C33) -> 0
B34: Exterior Walls 9' PLT HT | C34: =Estimate!F34 -> 0 | J34: 0 | K34: =C34-J34 -> 0 | L34: =IF(C34=0,0,J34/C34) -> 0
B35: Materials - Roof pack | C35: =Estimate!F35 -> 0 | J35: 0 | K35: =C35-J35 -> 0 | L35: =IF(C35=0,0,J35/C35) -> 0
B36: Materials - Trusses | C36: =Estimate!F36 -> 0 | J36: 0 | K36: =C36-J36 -> 0 | L36: =IF(C36=0,0,J36/C36) -> 0
B37: Beams - hardware - Posts | C37: =Estimate!F37 -> 0 | J37: =J38 -> 0 | K37: =C37-J37 -> 0 | L37: =IF(C37=0,0,J37/C37) -> 0
A38: 0320 | B38: ="Framing Labor"&IF($K38="Y"," (Allowance)","") -> Framing Labor | C38: =Estimate!F38 -> 0 | J38: 0 | K38: =C38-J38 -> 0 | L38: =IF(C38=0,0,J38/C38) -> 0
B39: Framing labor - living space | C39: =Estimate!F39 -> 0 | J39: 0 | K39: =C39-J39 -> 0 | L39: =IF(C39=0,0,J39/C39) -> 0
B40: Framing labor - Covered porch/Garage | C40: =Estimate!F40 -> 0 | J40: 0 | K40: =C40-J40 -> 0 | L40: =IF(C40=0,0,J40/C40) -> 0
A41: 0400 | B41: Windows & Doors, Exterior | C41: =Estimate!F41 -> 0 | J41: =J42 -> 0 | K41: =C41-J41 -> 0 | L41: =IF(C41=0,0,J41/C41) -> 0
A42: 0410 | B42: ="Front Door"&IF($K42="Y"," (Allowance)","") -> Front Door | C42: =Estimate!F42 -> 0 | J42: 0 | K42: =C42-J42 -> 0 | L42: =IF(C42=0,0,J42/C42) -> 0
B43: Front door 3080 - Knotty Alder | C43: =Estimate!F43 -> 0 | J43: =J44 -> 0 | K43: =C43-J43 -> 0 | L43: =IF(C43=0,0,J43/C43) -> 0
A44: 0420 | B44: ="Other exterior doors"&IF($K44="Y"," (Allowance)","") -> Other exterior doors | C44: =Estimate!F44 -> 0 | J44: 0 | K44: =C44-J44 -> 0 | L44: =IF(C44=0,0,J44/C44) -> 0
B45: Exterior doors | C45: =Estimate!F45 -> 0 | J45: =J46 -> 0 | K45: =C45-J45 -> 0 | L45: =IF(C45=0,0,J45/C45) -> 0
A46: 0430 | B46: ="Garage Doors"&IF($K46="Y"," (Allowance)","") -> Garage Doors | C46: =Estimate!F46 -> 0 | J46: 0 | K46: =C46-J46 -> 0 | L46: =IF(C46=0,0,J46/C46) -> 0
B47: 18*8 | C47: =Estimate!F47 -> 0 | J47: 0 | K47: =C47-J47 -> 0 | L47: =IF(C47=0,0,J47/C47) -> 0
B48: Garage Door openers | C48: =Estimate!F48 -> 0 | J48: =J49 -> 0 | K48: =C48-J48 -> 0 | L48: =IF(C48=0,0,J48/C48) -> 0
A49: 0440 | B49: ="Windows"&IF($K49="Y"," (Allowance)","") -> Windows | C49: =Estimate!F49 -> 0 | J49: 0 | K49: =C49-J49 -> 0 | L49: =IF(C49=0,0,J49/C49) -> 0
B50: Windows | C50: =Estimate!F50 -> 0 | J50: 0 | K50: =C50-J50 -> 0 | L50: =IF(C50=0,0,J50/C50) -> 0
B51: SGD (sliding glass door) | C51: =Estimate!F51 -> 0 | J51: 0 | K51: =C51-J51 -> 0 | L51: =IF(C51=0,0,J51/C51) -> 0
A52: 0500 | B52: Exterior Finishes | C52: =Estimate!F52 -> 0 | J52: =J53 -> 0 | K52: =C52-J52 -> 0 | L52: =IF(C52=0,0,J52/C52) -> 0
A53: 0510 | B53: ="Siding Materials"&IF($K53="Y"," (Allowance)","") -> Siding Materials | C53: =Estimate!F53 -> 0 | J53: 0 | K53: =C53-J53 -> 0 | L53: =IF(C53=0,0,J53/C53) -> 0
B54: Siding materials package | C54: =Estimate!F54 -> 0 | J54: =J55 -> 0 | K54: =C54-J54 -> 0 | L54: =IF(C54=0,0,J54/C54) -> 0
A55: 0520 | B55: ="Siding Labor"&IF($K55="Y"," (Allowance)","") -> Siding Labor | C55: =Estimate!F55 -> 0 | J55: 0 | K55: =C55-J55 -> 0 | L55: =IF(C55=0,0,J55/C55) -> 0
B56: Siding labor - 7" horizontal | C56: =Estimate!F56 -> 0 | J56: 0 | K56: =C56-J56 -> 0 | L56: =IF(C56=0,0,J56/C56) -> 0
B57: Siding labor - Soffits | C57: =Estimate!F57 -> 0 | J57: 0 | K57: =C57-J57 -> 0 | L57: =IF(C57=0,0,J57/C57) -> 0
B58: Siding labor - Post wraps | C58: =Estimate!F58 -> 0 | J58: =J59 -> 0 | K58: =C58-J58 -> 0 | L58: =IF(C58=0,0,J58/C58) -> 0
A59: 0530 | B59: ="Roofing Specifications"&IF($K59="Y"," (Allowance)","") -> Roofing Specifications | C59: =Estimate!F59 -> 0 | J59: 0 | K59: =C59-J59 -> 0 | L59: =IF(C59=0,0,J59/C59) -> 0
B60: Roofing Material | C60: =Estimate!F60 -> 0 | J60: 0 | K60: =C60-J60 -> 0 | L60: =IF(C60=0,0,J60/C60) -> 0
B61: Roofing Labor | C61: =Estimate!F61 -> 0 | J61: =J62 -> 0 | K61: =C61-J61 -> 0 | L61: =IF(C61=0,0,J61/C61) -> 0
A62: 0540 | B62: ="Gutters"&IF($K62="Y"," (Allowance)","") -> Gutters | C62: =Estimate!F62 -> 0 | J62: 0 | K62: =C62-J62 -> 0 | L62: =IF(C62=0,0,J62/C62) -> 0
B63: Gutters | C63: =Estimate!F63 -> 0 | J63: 0 | K63: =C63-J63 -> 0 | L63: =IF(C63=0,0,J63/C63) -> 0
A64: 0550 | B64: ="Exterior Masonry"&IF($K64="Y"," (Allowance)","") -> Exterior Masonry | C64: =Estimate!F64 -> 0 | J64: 0 | K64: =C64-J64 -> 0 | L64: =IF(C64=0,0,J64/C64) -> 0
B65: Cultured stone | C65: =Estimate!F65 -> 0 | J65: =J66 -> 0 | K65: =C65-J65 -> 0 | L65: =IF(C65=0,0,J65/C65) -> 0
A66: 0560 | B66: ="Exterior Painting"&IF($K66="Y"," (Allowance)","") -> Exterior Painting | C66: =Estimate!F66 -> 0 | J66: 0 | K66: =C66-J66 -> 0 | L66: =IF(C66=0,0,J66/C66) -> 0
B67: Exterior Painting Material & Labor | C67: =Estimate!F67 -> 0 | J67: =J68 -> 0 | K67: =C67-J67 -> 0 | L67: =IF(C67=0,0,J67/C67) -> 0
A68: 0570 | B68: ="Concrete Flatwork"&IF($K68="Y"," (Allowance)","") -> Concrete Flatwork | C68: =Estimate!F68 -> 0 | J68: 0 | K68: =C68-J68 -> 0 | L68: =IF(C68=0,0,J68/C68) -> 0
B69: Driveway | C69: =Estimate!F69 -> 0 | J69: 0 | K69: =C69-J69 -> 0 | L69: =IF(C69=0,0,J69/C69) -> 0
B70: Exterior concrete patio & walkway | C70: =Estimate!F70 -> 0 | J70: 0 | K70: =C70-J70 -> 0 | L70: =IF(C70=0,0,J70/C70) -> 0
B71: Garage slab | C71: =Estimate!F71 -> 0 | J71: 0 | K71: =C71-J71 -> 0 | L71: =IF(C71=0,0,J71/C71) -> 0
A72: 0600 | B72: HVAC | C72: =Estimate!F72 -> 0 | J72: =J73 -> 0 | K72: =C72-J72 -> 0 | L72: =IF(C72=0,0,J72/C72) -> 0
A73: 0610 | B73: ="HVAC"&IF($K73="Y"," (Allowance)","") -> HVAC | C73: =Estimate!F73 -> 0 | J73: 0 | K73: =C73-J73 -> 0 | L73: =IF(C73=0,0,J73/C73) -> 0
B74: HVAC system | C74: =Estimate!F74 -> 0 | J74: =J75 -> 0 | K74: =C74-J74 -> 0 | L74: =IF(C74=0,0,J74/C74) -> 0
A75: 0620 | B75: ="Fireplace"&IF($K75="Y"," (Allowance)","") -> Fireplace | C75: =Estimate!F75 -> 0 | J75: 0 | K75: =C75-J75 -> 0 | L75: =IF(C75=0,0,J75/C75) -> 0
B76: Fireplace - install only + stove pipe parts | C76: =Estimate!F76 -> 0 | J76: 0 | K76: =C76-J76 -> 0 | L76: =IF(C76=0,0,J76/C76) -> 0
A77: 0700 | B77: Plumbing | C77: =Estimate!F77 -> 0 | J77: =J78 -> 0 | K77: =C77-J77 -> 0 | L77: =IF(C77=0,0,J77/C77) -> 0
A78: 0710 | B78: ="Plumbing"&IF($K78="Y"," (Allowance)","") -> Plumbing | C78: =Estimate!F78 -> 0 | J78: 0 | K78: =C78-J78 -> 0 | L78: =IF(C78=0,0,J78/C78) -> 0
B79: Plumbing quote complete | C79: =Estimate!F79 -> 0 | J79: 0 | K79: =C79-J79 -> 0 | L79: =IF(C79=0,0,J79/C79) -> 0
A80: 0800 | B80: Electrical | C80: =Estimate!F80 -> 0 | J80: =J81 -> 0 | K80: =C80-J80 -> 0 | L80: =IF(C80=0,0,J80/C80) -> 0
A81: 0810 | B81: ="Electrical"&IF($K81="Y"," (Allowance)","") -> Electrical | C81: =Estimate!F81 -> 0 | J81: 0 | K81: =C81-J81 -> 0 | L81: =IF(C81=0,0,J81/C81) -> 0
B82: Electrical System | C82: =Estimate!F82 -> 0 | J82: 0 | K82: =C82-J82 -> 0 | L82: =IF(C82=0,0,J82/C82) -> 0
B83: Low-voltage rough-in (data / cable / TV) | C83: =Estimate!F83 -> 0 | J83: 0 | K83: =C83-J83 -> 0 | L83: =IF(C83=0,0,J83/C83) -> 0
B84: EV charger circuit (rough-in) | C84: =Estimate!F84 -> 0 | J84: 0 | K84: =C84-J84 -> 0 | L84: =IF(C84=0,0,J84/C84) -> 0
A85: 0820 | B85: ="Electrical Fixtures"&IF($K85="Y"," (Allowance)","") -> Electrical Fixtures | C85: =Estimate!F85 -> 0 | J85: 0 | K85: =C85-J85 -> 0 | L85: =IF(C85=0,0,J85/C85) -> 0
B86: Fixture allowance | C86: =Estimate!F86 -> 0 | J86: 0 | K86: =C86-J86 -> 0 | L86: =IF(C86=0,0,J86/C86) -> 0
A87: 0900 | B87: Insulation | C87: =Estimate!F87 -> 0 | J87: =J88 -> 0 | K87: =C87-J87 -> 0 | L87: =IF(C87=0,0,J87/C87) -> 0
A88: 0910 | B88: ="Insulation"&IF($K88="Y"," (Allowance)","") -> Insulation | C88: =Estimate!F88 -> 0 | J88: 0 | K88: =C88-J88 -> 0 | L88: =IF(C88=0,0,J88/C88) -> 0
B89: Insulation | C89: =Estimate!F89 -> 0 | J89: 0 | K89: =C89-J89 -> 0 | L89: =IF(C89=0,0,J89/C89) -> 0
A90: 1000 | B90: Interior Wall & Ceiling Finishes | C90: =Estimate!F90 -> 0 | J90: =J91 -> 0 | K90: =C90-J90 -> 0 | L90: =IF(C90=0,0,J90/C90) -> 0
A91: 1010 | B91: ="Drywall"&IF($K91="Y"," (Allowance)","") -> Drywall | C91: =Estimate!F91 -> 0 | J91: 0 | K91: =C91-J91 -> 0 | L91: =IF(C91=0,0,J91/C91) -> 0
B92: Drywall, hang, tape, texture | C92: =Estimate!F92 -> 0 | J92: =J93 -> 0 | K92: =C92-J92 -> 0 | L92: =IF(C92=0,0,J92/C92) -> 0
A93: 1020 | B93: ="Interior Paint"&IF($K93="Y"," (Allowance)","") -> Interior Paint | C93: =Estimate!F93 -> 0 | J93: 0 | K93: =C93-J93 -> 0 | L93: =IF(C93=0,0,J93/C93) -> 0
B94: Interior wall/ceiling/trim painting | C94: =Estimate!F94 -> 0 | J94: 0 | K94: =C94-J94 -> 0 | L94: =IF(C94=0,0,J94/C94) -> 0
A95: 1030 | B95: ="Interior Paint Color(s)"&IF($K95="Y"," (Allowance)","") -> Interior Paint Color(s) | C95: =Estimate!F95 -> 0 | J95: =J96 -> 0 | K95: =C95-J95 -> 0 | L95: =IF(C95=0,0,J95/C95) -> 0
A96: 1040 | B96: ="Bathroom accessories and mirrors"&IF($K96="Y"," (Allowance)","") -> Bathroom accessories and mirrors | C96: =Estimate!F96 -> 0 | J96: 0 | K96: =C96-J96 -> 0 | L96: =IF(C96=0,0,J96/C96) -> 0
B97: Bathroom mirrors | C97: =Estimate!F97 -> 0 | J97: 0 | K97: =C97-J97 -> 0 | L97: =IF(C97=0,0,J97/C97) -> 0
B98: TP holders, towel rod, towel ring per bath | C98: =Estimate!F98 -> 0 | J98: 0 | K98: =C98-J98 -> 0 | L98: =IF(C98=0,0,J98/C98) -> 0
A99: 1050 | B99: ="Masonry - Fireplace facade"&IF($K99="Y"," (Allowance)","") -> Masonry - Fireplace facade | C99: =Estimate!F99 -> 0 | J99: 0 | K99: =C99-J99 -> 0 | L99: =IF(C99=0,0,J99/C99) -> 0
B100: Stone | C100: =Estimate!F100 -> 0 | J100: 0 | K100: =C100-J100 -> 0 | L100: =IF(C100=0,0,J100/C100) -> 0
B101: Wood Mantel | C101: =Estimate!F101 -> 0 | J101: 0 | K101: =C101-J101 -> 0 | L101: =IF(C101=0,0,J101/C101) -> 0
...

Sheet Material Takeoff
A1: RIDGELINE CONSTRUCTION
A2: MATERIAL LIST - No pricing on this tab | Col H shows formula logic (excluded from print)
A4: JOB INFORMATION | F4: KEY DIMENSIONS (yellow = enter here)
A5: Job Name: | B5: =Settings!$C$8 -> Truesdell SFD | F5: Ext. Wall Lineal Ft: | G5: =Settings!$C$20 -> 190
A6: Client Name: | F6: Ext. Wall Sq Ft: | G6: =Settings!$C$23 -> 1710
A7: Job Address: | B7: =Settings!$C$9 -> 0 | F7: Roof Sq Ft: | G7: =(Settings!$C$13+Settings!$C$14+Settings!$C$15)*1.4 -> 3248
A8: Date: | B8: =TODAY() -> 46205 | F8: Living Sq Ft: | G8: =Settings!$C$13 -> 1800
A9: Estimator: | F9: Deck Sq Ft: | G9: =Settings!$C$16+Settings!$C$17 -> 0
F10: Concrete Slab Sq Ft: | G10: =Settings!$C$14 -> 400
A12: # | B12: Description | C12: Size | D12: Grade / Species | E12: Use / Location / Notes | F12: Qty | G12: Unit | H12: Formula Logic [screen only]
A13: FOUNDATION & FLOOR STRUCTURE
A14: 1 | B14: PT sill plate | C14: 2x6 16' | D14: P.T. pine | E14: Foundation perimeter sill | F14: =IFERROR(CEILING($G$5/16,1),0) -> 12 | G14: pcs | H14: EWLF / 16' each
A15: 2 | B15: Sill seal foam | C15: 6in 50' | D15: foam/fiberglass | E15: Between sill & concrete | F15: =IFERROR(CEILING($G$5/50,1),0) -> 4 | G15: rolls | H15: EWLF / 50' per roll
A16: 3 | B16: Sill plate washers | C16: 3x3x1/4in | D16: galvanized | E16: Under anchor bolt nuts | F16: =IFERROR(CEILING($G$5*2/100,1),0) -> 4 | G16: boxes | H16: EWLF x 2 / 100 per box
A17: 4 | B17: BCI floor joist pkg | C17: 9-1/2in BCI-5000 | D17: engineered | E17: Floor joists 16" o.c. | F17: =IFERROR(CEILING($G$8*0.8,1),0) -> 1440 | G17: LF | H17: LSF x 0.80 LF
A18: 5 | B18: T&G OSB subfloor | C18: 4x8 1-1/8in | D18: OSB T&G | E18: Glue-nail subfloor | F18: =IFERROR(CEILING($G$8*1.05/32,1),0) -> 60 | G18: sheets | H18: LSF x 1.05 / 32 sf/sheet
A19: 6 | B19: Pony wall plate | C19: 2x6 16' | D19: KD DF | E19: Pony wall top & bottom plates | F19: =IFERROR(CEILING($G$5*2/16,1),0) -> 24 | G19: pcs | H19: EWLF x 2 plates / 16'
A20: 7 | B20: Pony wall stud | C20: 2x6 104-5/8in | D20: KD DF | E20: Pony wall studs 16" o.c. | F20: =IFERROR(CEILING($G$5*0.75,1),0) -> 143 | G20: pcs | H20: EWLF x 0.75 studs
A21: 8 | B21: Pony wall sheathing | C21: 4x8 7/16in | D21: OSB RTD | E21: Pony wall ext sheathing | F21: =IFERROR(CEILING($G$5*2/32,1),0) -> 12 | G21: sheets | H21: EWLF x 2 sides / 32 sf/sheet
A22: 9 | B22: Framing nails | C22: 3in 10d | D22: vinyl coated | E22: Framing nailer | F22: =IFERROR(CEILING(($G$6+$G$8+$G$7)/2000,1),0) -> 4 | G22: boxes | H22: (EWSF + LSF + RSF) / 2000 per box
A23: 10 | B23: Sheathing nails | C23: 2-3/8in 8d | D23: ring-shank galv | E23: Sheathing nailer | F23: =IFERROR(CEILING(($G$6+$G$7)/2000,1),0) -> 3 | G23: boxes | H23: (EWSF + RSF) / 2000 per box
A24: 11 | B24: Sheathing staples | C24: 1-3/4in 7/16in | D24: electro galv | E24: Sheathing stapler | F24: =IFERROR(CEILING($G$6/2000,1),0) -> 1 | G24: boxes | H24: EWSF / 2000
A25: WALL FRAMING
A26: 12 | B26: Ext wall plate | C26: 2x6 16' | D26: KD DF | E26: Ext walls - 3 plates + window cuts & backing | F26: =IFERROR(CEILING($G$5*3/16*1.25,1),0) -> 45 | G26: pcs | H26: EWLF x 3 plates / 16' x 1.25 (incl. window cut waste & backing)
A27: 13 | B27: Ext wall stud | C27: 2x6 104-5/8in | D27: KD DF | E27: Ext studs 16" o.c. | F27: =IFERROR(CEILING($G$6/9*0.75*1.15,1),0) -> 164 | G27: pcs | H27: EWSF / 9 sf x 0.75 x 1.15 waste
A28: 14 | B28: Wall sheathing | C28: 4x9 7/16in | D28: OSB RTD | E28: Ext wall sheathing | F28: =IFERROR(CEILING($G$6*1.1/36,1),0) -> 53 | G28: sheets | H28: EWSF x 1.10 / 36 sf/sheet
A29: 15 | B29: Window header | C29: 4x10 14' | D29: #2 DF GRN | E29: Window rough openings | F29: 0 | G29: pcs | H29: MANUAL
A30: 16 | B30: LG door/garage header | C30: Glulam 5-1/2x12 | D30: 1.8E DF | E30: Garage or large openings | F30: 0 | G30: LF | H30: MANUAL
A31: 17 | B31: Int wall plate | C31: 2x4 16' | D31: KD DF | E31: Int walls - 3 plates + 10% waste | F31: =IFERROR(CEILING($G$8/8*3/16*1.1,1),0) -> 47 | G31: pcs | H31: LSF / 8 x 3 plates / 16' x 1.10
A32: 18 | B32: Int wall stud | C32: 2x4 104-5/8in | D32: KD DF | E32: Int studs 16" o.c. | F32: =IFERROR(CEILING($G$8/8*0.75*1.15,1),0) -> 195 | G32: pcs | H32: LSF / 8 x 0.75 x 1.15 waste
A33: 19 | B33: PT sill (garage/slab) | C33: 2x4 14' | D33: P.T. pine | E33: Interior slab sill plate | F33: 0 | G33: pcs | H33: MANUAL
A34: ROOF FRAMING & TRIM
A35: 20 | B35: Roof sheathing | C35: 4x8 7/16in | D35: OSB RTD | E35: Roof decking | F35: =IFERROR(CEILING($G$7*1.1/32,1),0) -> 112 | G35: sheets | H35: RSF x 1.10 / 32 sf/sheet
A36: 21 | B36: Plywood clips | C36: 7/16in H-clips | D36: metal | E36: Between roof sheets at mid-span | F36: =IFERROR(CEILING($G$7/64,1),0) -> 51 | G36: boxes | H36: RSF / 64 sf per box
A37: 22 | B37: Barge rafter | C37: 2x8 20' | D37: primed cypress | E37: Barge rafters & gable | F37: =IFERROR(CEILING($G$5*0.2/20*1.1,1),0) -> 3 | G37: pcs | H37: EWLF x 0.20 / 20' x 1.10
A38: 23 | B38: Fascia board | C38: 5/4x8 20' | D38: primed cypress | E38: Fascia | F38: =IFERROR(CEILING($G$5*1.05/20,1),0) -> 10 | G38: pcs | H38: EWLF x 1.05 / 20'
A39: 24 | B39: Subfascia nailer | C39: 1x4 12' | D39: utility DF | E39: Subfascia | F39: =IFERROR(CEILING($G$5*1.05/12,1),0) -> 17 | G39: pcs | H39: EWLF x 1.05 / 12'
A40: 25 | B40: Roof bracing/lookout | C40: 2x4 12' | D40: KD DF | E40: Outlookers, bracing | F40: =IFERROR(CEILING($G$5*0.15/12,1),0) -> 3 | G40: pcs | H40: EWLF x 0.15 / 12'
A41: 26 | B41: Soffit panel | C41: 16inx16ft 7/16in | D41: LP SmartSide | E41: Eave soffit | F41: =IFERROR(CEILING($G$5*1.5/16,1),0) -> 18 | G41: pcs | H41: EWLF x 1.5 ft overhang / 16'
A42: 27 | B42: Barge sheathing | C42: 12inx16ft 7/16in | D42: LP SmartSide | E42: Barge rafter sheathing | F42: =IFERROR(CEILING($G$5*0.15/16,1),0) -> 2 | G42: pcs | H42: EWLF x 0.15 / 16'
A43: 28 | B43: Barge trim | C43: 1x4 20' | D43: primed cypress | E43: Barge rafter trim cover | F43: =IFERROR(CEILING($G$5*0.2/20,1),0) -> 2 | G43: pcs | H43: EWLF x 0.20 / 20'
A44: SIDING & EXTERIOR TRIM
A45: 29 | B45: House wrap | C45: 9ftx150ft | D45: Tyvek HomeWrap | E45: Full exterior wrap | F45: =IFERROR(CEILING($G$6/1350,1),0) -> 2 | G45: rolls | H45: EWSF / 1350 sf per roll
A46: 30 | B46: Flashing tape 6in | C46: 6in roll | D46: butyl | E46: Window/door RO flashing | F46: =IFERROR(CEILING($G$5/50,1),0) -> 4 | G46: rolls | H46: EWLF / 50' per roll
A47: 31 | B47: Flashing tape 4in | C47: 4in roll | D47: butyl | E47: Seams & penetrations | F47: =IFERROR(CEILING($G$5/50,1),0) -> 4 | G47: rolls | H47: EWLF / 50' per roll
A48: 32 | B48: Tyvek tape | C48: 2in roll | D48: Tyvek tape | E48: Sealing wrap seams | F48: =IFERROR(CEILING($G$6/500,1),0) -> 4 | G48: rolls | H48: EWSF / 500 per roll
A49: 33 | B49: Lap siding Hz10 | C49: 8-1/4inx12ft | D49: fiber cement | E49: Exterior lap siding | F49: =IFERROR(CEILING($G$6*1.1/100,1),0) -> 19 | G49: squares | H49: EWSF x 1.10 / 100 sf per sq
A50: 34 | B50: Corner boards | C50: 5/4x4 20' | D50: primed cypress | E50: Exterior corners | F50: =IFERROR(CEILING($G$5*0.06,1),0) -> 12 | G50: pcs | H50: EWLF x 0.06 (corner count est.)
A51: 35 | B51: Window casing trim | C51: 5/4x4 16' | D51: primed cypress | E51: Window casings | F51: 0 | G51: pcs | H51: MANUAL
A52: 36 | B52: Band/trim board | C52: 5/4x6 20' | D52: primed cypress | E52: Band boards, trim | F52: =IFERROR(CEILING($G$5*0.15/20,1),0) -> 2 | G52: pcs | H52: EWLF x 0.15 / 20'
A53: 37 | B53: Belly band | C53: 5/4x8 16' | D53: primed cypress | E53: Belly band / water table | F53: =IFERROR(CEILING($G$5*1.05/16,1),0) -> 13 | G53: pcs | H53: EWLF x 1.05 / 16'
A54: 38 | B54: Inside corners | C54: 2x2 10' | D54: primed | E54: Inside corner trim | F54: =IFERROR(CEILING($G$5*0.04,1),0) -> 8 | G54: pcs | H54: EWLF x 0.04
A55: 39 | B55: 1x2 trim | C55: 1x2 16' | D55: primed cypress | E55: Z-flashing base / small trim | F55: =IFERROR(CEILING($G$5*0.2/16,1),0) -> 3 | G55: pcs | H55: EWLF x 0.20 / 16'
A56: 40 | B56: Hardi panel (gable) | C56: 4x8 1/4in | D56: cedar mill | E56: Panel siding - gables/accents | F56: 0 | G56: sheets | H56: MANUAL
A57: 41 | B57: Window high-back flashing | C57: 1x4in | D57: white | E57: Window sill pan flashing | F57: 0 | G57: pcs | H57: MANUAL
A58: 42 | B58: Exterior caulk TX-1 | C58: 10 oz tube | D58: sealant | E58: All exterior joints | F58: =IFERROR(CEILING($G$6/200,1),0) -> 9 | G58: tubes | H58: EWSF / 200 per tube
A59: 43 | B59: Siding nails | C59: electro-galv coil | D59: fiber cement | E59: Lap siding gun nails | F59: =IFERROR(CEILING($G$6/500,1),0) -> 4 | G59: boxes | H59: EWSF / 500 per box
A60: DECK
A61: 44 | B61: PT ledger & rim board | C61: 2x6 16' | D61: P.T. | E61: Perimeter ledger + rim | F61: =IF($G$9>0,IFERROR(CEILING(SQRT($G$9)*3/16,1),0),0) -> 0 | G61: pcs | H61: IF DSF>0: sqrt(DSF) x 3 / 16'
A62: 45 | B62: PT deck joist | C62: 2x8 16' | D62: P.T. | E62: Deck joists 16" o.c. | F62: =IF($G$9>0,IFERROR(CEILING($G$9*0.8,1),0),0) -> 0 | G62: LF | H62: IF DSF>0: DSF x 0.80 LF
A63: 46 | B63: PT post 4x4 | C63: 4x4 12' | D63: P.T. | E63: Deck support posts | F63: =IF($G$9>0,IFERROR(CEILING(SQRT($G$9)/6,1),0),0) -> 0 | G63: pcs | H63: IF DSF>0: sqrt(DSF) / 6
A64: 47 | B64: PT beam post 6x6 | C64: 6x6 12' | D64: P.T. | E64: Heavy beam support posts | F64: =IF($G$9>0,4,0) -> 0 | G64: pcs | H64: IF DSF>0: 4 pcs
A65: 48 | B65: Composite decking | C65: 5/4x6 16' | D65: Fiberon/Trex | E65: Deck surface | F65: =IF($G$9>0,IFERROR(CEILING($G$9*1.1/(5.5/12*16),1),0),0) -> 0 | G65: pcs | H65: IF DSF>0: DSF x 1.10 / (5.5/12 x 16')
A66: 49 | B66: Deck hardware & fasteners | C66: misc | D66: galvanized | E66: Joist hangers, lag screws, clips | F66: =IF($G$9>0,1,0) -> 0 | G66: allow | H66: IF DSF>0: 1 allowance
A67: STAIRCASE MATERIALS (key in qtys if applicable)
A68: 50 | B68: Stringers | C68: 2x12x20' | D68: #2 DF / key in species | E68: Staircase stringers | F68: 0 | G68: pcs | H68: MANUAL -- enter qty if staircase applies
A69: 51 | B69: Risers | C69: varies / key in | D69: key in | E69: Staircase risers | F69: 0 | G69: pcs | H69: MANUAL -- enter qty if staircase applies
A70: 52 | B70: Treads | C70: varies / key in | D70: key in | E70: Staircase treads | F70: 0 | G70: pcs | H70: MANUAL -- enter qty if staircase applies
A71: 53 | B71: Stair hangers & fasteners | C71: misc | D71: galvanized | E71: Staircase hardware allowance | F71: 0 | G71: allow | H71: MANUAL -- enter qty if staircase applies
A73: NOTES -- Porch Posts / Beams / Other Specialty Items (type notes in yellow cells)
A74: Porch Posts / Columns:
A77: Beams / Specialty Framing:
A80: Other Specialty Items:
A84: YELLOW = enter manually | All other qty auto-calculated from key dimensions | Col H = formula logic (print-excluded)

Sheet Material Estimate
A1: RIDGELINE CONSTRUCTION - PROJECT ESTIMATE
A2: ='Material Takeoff'!B5 -> Truesdell SFD | D2: ='Material Takeoff'!G9 -> 0
A4: Prices linked to Price Database (BFS QT# 4269124 - 06-26-2026) | F4: Markup %: | H4: =Settings!$C$35 -> 0.2
A6: # | B6: Description | C6: Size / Grade | D6: Qty | E6: Unit | F6: Used / Location | G6: Unit Price | H6: Total
A7: FOUNDATION & FLOOR STRUCTURE
A8: 1 | B8: PT sill plate | C8: 2x6 16' - P.T. pine | D8: ='Material Takeoff'!F14 -> 12 | E8: pcs | F8: Foundation perimeter sill | G8: ='Price Database'!$E$20*16/1000 -> 21.808 | H8: =IFERROR(D8*G8,0) -> 261.696
A9: 2 | B9: Sill seal foam | C9: 6in 50' - foam/fiberglass | D9: ='Material Takeoff'!F15 -> 4 | E9: rolls | F9: Between sill & concrete | G9: 14.95 | H9: =IFERROR(D9*G9,0) -> 59.8
A10: 3 | B10: Sill plate washers | C10: 3x3x1/4in - galvanized | D10: ='Material Takeoff'!F16 -> 4 | E10: boxes | F10: Under anchor bolt nuts | G10: 24.99 | H10: =IFERROR(D10*G10,0) -> 99.96
A11: 4 | B11: BCI floor joist pkg | C11: 9-1/2in BCI-5000 - engineered | D11: ='Material Takeoff'!F17 -> 1440 | E11: LF | F11: Floor joists 16" o.c. | G11: ='Price Database'!$E$16 -> 3.19 | H11: =IFERROR(D11*G11,0) -> 4593.6
A12: 5 | B12: T&G OSB subfloor | C12: 4x8 1-1/8in - OSB T&G | D12: ='Material Takeoff'!F18 -> 60 | E12: sheets | F12: Glue-nail subfloor | G12: ='Price Database'!$E$14*32/1000 -> 38.24 | H12: =IFERROR(D12*G12,0) -> 2294.4
A13: 6 | B13: Pony wall plate | C13: 2x6 16' - KD DF | D13: ='Material Takeoff'!F19 -> 24 | E13: pcs | F13: Pony wall top & bottom plates | G13: ='Price Database'!$E$5*16/1000 -> 12.8 | H13: =IFERROR(D13*G13,0) -> 307.2
A14: 7 | B14: Pony wall stud | C14: 2x6 104-5/8in - KD DF | D14: ='Material Takeoff'!F20 -> 143 | E14: pcs | F14: Pony wall studs 16" o.c. | G14: ='Price Database'!$E$8*8.71875/1000 -> 6.870375 | H14: =IFERROR(D14*G14,0) -> 982.46362
A15: 8 | B15: Pony wall sheathing | C15: 4x8 7/16in - OSB RTD | D15: ='Material Takeoff'!F21 -> 12 | E15: sheets | F15: Pony wall ext sheathing | G15: ='Price Database'!$E$11*32/1000 -> 11.904 | H15: =IFERROR(D15*G15,0) -> 142.848
A16: 9 | B16: Framing nails | C16: 3in 10d - vinyl coated | D16: ='Material Takeoff'!F22 -> 4 | E16: boxes | F16: Framing nailer | G16: 64.99 | H16: =IFERROR(D16*G16,0) -> 259.96
A17: 10 | B17: Sheathing nails | C17: 2-3/8in 8d - ring-shank galv | D17: ='Material Takeoff'!F23 -> 3 | E17: boxes | F17: Sheathing nailer | G17: 48.99 | H17: =IFERROR(D17*G17,0) -> 146.97
A18: 11 | B18: Sheathing staples | C18: 1-3/4in 7/16in - electro galv | D18: ='Material Takeoff'!F24 -> 1 | E18: boxes | F18: Sheathing stapler | G18: 52 | H18: =IFERROR(D18*G18,0) -> 52
A19: FOUNDATION & FLOOR STRUCTURE — Subtotal | H19: =SUM(H8:H18) -> 9200.8976
A20: WALL FRAMING
A21: 12 | B21: Ext wall plate | C21: 2x6 16' - KD DF | D21: ='Material Takeoff'!F26 -> 45 | E21: pcs | F21: Ext walls - 3 plates + window cuts & backing | G21: ='Price Database'!$E$5*16/1000 -> 12.8 | H21: =IFERROR(D21*G21,0) -> 576
A22: 13 | B22: Ext wall stud | C22: 2x6 104-5/8in - KD DF | D22: ='Material Takeoff'!F27 -> 164 | E22: pcs | F22: Ext studs 16" o.c. | G22: ='Price Database'!$E$8*8.71875/1000 -> 6.870375 | H22: =IFERROR(D22*G22,0) -> 1126.7415
A23: 14 | B23: Wall sheathing | C23: 4x9 7/16in - OSB RTD | D23: ='Material Takeoff'!F28 -> 53 | E23: sheets | F23: Ext wall sheathing | G23: ='Price Database'!$E$12*36/1000 -> 14.94 | H23: =IFERROR(D23*G23,0) -> 791.82
A24: 15 | B24: Window header | C24: 4x10 14' - #2 DF GRN | D24: ='Material Takeoff'!F29 -> 0 | E24: pcs | F24: Window rough openings | G24: ='Price Database'!$E$9*46.66667/1000 -> 46.620003 | H24: =IFERROR(D24*G24,0) -> 0
A25: 16 | B25: LG door/garage header | C25: Glulam 5-1/2x12 - 1.8E DF | D25: ='Material Takeoff'!F30 -> 0 | E25: LF | F25: Garage or large openings | G25: ='Price Database'!$E$18 -> 22.29 | H25: =IFERROR(D25*G25,0) -> 0
A26: 17 | B26: Int wall plate | C26: 2x4 16' - KD DF | D26: ='Material Takeoff'!F31 -> 47 | E26: pcs | F26: Int walls - 3 plates + 10% waste | G26: ='Price Database'!$E$6*10.66667/1000 -> 7.9466691 | H26: =IFERROR(D26*G26,0) -> 373.49345
A27: 18 | B27: Int wall stud | C27: 2x4 104-5/8in - KD DF | D27: ='Material Takeoff'!F32 -> 195 | E27: pcs | F27: Int studs 16" o.c. | G27: ='Price Database'!$E$7*5.8125/1000 -> 4.2954375 | H27: =IFERROR(D27*G27,0) -> 837.61031
A28: 19 | B28: PT sill (garage/slab) | C28: 2x4 14' - P.T. pine | D28: ='Material Takeoff'!F33 -> 0 | E28: pcs | F28: Interior slab sill plate | G28: ='Price Database'!$E$20*9.33333/1000 -> 12.721329 | H28: =IFERROR(D28*G28,0) -> 0
A29: WALL FRAMING — Subtotal | H29: =SUM(H21:H28) -> 3705.6653
A30: ROOF FRAMING & TRIM
A31: 20 | B31: Roof sheathing | C31: 4x8 7/16in - OSB RTD | D31: ='Material Takeoff'!F35 -> 112 | E31: sheets | F31: Roof decking | G31: ='Price Database'!$E$11*32/1000 -> 11.904 | H31: =IFERROR(D31*G31,0) -> 1333.248
A32: 21 | B32: Plywood clips | C32: 7/16in H-clips - metal | D32: ='Material Takeoff'!F36 -> 51 | E32: boxes | F32: Between roof sheets at mid-span | G32: 15 | H32: =IFERROR(D32*G32,0) -> 765
A33: 22 | B33: Barge rafter | C33: 2x8 20' - primed cypress | D33: ='Material Takeoff'!F37 -> 3 | E33: pcs | F33: Barge rafters & gable | G33: ='Price Database'!$E$32*26.66667/1000 -> 104.24001 | H33: =IFERROR(D33*G33,0) -> 312.72004
A34: 23 | B34: Fascia board | C34: 5/4x8 20' - primed cypress | D34: ='Material Takeoff'!F38 -> 10 | E34: pcs | F34: Fascia | G34: ='Price Database'!$E$31*(1.25*8*20/12)/1000 -> 76.15 | H34: =IFERROR(D34*G34,0) -> 761.5
A35: 24 | B35: Subfascia nailer | C35: 1x4 12' - utility DF | D35: ='Material Takeoff'!F39 -> 17 | E35: pcs | F35: Subfascia | G35: 7.5 | H35: =IFERROR(D35*G35,0) -> 127.5
A36: 25 | B36: Roof bracing/lookout | C36: 2x4 12' - KD DF | D36: ='Material Takeoff'!F40 -> 3 | E36: pcs | F36: Outlookers, bracing | G36: ='Price Database'!$E$6*8/1000 -> 5.96 | H36: =IFERROR(D36*G36,0) -> 17.88
A37: 26 | B37: Soffit panel | C37: 16inx16ft 7/16in - LP SmartSide | D37: ='Material Takeoff'!F41 -> 18 | E37: pcs | F37: Eave soffit | G37: 34.99 | H37: =IFERROR(D37*G37,0) -> 629.82
A38: 27 | B38: Barge sheathing | C38: 12inx16ft 7/16in - LP SmartSide | D38: ='Material Takeoff'!F42 -> 2 | E38: pcs | F38: Barge rafter sheathing | G38: 27.99 | H38: =IFERROR(D38*G38,0) -> 55.98
A39: 28 | B39: Barge trim | C39: 1x4 20' - primed cypress | D39: ='Material Takeoff'!F43 -> 2 | E39: pcs | F39: Barge rafter trim cover | G39: ='Price Database'!$E$34*6.66667/1000 -> 25.179946 | H39: =IFERROR(D39*G39,0) -> 50.359892
A40: ROOF FRAMING & TRIM — Subtotal | H40: =SUM(H31:H39) -> 4054.0079
A41: SIDING & EXTERIOR TRIM
A42: 29 | B42: House wrap | C42: 9ftx150ft - Tyvek HomeWrap | D42: ='Material Takeoff'!F45 -> 2 | E42: rolls | F42: Full exterior wrap | G42: 209.99 | H42: =IFERROR(D42*G42,0) -> 419.98
A43: 30 | B43: Flashing tape 6in | C43: 6in roll - butyl | D43: ='Material Takeoff'!F46 -> 4 | E43: rolls | F43: Window/door RO flashing | G43: 21.99 | H43: =IFERROR(D43*G43,0) -> 87.96
A44: 31 | B44: Flashing tape 4in | C44: 4in roll - butyl | D44: ='Material Takeoff'!F47 -> 4 | E44: rolls | F44: Seams & penetrations | G44: 17.99 | H44: =IFERROR(D44*G44,0) -> 71.96
A45: 32 | B45: Tyvek tape | C45: 2in roll - Tyvek tape | D45: ='Material Takeoff'!F48 -> 4 | E45: rolls | F45: Sealing wrap seams | G45: 8.49 | H45: =IFERROR(D45*G45,0) -> 33.96
A46: 33 | B46: Lap siding Hz10 | C46: 8-1/4inx12ft - fiber cement | D46: ='Material Takeoff'!F49 -> 19 | E46: squares | F46: Exterior lap siding | G46: ='Price Database'!$E$27*100/1000 -> 156.6 | H46: =IFERROR(D46*G46,0) -> 2975.4
A47: 34 | B47: Corner boards | C47: 5/4x4 20' - primed cypress | D47: ='Material Takeoff'!F50 -> 12 | E47: pcs | F47: Exterior corners | G47: ='Price Database'!$E$30*8.33333/1000 -> 36.100069 | H47: =IFERROR(D47*G47,0) -> 433.20083
A48: 35 | B48: Window casing trim | C48: 5/4x4 16' - primed cypress | D48: ='Material Takeoff'!F51 -> 0 | E48: pcs | F48: Window casings | G48: ='Price Database'!$E$30*6.66667/1000 -> 28.880081 | H48: =IFERROR(D48*G48,0) -> 0
A49: 36 | B49: Band/trim board | C49: 5/4x6 20' - primed cypress | D49: ='Material Takeoff'!F52 -> 2 | E49: pcs | F49: Band boards, trim | G49: ='Price Database'!$E$31*12.5/1000 -> 57.1125 | H49: =IFERROR(D49*G49,0) -> 114.225
A50: 37 | B50: Belly band | C50: 5/4x8 16' - primed cypress | D50: ='Material Takeoff'!F53 -> 13 | E50: pcs | F50: Belly band / water table | G50: ='Price Database'!$E$31*(1.25*8*16/12)/1000 -> 60.92 | H50: =IFERROR(D50*G50,0) -> 791.96
A51: 38 | B51: Inside corners | C51: 2x2 10' - primed | D51: ='Material Takeoff'!F54 -> 8 | E51: pcs | F51: Inside corner trim | G51: 7.99 | H51: =IFERROR(D51*G51,0) -> 63.92
A52: 39 | B52: 1x2 trim | C52: 1x2 16' - primed cypress | D52: ='Material Takeoff'!F55 -> 3 | E52: pcs | F52: Z-flashing base / small trim | G52: ='Price Database'!$E$34*2.66667/1000 -> 10.071986 | H52: =IFERROR(D52*G52,0) -> 30.215958
A53: 40 | B53: Hardi panel (gable) | C53: 4x8 1/4in - cedar mill | D53: ='Material Takeoff'!F56 -> 0 | E53: sheets | F53: Panel siding - gables/accents | G53: ='Price Database'!$E$28*32/1000 -> 50.624 | H53: =IFERROR(D53*G53,0) -> 0
A54: 41 | B54: Window high-back flashing | C54: 1x4in - white | D54: ='Material Takeoff'!F57 -> 0 | E54: pcs | F54: Window sill pan flashing | G54: 14.99 | H54: =IFERROR(D54*G54,0) -> 0
A55: 42 | B55: Exterior caulk TX-1 | C55: 10 oz tube - sealant | D55: ='Material Takeoff'!F58 -> 9 | E55: tubes | F55: All exterior joints | G55: 5.19 | H55: =IFERROR(D55*G55,0) -> 46.71
A56: 43 | B56: Siding nails | C56: electro-galv coil - fiber cement | D56: ='Material Takeoff'!F59 -> 4 | E56: boxes | F56: Lap siding gun nails | G56: 67.99 | H56: =IFERROR(D56*G56,0) -> 271.96
A57: SIDING & EXTERIOR TRIM — Subtotal | H57: =SUM(H42:H56) -> 5341.4518
A58: DECK
A59: 44 | B59: PT ledger & rim board | C59: 2x6 16' - P.T. | D59: ='Material Takeoff'!F61 -> 0 | E59: pcs | F59: Perimeter ledger + rim | G59: ='Price Database'!$E$20*16/1000 -> 21.808 | H59: =IFERROR(D59*G59,0) -> 0
A60: 45 | B60: PT deck joist | C60: 2x8 16' - P.T. | D60: ='Material Takeoff'!F62 -> 0 | E60: LF | F60: Deck joists 16" o.c. | G60: ='Price Database'!$E$21*(2*8/12)/1000 -> 1.684 | H60: =IFERROR(D60*G60,0) -> 0
A61: 46 | B61: PT post 4x4 | C61: 4x4 12' - P.T. | D61: ='Material Takeoff'!F63 -> 0 | E61: pcs | F61: Deck support posts | G61: ='Price Database'!$E$22*16/1000 -> 26.752 | H61: =IFERROR(D61*G61,0) -> 0
A62: 47 | B62: PT beam post 6x6 | C62: 6x6 12' - P.T. | D62: ='Material Takeoff'!F64 -> 0 | E62: pcs | F62: Heavy beam support posts | G62: ='Price Database'!$E$23*36/1000 -> 67.788 | H62: =IFERROR(D62*G62,0) -> 0
A63: 48 | B63: Composite decking | C63: 5/4x6 16' - Fiberon/Trex | D63: ='Material Takeoff'!F65 -> 0 | E63: pcs | F63: Deck surface | G63: 54.99 | H63: =IFERROR(D63*G63,0) -> 0
A64: 49 | B64: Deck hardware & fasteners | C64: misc - galvanized | D64: ='Material Takeoff'!F66 -> 0 | E64: allow | F64: Joist hangers, lag screws, clips | G64: 249.99 | H64: =IFERROR(D64*G64,0) -> 0
A65: DECK — Subtotal | H65: =SUM(H59:H64) -> 0
A66: STAIRCASE MATERIALS (key in qtys if applicable)
A67: 50 | B67: Stringers | C67: 2x12x20' - #2 DF / key in species | D67: ='Material Takeoff'!F68 -> 0 | E67: pcs | F67: Staircase stringers | G67: 0 | H67: =IFERROR(D67*G67,0) -> 0
A68: 51 | B68: Risers | C68: varies / key in - key in | D68: ='Material Takeoff'!F69 -> 0 | E68: pcs | F68: Staircase risers | G68: 0 | H68: =IFERROR(D68*G68,0) -> 0
A69: 52 | B69: Treads | C69: varies / key in - key in | D69: ='Material Takeoff'!F70 -> 0 | E69: pcs | F69: Staircase treads | G69: 0 | H69: =IFERROR(D69*G69,0) -> 0
A70: 53 | B70: Stair hangers & fasteners | C70: misc - galvanized | D70: ='Material Takeoff'!F71 -> 0 | E70: allow | F70: Staircase hardware allowance | G70: 0 | H70: =IFERROR(D70*G70,0) -> 0
A71: STAIRCASE MATERIALS — Subtotal | H71: =SUM(H67:H70) -> 0
A73: MATERIAL SUBTOTAL | H73: =H19+H29+H40+H57+H65+H71 -> 22302.023
A75: SPECIAL ITEMS & ADD-ONS - Enter description, qty, and unit price in yellow cells
A76: # | B76: Description | C76: Notes | D76: Qty | E76: Unit | F76: Used / Location | G76: Unit Price | H76: Total
H77: =IFERROR(D77*G77,0) -> 0
H78: =IFERROR(D78*G78,0) -> 0
H79: =IFERROR(D79*G79,0) -> 0
H80: =IFERROR(D80*G80,0) -> 0
H81: =IFERROR(D81*G81,0) -> 0
H82: =IFERROR(D82*G82,0) -> 0
H83: =IFERROR(D83*G83,0) -> 0
H84: =IFERROR(D84*G84,0) -> 0
H85: =IFERROR(D85*G85,0) -> 0
H86: =IFERROR(D86*G86,0) -> 0
H87: =IFERROR(D87*G87,0) -> 0
H88: =IFERROR(D88*G88,0) -> 0
... H90: =IFERROR(D90*G90,0) -> 0
A91: ADD-ONS SUBTOTAL | H91: =SUM(H77:H90) -> 0
A92: GRAND TOTAL (materials + add-ons) | H92: =H73+H91 -> 22302.023
A93: TOTAL WITH MARKUP | H93: =H92*(1+'Material Estimate'!$H$4) -> 26762.427
A95: BLUE = hardcoded | GREEN = live from Price Database (BFS) | YELLOW = enter manually

Sheet Calculators
A1: RIDGELINE CONSTRUCTION - ESTIMATING CALCULATORS
A2: Standalone calculators - enter dimensions in yellow cells - prices pull from Price Database tab
A4: 1. DECK ESTIMATOR
A5: INPUTS (enter in yellow) | E5: RESULTS (auto)
A6: Deck length (ft): | D6: =(Settings!$C$16+Settings!$C$17)/12 -> 0 | E6: Deck area (sq ft): | H6: =IFERROR($D$6*$D$7,0) -> 0
A7: Deck width (ft): | D7: =IF((Settings!$C$16+Settings!$C$17)=0,0,12) -> 0 | E7: Decking pieces: | H7: =IFERROR(CEILING($D$6*$D$7*1.1/(5.5/12*16),1),0) -> 0
A8: Railing LF (approx): | D8: =IF(D6=0,0,D6+2*D7) -> 0 | E8: Joist LF needed: | H8: =IFERROR(CEILING($D$6*$D$7*0.8,1),0) -> 0
E9: Ledger/rim pcs (16'): | H9: =IFERROR(CEILING(($D$6+$D$7)*2/16,1),0) -> 0
A10: -- Deck Material Pricing -- | E10: Railing LF: | H10: =$D$8 -> 0
A11: Composite decking / pc: | D11: 54.99 | H11: None
A12: PT 2x8 joist / LF: | D12: ='Price Database'!$E$21*(2*8/12)/1000 -> 1.684 | E12: Decking cost: | H12: =IFERROR(CEILING($D$6*$D$7*1.1/(5.5/12*16),1)*$D$11,0) -> 0
A13: Deck hardware allow $: | D13: =IF(D6=0,0,249.99) -> 0 | E13: Joist cost: | H13: =IFERROR(CEILING($D$6*$D$7*0.8,1)*$D$12,0) -> 0
E14: Hardware: | H14: =$D$13 -> 0
A15: -- Metal Post & Rail System (key in qtys) -- | H15: None
A16: Corner posts (qty): | D16: =IF(D6=0,0,2) -> 0 | E16: Corner posts cost: | H16: =IFERROR($D$16*$D$27,0) -> 0
A17: Mid posts (qty): | D17: =MAX(CEILING(D8/6,1)-4,0) -> 0 | E17: Mid posts cost: | H17: =IFERROR($D$17*$D$28,0) -> 0
A18: End posts (qty): | D18: =IF(D6=0,0,2) -> 0 | E18: End posts cost: | H18: =IFERROR($D$18*$D$29,0) -> 0
A19: Stair posts (qty): | D19: =IF(D6=0,0,2) -> 0 | E19: Stair posts cost: | H19: =IFERROR($D$19*$D$30,0) -> 0
A20: 6-ft rail sections (qty): | D20: 0 | E20: 6-ft rail cost: | H20: =IFERROR($D$20*$D$31,0) -> 0
A21: 8-ft rail sections (qty): | D21: =CEILING(D8/8,1) -> 0 | E21: 8-ft rail cost: | H21: =IFERROR($D$21*$D$32,0) -> 0
A22: Brackets (qty): | D22: =D21*4 -> 0 | E22: Brackets cost: | H22: =IFERROR($D$22*$D$33,0) -> 0
A23: Lag bolts (qty): | D23: =(D16+D17+D18+D19)*3 -> 0 | E23: Lag bolts cost: | H23: =IFERROR($D$23*$D$34,0) -> 0
A24: Misc metal rail allow $: | D24: =IF(D6=0,0,150) -> 0 | E24: Misc metal allow: | H24: =$D$24 -> 0
E25: Metal rail subtotal: | H25: =IFERROR($D$16*$D$27+$D$17*$D$28+$D$18*$D$29+$D$19*$D$30+$D$20*$D$31+$D$21*$D$32+$D$22*$D$33+$D$23*$D$34+$D$24,0) -> 0
A26: -- Metal Rail Unit Pricing -- | H26: None
A27: Corner post / ea: | D27: 85 | E27: ESTIMATED TOTAL: | H27: =IFERROR(CEILING($D$6*$D$7*1.1/(5.5/12*16),1)*$D$11+CEILING($D$6*$D$7*0.8,1)*$D$12+$D$13+$D$16*$D$27+$D$17*$D$28+$D$18*$D$29+$D$19*$D$30+$D$20*$D$31+$D$21*$D$32+$D$22*$D$33+$D$23*$D$34+$D$24,0) -> 0
A28: Mid post / ea: | D28: 75
A29: End post / ea: | D29: 75
A30: Stair post / ea: | D30: 85
A31: 6-ft rail section / ea: | D31: 45
A32: 8-ft rail section / ea: | D32: 55
A33: Bracket / ea: | D33: 8
A34: Lag bolt / ea: | D34: 1.25
A37: 2. METAL ROOFING ESTIMATOR
A38: INPUTS (enter in yellow) | E38: RESULTS (auto)
A39: Roof length / ridge (ft): | D39: 0 | E39: Total roof area (sq ft): | H39: =IFERROR($D$39*$D$40*$D$41,0) -> 0
A40: Slope length - peak to gutter (ft): | D40: 0 | E40: Squares needed (10% waste): | H40: =IFERROR(CEILING($D$39*$D$40*$D$41*1.1/100,1),0) -> 0
A41: Number of slopes: | D41: 2 | E41: Panels across ridge: | H41: =IFERROR(CEILING($D$39*12/$D$42,1),0) -> 0
A42: Panel width (inches): | D42: 16 | E42: Total panel pieces: | H42: =IFERROR(CEILING($D$39*12/$D$42,1)*$D$41,0) -> 0
A43: Ridge cap LF: | D43: 0 | E43: Panel length each (ft): | H43: =$D$40 -> 0
A44: Eave drip edge LF: | D44: 0 | E44: Gable trim LF (auto): | H44: =IFERROR($D$40*2,0) -> 0
A45: Valley LF: | D45: 0 | E45: (slope length x 2 sides) | H45: None
E46: Ridge cap LF: | H46: =$D$43 -> 0
A47: Metal panel (per sq): | D47: 394 | E47: Eave drip edge LF: | H47: =$D$44 -> 0
A48: Ridge cap (per LF): | D48: 25 | E48: Valley LF: | H48: =$D$45 -> 0
A49: Gable trim (per LF): | D49: 25 | H49: None
A50: Eave drip edge (per LF): | D50: 15 | E50: Panel cost: | H50: =IFERROR(CEILING($D$39*$D$40*$D$41*1.1/100,1)*$D$47,0) -> 0
A51: Valley flashing (per LF): | D51: 22 | E51: Ridge cap cost: | H51: =IFERROR($D$43*$D$48,0) -> 0
A52: Fasteners allowance $: | D52: 120 | E52: Gable trim cost: | H52: =IFERROR($D$40*2*$D$49,0) -> 0
E53: Eave drip edge cost: | H53: =IFERROR($D$44*$D$50,0) -> 0
E54: Valley cost: | H54: =IFERROR($D$45*$D$51,0) -> 0
E55: Fasteners: | H55: =$D$52 -> 120
E56: ESTIMATED TOTAL: | H56: =IFERROR(CEILING($D$39*$D$40*$D$41*1.1/100,1)*$D$47+$D$43*$D$48+$D$40*2*$D$49+$D$44*$D$50+$D$45*$D$51+$D$52,0) -> 120
A59: 3. LAP SIDING ESTIMATOR (Hardi Hz10 8-1/4")
A60: INPUTS (enter in yellow) | E60: RESULTS (auto)
A61: Gross wall area (sq ft): | D61: 0 | E61: Net siding area (sq ft): | H61: =IFERROR(($D$61-$D$62)*(1+$D$63),0) -> 0
A62: Window/door deduct (sq ft): | D62: 0 | E62: Hardi squares needed: | H62: =IFERROR(CEILING(($D$61-$D$62)*(1+$D$63)/100,1),0) -> 0
A63: Waste factor (%): | D63: 0.1 | E63: Corner boards: | H63: =IFERROR(CEILING($D$64*0.06,1),0) -> 0
A64: Wall perimeter (LF): | D64: 0 | E64: Tyvek rolls: | H64: =IFERROR(CEILING($D$61/1350,1),0) -> 0
E65: Caulk tubes: | H65: =IFERROR(CEILING($D$61/200,1),0) -> 0
A66: Hardi lap / sq: | D66: ='Price Database'!$E$27*100/1000 -> 156.6 | E66: Nail boxes: | H66: =IFERROR(CEILING($D$61/500,1),0) -> 0
A67: Corner board 5/4x4 20' / pc: | D67: ='Price Database'!$E$30*(1.25*4*20/12)/1000 -> 36.100083 | H67: None
A68: Tyvek roll: | D68: 209.99 | E68: Siding cost: | H68: =IFERROR(CEILING(($D$61-$D$62)*(1+$D$63)/100,1)*$D$66,0) -> 0
A69: Caulk tube: | D69: 5.19 | E69: Corner board cost: | H69: =IFERROR(CEILING($D$64*0.06,1)*$D$67,0) -> 0
A70: Siding nail box: | D70: 67.99 | E70: Tyvek cost: | H70: =IFERROR(CEILING($D$61/1350,1)*$D$68,0) -> 0
E71: Caulk cost: | H71: =IFERROR(CEILING($D$61/200,1)*$D$69,0) -> 0
E72: Nails cost: | H72: =IFERROR(CEILING($D$61/500,1)*$D$70,0) -> 0
E73: ESTIMATED TOTAL: | H73: =IFERROR(CEILING(($D$61-$D$62)*(1+$D$63)/100,1)*$D$66+CEILING($D$64*0.06,1)*$D$67+CEILING($D$61/1350,1)*$D$68+CEILING($D$61/200,1)*$D$69+CEILING($D$61/500,1)*$D$70,0) -> 0
A76: 4. BOARD & BATTEN SIDING ESTIMATOR
A77: INPUTS (enter in yellow) | E77: RESULTS (auto)
A78: Gross wall area (sq ft): | D78: 0 | E78: Net wall area (sq ft): | H78: =IFERROR(($D$78-$D$79)*(1+$D$80),0) -> 0
A79: Window/door deduct (sq ft): | D79: 0 | E79: Hardi 4x10 panels: | H79: =IFERROR(CEILING(($D$78-$D$79)*(1+$D$80)/40,1),0) -> 0
A80: Waste factor (%): | D80: 0.1 | E80: Batten LF needed: | H80: =IFERROR(CEILING(($D$78/$D$82*12)*$D$81*(1+$D$80),1),0) -> 0
A81: Wall height (ft): | D81: 9 | E81: Tyvek rolls: | H81: =IFERROR(CEILING($D$78/1350,1),0) -> 0
A82: Batten spacing (in): | D82: 12 | E82: Caulk tubes: | H82: =IFERROR(CEILING($D$78/150,1),0) -> 0
E83: Nail boxes: | H83: =IFERROR(CEILING($D$78/500,1),0) -> 0
A84: Hardi 4x10 panel / sheet: | D84: ='Price Database'!$E$28*40/1000 -> 63.28 | H84: None
A85: 1x3 batten (per LF): | D85: 1.25 | E85: Panel cost: | H85: =IFERROR(CEILING(($D$78-$D$79)*(1+$D$80)/40,1)*$D$84,0) -> 0
A86: Tyvek roll: | D86: 209.99 | E86: Batten cost: | H86: =IFERROR(CEILING(($D$78/$D$82*12)*$D$81*(1+$D$80),1)*$D$85,0) -> 0
A87: Caulk tube: | D87: 5.19 | E87: Tyvek cost: | H87: =IFERROR(CEILING($D$78/1350,1)*$D$86,0) -> 0
A88: Nail box: | D88: 67.99 | E88: Caulk cost: | H88: =IFERROR(CEILING($D$78/150,1)*$D$87,0) -> 0
E89: Nails cost: | H89: =IFERROR(CEILING($D$78/500,1)*$D$88,0) -> 0
E90: ESTIMATED TOTAL: | H90: =IFERROR(CEILING(($D$78-$D$79)*(1+$D$80)/40,1)*$D$84+CEILING(($D$78/$D$82*12)*$D$81*(1+$D$80),1)*$D$85+CEILING($D$78/1350,1)*$D$86+CEILING($D$78/150,1)*$D$87+CEILING($D$78/500,1)*$D$88,0) -> 0

Sheet Price Database
A1: RIDGELINE CONSTRUCTION — MATERIAL PRICE DATABASE
A2: BFS QT# 4269124 | Date: 06-26-2026 | Expires: 07-02-2026 | Location: Woodland WA Yard | BLUE cells = update prices here
A3: # | B3: Description | C3: Item Code | D3: Unit | E3: Unit Price | F3: Old Price | G3: Change % | H3: Notes
A4: DIMENSIONAL LUMBER
A5: 1 | B5: 2X6-16' #2&BTR Douglas Fir | C5: 2616DF2 | D5: MBF | E5: 800 | F5: 657 | G5: 0.21765601 | H5: General framing
A6: 2 | B6: 2X4-16' STD&BTR Douglas Fir | C6: 2416DF | D6: MBF | E6: 745 | F6: 555 | G6: 0.34234234 | H6: General framing
A7: 3 | B7: 2X4-104-5/8" Stud DF PET | C7: 2410458DF | D7: MBF | E7: 739 | F7: 573 | G7: 0.28970332 | H7: Precut stud - 9' wall
A8: 4 | B8: 2X6-104-5/8" Stud DF PET | C8: 2610458DF | D8: MBF | E8: 788 | F8: 681 | G8: 0.15712188 | H8: Precut stud - 9' wall
A9: 5 | B9: 4X10-14' #2 DF GRN | C9: 41014GDF2 | D9: MBF | E9: 999 | F9: 858 | G9: 0.16433566 | H9: Header / beam
A10: SHEATHING & OSB
A11: 6 | B11: 7/16"x4x8 OSB RTD | C11: 716OSB | D11: MSF | E11: 372 | F11: 456 | G11: -0.18421053 | H11: Wall sheathing
A12: 7 | B12: 7/16"x4x9 OSB RTD | C12: 716OSB9 | D12: MSF | E12: 415 | F12: 468 | G12: -0.11324786 | H12: Wall sheathing
A13: 8 | B13: 7/16"x4x10 OSB RTD | C13: 716OSB10 | D13: MSF | E13: 415 | F13: 468 | G13: -0.11324786 | H13: Wall/roof sheathing
A14: 9 | B14: 1-1/8"x4x8 T&G OSB EDGGLD SIF Full Face | C14: 118TGOSBWGOFF | D14: MSF | E14: 1195 | F14: 1294 | G14: -0.076506955 | H14: Subfloor T&G
A15: ENGINEERED LUMBER & I-JOISTS
A16: 10 | B16: 9-1/2 BCI-5000 LF - 2" BC I-Joist | C16: 10BCI5000 | D16: LF | E16: 3.19 | F16: 3.49 | G16: -0.085959885 | H16: Floor joist
A17: 11 | B17: 11-7/8 BCI-5000 LF - 2" BC I-Joist | C17: 12BCI5000 | D17: LF | E17: 3.29 | F17: 3.69 | G17: -0.10840108 | H17: Floor joist
A18: 12 | B18: 5-1/2X11-7/8 Glulam LF 1.8E | C18: 5121178DF18GL | D18: LF | E18: 22.29 | F18: 25.09 | G18: -0.11159825 | H18: Glulam beam
A19: PRESSURE TREATED LUMBER
A20: 13 | B20: 2X6-16' #2 HF TRTD GC ICT Incised Cedartone | C20: 2616HF2TICGC | D20: MBF | E20: 1363 | F20: NEW | G20: NEW ✦ | H20: NEW - Deck ledger/framing
A21: 14 | B21: 2X8-16' #2 HF TRTD GC ICT Incised Cedartone | C21: 2816HF2TICGC | D21: MBF | E21: 1263 | F21: 1232 | G21: 0.025162338 | H21: Deck framing (was PTICGC)
A22: 15 | B22: 4X4-12' #2 HF TRTD Incised CT GC S4S | C22: 4412HF2TICGC | D22: MBF | E22: 1672 | F22: 1643 | G22: 0.017650639 | H22: Deck post
A23: 16 | B23: 6X6-12' #2 HF TRTD Incised CT GC S4S | C23: 6612HF2TICGC | D23: MBF | E23: 1883 | F23: 2173 | G23: -0.13345605 | H23: Deck post/beam
A24: SIDING & TRIM — FIBER CEMENT
A25: 17 | B25: Hardi Trim Board 5/4"x3.5"x12' Rustic Grain | C25: HZU54412RT | D25: MSF | E25: 6009 | F25: 4792 | G25: 0.25396494 | H25: Hardi trim
A26: 18 | B26: Hardi Trim Board 5/4"x5.5"x12' Rustic Grain | C26: HZU54612RT | D26: MSF | E26: 6009 | F26: 4792 | G26: 0.25396494 | H26: Hardi trim
A27: 19 | B27: Hardi Plank Lap Siding 8.25"x12' HZ10 Cedarmill | C27: HZ10814CMSP | D27: MSF | E27: 1566 | F27: 1260 | G27: 0.24285714 | H27: Lap siding
A28: 20 | B28: Hardi Panel 4x8 5/16" Cedarmill | C28: HZ1048CMP | D28: MSF | E28: 1582 | F28: NEW | G28: NEW ✦ | H28: NEW - Panel siding
A29: CYPRESS FJ PRIMED TRIM (NEW)
A30: 21 | B30: 5/4X4-20' Cypress FJ Primed | C30: 540420CYPP | D30: MBF | E30: 4332.01 | F30: NEW | G30: NEW ✦ | H30: NEW - Exterior trim
A31: 22 | B31: 5/4X6-20' Cypress FJ Primed | C31: 540620CYPP | D31: MBF | E31: 4569 | F31: NEW | G31: NEW ✦ | H31: NEW - Exterior trim
A32: 23 | B32: 2X8-20' Cypress FJ Primed | C32: 20820CYPP | D32: MBF | E32: 3909 | F32: NEW | G32: NEW ✦ | H32: NEW - Fascia/trim
A33: 24 | B33: 2X6-20' Cypress FJ Primed | C33: 20620CYPP | D33: MBF | E33: 3843 | F33: NEW | G33: NEW ✦ | H33: NEW - Fascia/trim
A34: 25 | B34: 1X2-20 Cypress TK FJ Primed | C34: 10220CYPP | D34: MBF | E34: 3776.99 | F34: NEW | G34: NEW ✦ | H34: NEW - Small trim
A35: QUOTE TOTAL (QT# 4269124) | E35: 737.15
A37: COLOR KEY: 🔴 Pink = Price INCREASED 🟢 Green = Price DECREASED 🟡 Yellow = NEW item this quote 🔵 Blue text = Update here when prices change
